Workbook
Name All_Currencies_Invested: Dashboard!$D$5:$D$36
Name Date_1: INDEX(Account_Value!$C$3:$C$2001,MATCH(Dashboard!$D$49,Account_Value!$C$3:$C$2001,0)):INDEX(Account_Value!$C$3:$C$2001,MATCH(Dashboard!$D$51,Account_Value!$C$3:$C$2001,0))
Name Date_2: INDEX(Account_Value!$N$3:$N$2001,MATCH(Dashboard!$D$49,Account_Value!$N$3:$N$2001,0)):INDEX(Account_Value!$N$3:$N$2001,MATCH(Dashboard!$D$51,Account_Value!$N$3:$N$2001,0))
Name Date_Market: Calculator!$D:$E
Name ETH_1: INDEX(Account_Value!$J$3:$J$2001,MATCH(Dashboard!$D$49,Account_Value!$I$3:$I$2001,0)):INDEX(Account_Value!$J$3:$J$2001,MATCH(Dashboard!$D$51,Account_Value!$I$3:$I$2001,0))
Name Profit_1: INDEX(Account_Value!$O$3:$O$2001,MATCH(Dashboard!$D$49,Account_Value!$N$3:$N$2001,0)):INDEX(Account_Value!$O$3:$O$2001,MATCH(Dashboard!$D$51,Account_Value!$N$3:$N$2001,0))
Name Values_1: INDEX(Account_Value!$D$3:$D$2001,MATCH(Dashboard!$D$49,Account_Value!$C$3:$C$2001,0)):INDEX(Account_Value!$D$3:$D$2001,MATCH(Dashboard!$D$51,Account_Value!$C$3:$C$2001,0))

Sheet Dashboard
AD2: Navigation
D3: Trade History | P3: Crypto Trading Dashboard v6b | X3: =TODAY() -> 44234
D4: Crypto | F4: Costs | H4: Sales | J4: Fees | L4: Profit | N4: Profit %
D5: =Calculator!$AM2 | F5: =IF($D5="","",Calculator!$AS2) | H5: =IF($D5="","",Calculator!$AT2) | J5: =IF($D5="","",Calculator!$AU2) | L5: =IF($D5="","",Calculator!$BC2) | N5: =IF(Calculator!$BA2="CURRENT","",IF($L5="","",$L5/$F5)) | P5: Current Investments
D6: =Calculator!$AM3 | F6: =IF($D6="","",Calculator!$AS3) | H6: =IF($D6="","",Calculator!$AT3) | J6: =IF($D6="","",Calculator!$AU3) | L6: =IF($D6="","",Calculator!$BC3) | N6: =IF(Calculator!$BA3="CURRENT","",IF($L6="","",$L6/$F6)) | Q6: Purchase | R6: Amount of | S6: Price | T6: Current | V6: Current
D7: =Calculator!$AM4 | F7: =IF($D7="","",Calculator!$AS4) | H7: =IF($D7="","",Calculator!$AT4) | J7: =IF($D7="","",Calculator!$AU4) | L7: =IF($D7="","",Calculator!$BC4) | N7: =IF(Calculator!$BA4="CURRENT","",IF($L7="","",$L7/$F7)) | P7: Currency | Q7: Date | R7: Coins | S7: Paid | T7: Price | U7: Cost | V7: Value | W7: Diff. | X7: % | Y7: 24 hr
D8: =Calculator!$AM5 | F8: =IF($D8="","",Calculator!$AS5) | H8: =IF($D8="","",Calculator!$AT5) | J8: =IF($D8="","",Calculator!$AU5) | L8: =IF($D8="","",Calculator!$BC5) | N8: =IF(Calculator!$BA5="CURRENT","",IF($L8="","",$L8/$F8)) | P8: USD | Q8: 44232 | R8: 0 | V8: =$R$8 -> 0
D9: =Calculator!$AM6 | F9: =IF($D9="","",Calculator!$AS6) | H9: =IF($D9="","",Calculator!$AT6) | J9: =IF($D9="","",Calculator!$AU6) | L9: =IF($D9="","",Calculator!$BC6) | N9: =IF(Calculator!$BA6="CURRENT","",IF($L9="","",$L9/$F9)) | R9: =IFERROR(VLOOKUP($P9,Calculator!$AM$2:$BD$50,12,0),"") | S9: =IFERROR(VLOOKUP($P9,Calculator!$AM$2:$BD$50,6,0),"") | T9: =IFERROR(VLOOKUP($P9,Calculator!$BS$2:$BU$50,3,0),"") | U9: =IFERROR($R9*$S9,"") | V9: =IFERROR($R9*$T9,"") | W9: =IFERROR($V9-$U9, "") | X9: =IFERROR($W9/$U9,"") | Y9: =IFERROR(VLOOKUP($P9,Calculator!$BS$2:$BW$50,5,0),"")
D10: =Calculator!$AM7 | F10: =IF($D10="","",Calculator!$AS7) | H10: =IF($D10="","",Calculator!$AT7) | J10: =IF($D10="","",Calculator!$AU7) | L10: =IF($D10="","",Calculator!$BC7) | N10: =IF(Calculator!$BA7="CURRENT","",IF($L10="","",$L10/$F10)) | R10: =IFERROR(VLOOKUP($P10,Calculator!$AM$2:$BD$50,12,0),"") | S10: =IFERROR(VLOOKUP($P10,Calculator!$AM$2:$BD$50,6,0),"") | T10: =IFERROR(VLOOKUP($P10,Calculator!$BS$2:$BU$50,3,0),"") | U10: =IFERROR($R10*$S10,"") | V10: =IFERROR($R10*$T10,"") | W10: =IFERROR($V10-$U10, "") | X10: =IFERROR($W10/$U10,"") | Y10: =IFERROR(VLOOKUP($P10,Calculator!$BS$2:$BW$50,5,0),"")
D11: =Calculator!$AM8 | F11: =IF($D11="","",Calculator!$AS8) | H11: =IF($D11="","",Calculator!$AT8) | J11: =IF($D11="","",Calculator!$AU8) | L11: =IF($D11="","",Calculator!$BC8) | N11: =IF(Calculator!$BA8="CURRENT","",IF($L11="","",$L11/$F11)) | R11: =IFERROR(VLOOKUP($P11,Calculator!$AM$2:$BD$50,12,0),"") | S11: =IFERROR(VLOOKUP($P11,Calculator!$AM$2:$BD$50,6,0),"") | T11: =IFERROR(VLOOKUP($P11,Calculator!$BS$2:$BU$50,3,0),"") | U11: =IFERROR($R11*$S11,"") | V11: =IFERROR($R11*$T11,"") | W11: =IFERROR($V11-$U11, "") | X11: =IFERROR($W11/$U11,"") | Y11: =IFERROR(VLOOKUP($P11,Calculator!$BS$2:$BW$50,5,0),"")
D12: =Calculator!$AM9 | F12: =IF($D12="","",Calculator!$AS9) | H12: =IF($D12="","",Calculator!$AT9) | J12: =IF($D12="","",Calculator!$AU9) | L12: =IF($D12="","",Calculator!$BC9) | N12: =IF(Calculator!$BA9="CURRENT","",IF($L12="","",$L12/$F12)) | R12: =IFERROR(VLOOKUP($P12,Calculator!$AM$2:$BD$50,12,0),"") | S12: =IFERROR(VLOOKUP($P12,Calculator!$AM$2:$BD$50,6,0),"") | T12: =IFERROR(VLOOKUP($P12,Calculator!$BS$2:$BU$50,3,0),"") | U12: =IFERROR($R12*$S12,"") | V12: =IFERROR($R12*$T12,"") | W12: =IFERROR($V12-$U12, "") | X12: =IFERROR($W12/$U12,"") | Y12: =IFERROR(VLOOKUP($P12,Calculator!$BS$2:$BW$50,5,0),"")
D13: =Calculator!$AM10 | F13: =IF($D13="","",Calculator!$AS10) | H13: =IF($D13="","",Calculator!$AT10) | J13: =IF($D13="","",Calculator!$AU10) | L13: =IF($D13="","",Calculator!$BC10) | N13: =IF(Calculator!$BA10="CURRENT","",IF($L13="","",$L13/$F13)) | R13: =IFERROR(VLOOKUP($P13,Calculator!$AM$2:$BD$50,12,0),"") | S13: =IFERROR(VLOOKUP($P13,Calculator!$AM$2:$BD$50,6,0),"") | T13: =IFERROR(VLOOKUP($P13,Calculator!$BS$2:$BU$50,3,0),"") | U13: =IFERROR($R13*$S13,"") | V13: =IFERROR($R13*$T13,"") | W13: =IFERROR($V13-$U13, "") | X13: =IFERROR($W13/$U13,"") | Y13: =IFERROR(VLOOKUP($P13,Calculator!$BS$2:$BW$50,5,0),"")
D14: =Calculator!$AM11 | F14: =IF($D14="","",Calculator!$AS11) | H14: =IF($D14="","",Calculator!$AT11) | J14: =IF($D14="","",Calculator!$AU11) | L14: =IF($D14="","",Calculator!$BC11) | N14: =IF(Calculator!$BA11="CURRENT","",IF($L14="","",$L14/$F14)) | R14: =IFERROR(VLOOKUP($P14,Calculator!$AM$2:$BD$50,12,0),"") | S14: =IFERROR(VLOOKUP($P14,Calculator!$AM$2:$BD$50,6,0),"") | T14: =IFERROR(VLOOKUP($P14,Calculator!$BS$2:$BU$50,3,0),"") | U14: =IFERROR($R14*$S14,"") | V14: =IFERROR($R14*$T14,"") | W14: =IFERROR($V14-$U14, "") | X14: =IFERROR($W14/$U14,"") | Y14: =IFERROR(VLOOKUP($P14,Calculator!$BS$2:$BW$50,5,0),"")
D15: =Calculator!$AM12 | F15: =IF($D15="","",Calculator!$AS12) | H15: =IF($D15="","",Calculator!$AT12) | J15: =IF($D15="","",Calculator!$AU12) | L15: =IF($D15="","",Calculator!$BC12) | N15: =IF(Calculator!$BA12="CURRENT","",IF($L15="","",$L15/$F15)) | R15: =IFERROR(VLOOKUP($P15,Calculator!$AM$2:$BD$50,12,0),"") | S15: =IFERROR(VLOOKUP($P15,Calculator!$AM$2:$BD$50,6,0),"") | T15: =IFERROR(VLOOKUP($P15,Calculator!$BS$2:$BU$50,3,0),"") | U15: =IFERROR($R15*$S15,"") | V15: =IFERROR($R15*$T15,"") | W15: =IFERROR($V15-$U15, "") | X15: =IFERROR($W15/$U15,"") | Y15: =IFERROR(VLOOKUP($P15,Calculator!$BS$2:$BW$50,5,0),"")
D16: =Calculator!$AM13 | F16: =IF($D16="","",Calculator!$AS13) | H16: =IF($D16="","",Calculator!$AT13) | J16: =IF($D16="","",Calculator!$AU13) | L16: =IF($D16="","",Calculator!$BC13) | N16: =IF(Calculator!$BA13="CURRENT","",IF($L16="","",$L16/$F16)) | R16: =IFERROR(VLOOKUP($P16,Calculator!$AM$2:$BD$50,12,0),"") | S16: =IFERROR(VLOOKUP($P16,Calculator!$AM$2:$BD$50,6,0),"") | T16: =IFERROR(VLOOKUP($P16,Calculator!$BS$2:$BU$50,3,0),"") | U16: =IFERROR($R16*$S16,"") | V16: =IFERROR($R16*$T16,"") | W16: =IFERROR($V16-$U16, "") | X16: =IFERROR($W16/$U16,"") | Y16: =IFERROR(VLOOKUP($P16,Calculator!$BS$2:$BW$50,5,0),"")
D17: =Calculator!$AM14 | F17: =IF($D17="","",Calculator!$AS14) | H17: =IF($D17="","",Calculator!$AT14) | J17: =IF($D17="","",Calculator!$AU14) | L17: =IF($D17="","",Calculator!$BC14) | N17: =IF(Calculator!$BA14="CURRENT","",IF($L17="","",$L17/$F17)) | R17: =IFERROR(VLOOKUP($P17,Calculator!$AM$2:$BD$50,12,0),"") | S17: =IFERROR(VLOOKUP($P17,Calculator!$AM$2:$BD$50,6,0),"") | T17: =IFERROR(VLOOKUP($P17,Calculator!$BS$2:$BU$50,3,0),"") | U17: =IFERROR($R17*$S17,"") | V17: =IFERROR($R17*$T17,"") | W17: =IFERROR($V17-$U17, "") | X17: =IFERROR($W17/$U17,"") | Y17: =IFERROR(VLOOKUP($P17,Calculator!$BS$2:$BW$50,5,0),"")
D18: =Calculator!$AM15 | F18: =IF($D18="","",Calculator!$AS15) | H18: =IF($D18="","",Calculator!$AT15) | J18: =IF($D18="","",Calculator!$AU15) | L18: =IF($D18="","",Calculator!$BC15) | N18: =IF(Calculator!$BA15="CURRENT","",IF($L18="","",$L18/$F18)) | R18: =IFERROR(VLOOKUP($P18,Calculator!$AM$2:$BD$50,12,0),"") | S18: =IFERROR(VLOOKUP($P18,Calculator!$AM$2:$BD$50,6,0),"") | T18: =IFERROR(VLOOKUP($P18,Calculator!$BS$2:$BU$50,3,0),"") | U18: =IFERROR($R18*$S18,"") | V18: =IFERROR($R18*$T18,"") | W18: =IFERROR($V18-$U18, "") | X18: =IFERROR($W18/$U18,"") | Y18: =IFERROR(VLOOKUP($P18,Calculator!$BS$2:$BW$50,5,0),"")
D19: =Calculator!$AM16 | F19: =IF($D19="","",Calculator!$AS16) | H19: =IF($D19="","",Calculator!$AT16) | J19: =IF($D19="","",Calculator!$AU16) | L19: =IF($D19="","",Calculator!$BC16) | N19: =IF(Calculator!$BA16="CURRENT","",IF($L19="","",$L19/$F19)) | P19: ETH | R19: =Calculator!$BQ$2 -> 0 | T19: =IFERROR(VLOOKUP($P19,Calculator!$BS$2:$BU$50,3,0),"") -> 1624.07 | V19: =IFERROR($R19*$T19,"") -> 0 | Y19: =IFERROR(VLOOKUP($P19,Calculator!$BS$2:$BW$50,5,0),"") -> -0.033941456
D20: =Calculator!$AM17 | F20: =IF($D20="","",Calculator!$AS17) | H20: =IF($D20="","",Calculator!$AT17) | J20: =IF($D20="","",Calculator!$AU17) | L20: =IF($D20="","",Calculator!$BC17) | N20: =IF(Calculator!$BA17="CURRENT","",IF($L20="","",$L20/$F20)) | R20: Cash | S20: ETH
D21: =Calculator!$AM18 | F21: =IF($D21="","",Calculator!$AS18) | H21: =IF($D21="","",Calculator!$AT18) | J21: =IF($D21="","",Calculator!$AU18) | L21: =IF($D21="","",Calculator!$BC18) | N21: =IF(Calculator!$BA18="CURRENT","",IF($L21="","",$L21/$F21)) | Q21: Account Deposits: | R21: =SUM(Account_Value!$E:$E) -> 0 | S21: =$Y$34 -> 0 | V21: Investment Data
D22: =Calculator!$AM19 | F22: =IF($D22="","",Calculator!$AS19) | H22: =IF($D22="","",Calculator!$AT19) | J22: =IF($D22="","",Calculator!$AU19) | L22: =IF($D22="","",Calculator!$BC19) | N22: =IF(Calculator!$BA19="CURRENT","",IF($L22="","",$L22/$F22)) | X22: Number of Transactions | Y22: =Calculator!$BN$2 -> 4.9515947e-14
D23: =Calculator!$AM20 | F23: =IF($D23="","",Calculator!$AS20) | H23: =IF($D23="","",Calculator!$AT20) | J23: =IF($D23="","",Calculator!$AU20) | L23: =IF($D23="","",Calculator!$BC20) | N23: =IF(Calculator!$BA20="CURRENT","",IF($L23="","",$L23/$F23)) | Q23: Account Value: | R23: =SUM(V8:V19) -> 0 | X23: from | Y23: =MIN(Calculator!$C:$C) -> 0
D24: =Calculator!$AM21 | F24: =IF($D24="","",Calculator!$AS21) | H24: =IF($D24="","",Calculator!$AT21) | J24: =IF($D24="","",Calculator!$AU21) | L24: =IF($D24="","",Calculator!$BC21) | N24: =IF(Calculator!$BA21="CURRENT","",IF($L24="","",$L24/$F24)) | X24: to | Y24: =MAX(Calculator!$C:$C) -> 0
D25: =Calculator!$AM22 | F25: =IF($D25="","",Calculator!$AS22) | H25: =IF($D25="","",Calculator!$AT22) | J25: =IF($D25="","",Calculator!$AU22) | L25: =IF($D25="","",Calculator!$BC22) | N25: =IF(Calculator!$BA22="CURRENT","",IF($L25="","",$L25/$F25)) | Q25: Account Gain/Loss: | R25: =$R$23-$R$21 -> 0 | S25: =IFERROR($R$25/$R$21,"") | X25: Cost of Sales | Y25: =IFERROR(Calculator!$BK$2,"$0") -> 0
D26: =Calculator!$AM23 | F26: =IF($D26="","",Calculator!$AS23) | H26: =IF($D26="","",Calculator!$AT23) | J26: =IF($D26="","",Calculator!$AU23) | L26: =IF($D26="","",Calculator!$BC23) | N26: =IF(Calculator!$BA23="CURRENT","",IF($L26="","",$L26/$F26)) | X26: Total Sales | Y26: =Calculator!$BJ$2 -> 0
D27: =Calculator!$AM24 | F27: =IF($D27="","",Calculator!$AS24) | H27: =IF($D27="","",Calculator!$AT24) | J27: =IF($D27="","",Calculator!$AU24) | L27: =IF($D27="","",Calculator!$BC24) | N27: =IF(Calculator!$BA24="CURRENT","",IF($L27="","",$L27/$F27)) | X27: Binance Fees | Y27: =Calculator!$BM$2 -> 0
D28: =Calculator!$AM25 | F28: =IF($D28="","",Calculator!$AS25) | H28: =IF($D28="","",Calculator!$AT25) | J28: =IF($D28="","",Calculator!$AU25) | L28: =IF($D28="","",Calculator!$BC25) | N28: =IF(Calculator!$BA25="CURRENT","",IF($L28="","",$L28/$F28)) | X28: Profit from Sales | Y28: =Calculator!$BL$2 -> 0
D29: =Calculator!$AM26 | F29: =IF($D29="","",Calculator!$AS26) | H29: =IF($D29="","",Calculator!$AT26) | J29: =IF($D29="","",Calculator!$AU26) | L29: =IF($D29="","",Calculator!$BC26) | N29: =IF(Calculator!$BA26="CURRENT","",IF($L29="","",$L29/$F29))
D30: =Calculator!$AM27 | F30: =IF($D30="","",Calculator!$AS27) | H30: =IF($D30="","",Calculator!$AT27) | J30: =IF($D30="","",Calculator!$AU27) | L30: =IF($D30="","",Calculator!$BC27) | N30: =IF(Calculator!$BA27="CURRENT","",IF($L30="","",$L30/$F30)) | V30: Ethereum Mining
D31: =Calculator!$AM28 | F31: =IF($D31="","",Calculator!$AS28) | H31: =IF($D31="","",Calculator!$AT28) | J31: =IF($D31="","",Calculator!$AU28) | L31: =IF($D31="","",Calculator!$BC28) | N31: =IF(Calculator!$BA28="CURRENT","",IF($L31="","",$L31/$F31)) | X31: Number of Deposits | Y31: =Calculator!$BO$2 -> 0
D32: =Calculator!$AM29 | F32: =IF($D32="","",Calculator!$AS29) | H32: =IF($D32="","",Calculator!$AT29) | J32: =IF($D32="","",Calculator!$AU29) | L32: =IF($D32="","",Calculator!$BC29) | N32: =IF(Calculator!$BA29="CURRENT","",IF($L32="","",$L32/$F32)) | X32: from | Y32: =MIN(Calculator!$V:$V) -> 0
D33: =Calculator!$AM30 | F33: =IF($D33="","",Calculator!$AS30) | H33: =IF($D33="","",Calculator!$AT30) | J33: =IF($D33="","",Calculator!$AU30) | L33: =IF($D33="","",Calculator!$BC30) | N33: =IF(Calculator!$BA30="CURRENT","",IF($L33="","",$L33/$F33)) | X33: to | Y33: =MAX(Calculator!$V:$V) -> 0
D34: =Calculator!$AM31 | F34: =IF($D34="","",Calculator!$AS31) | H34: =IF($D34="","",Calculator!$AT31) | J34: =IF($D34="","",Calculator!$AU31) | L34: =IF($D34="","",Calculator!$BC31) | N34: =IF(Calculator!$BA31="CURRENT","",IF($L34="","",$L34/$F34)) | X34: All ETH Mined | Y34: =SUM(Calculator!$CB:$CB) -> 0
D35: =Calculator!$AM32 | F35: =IF($D35="","",Calculator!$AS32) | H35: =IF($D35="","",Calculator!$AT32) | J35: =IF($D35="","",Calculator!$AU32) | L35: =IF($D35="","",Calculator!$BC32) | N35: =IF(Calculator!$BA32="CURRENT","",IF($L35="","",$L35/$F35)) | X35: Current ETH Value | Y35: =$V$19 -> 0
D36: =Calculator!$AM33 | F36: =IF($D36="","",Calculator!$AS33) | H36: =IF($D36="","",Calculator!$AT33) | J36: =IF($D36="","",Calculator!$AU33) | L36: =IF($D36="","",Calculator!$BC33) | N36: =IF(Calculator!$BA33="CURRENT","",IF($L36="","",$L36/$F36))
D46: Select Date Range
D47: for Charts
D48: From
D49: 44197
D50: To
D51: 44282

Sheet Account_Value
B2: Days | C2: Date | D2: Account Value | E2: Cash Deposits | F2: ETH_Price | G2: ETH Deposits | H2: ETH_Dep_copy | I2: Date_3 | J2: Mined_Value | K2: Ttl_ETH_Value | L2: Ttl_Acct_Value | M2: Gain_Loss | N2: Date_2 | O2: Percent Profit
B3: 1 | C3: 44061 | G3: =IFERROR(VLOOKUP($C3,Calculator!$BY$2:$CB$2500,4,0),"") | H3: =$G3*1 -> #VALUE! | I3: =$C3 -> 44061 | J3: =IF($C3>(TODAY()),NA(),SUM($G$3:$G3)) -> 0 | K3: =IFERROR(VLOOKUP($C3,Calculator!$BY$2:$CD$2500,6,0),"") | L3: =IF($D3="","",$D3) | M3: =IF($D3="","",$L3-(Dashboard!$R$21-(SUM($E4:$E$224)))) | N3: 44061 | O3: =IF($D3="",NA(),($M3)/Dashboard!$R$21) -> #N/A
B4: =$B3+1 -> 2 | C4: =$C3+1 -> 44062 | G4: =IFERROR(VLOOKUP($C4,Calculator!$BY$2:$CB$2500,4,0),"") | H4: =$G4*1 -> #VALUE! | I4: =$C4 -> 44062 | J4: =IF($C4>(TODAY()),NA(),SUM($G$3:$G4)) -> 0 | K4: =IFERROR(VLOOKUP($C4,Calculator!$BY$2:$CD$2500,6,0),"") | L4: =IF($D4="","",$D4) | M4: =IF($D4="","",$L4-(Dashboard!$R$21-(SUM($E5:$E$224)))) | N4: =$C3+1 -> 44062 | O4: =IF($D4="",NA(),($M4)/Dashboard!$R$21) -> #N/A
B5: =$B4+1 -> 3 | C5: =$C4+1 -> 44063 | G5: =IFERROR(VLOOKUP($C5,Calculator!$BY$2:$CB$2500,4,0),"") | H5: =$G5*1 -> #VALUE! | I5: =$C5 -> 44063 | J5: =IF($C5>(TODAY()),NA(),SUM($G$3:$G5)) -> 0 | K5: =IFERROR(VLOOKUP($C5,Calculator!$BY$2:$CD$2500,6,0),"") | L5: =IF($D5="","",$D5) | M5: =IF($D5="","",$L5-(Dashboard!$R$21-(SUM($E6:$E$224)))) | N5: =$C4+1 -> 44063 | O5: =IF($D5="",NA(),($M5)/Dashboard!$R$21) -> #N/A
B6: =$B5+1 -> 4 | C6: =$C5+1 -> 44064 | G6: =IFERROR(VLOOKUP($C6,Calculator!$BY$2:$CB$2500,4,0),"") | H6: =$G6*1 -> #VALUE! | I6: =$C6 -> 44064 | J6: =IF($C6>(TODAY()),NA(),SUM($G$3:$G6)) -> 0 | K6: =IFERROR(VLOOKUP($C6,Calculator!$BY$2:$CD$2500,6,0),"") | L6: =IF($D6="","",$D6) | M6: =IF($D6="","",$L6-(Dashboard!$R$21-(SUM($E7:$E$224)))) | N6: =$C5+1 -> 44064 | O6: =IF($D6="",NA(),($M6)/Dashboard!$R$21) -> #N/A
B7: =$B6+1 -> 5 | C7: =$C6+1 -> 44065 | G7: =IFERROR(VLOOKUP($C7,Calculator!$BY$2:$CB$2500,4,0),"") | H7: =$G7*1 -> #VALUE! | I7: =$C7 -> 44065 | J7: =IF($C7>(TODAY()),NA(),SUM($G$3:$G7)) -> 0 | K7: =IFERROR(VLOOKUP($C7,Calculator!$BY$2:$CD$2500,6,0),"") | L7: =IF($D7="","",$D7) | M7: =IF($D7="","",$L7-(Dashboard!$R$21-(SUM($E8:$E$224)))) | N7: =$C6+1 -> 44065 | O7: =IF($D7="",NA(),($M7)/Dashboard!$R$21) -> #N/A
B8: =$B7+1 -> 6 | C8: =$C7+1 -> 44066 | G8: =IFERROR(VLOOKUP($C8,Calculator!$BY$2:$CB$2500,4,0),"") | H8: =$G8*1 -> #VALUE! | I8: =$C8 -> 44066 | J8: =IF($C8>(TODAY()),NA(),SUM($G$3:$G8)) -> 0 | K8: =IFERROR(VLOOKUP($C8,Calculator!$BY$2:$CD$2500,6,0),"") | L8: =IF($D8="","",$D8) | M8: =IF($D8="","",$L8-(Dashboard!$R$21-(SUM($E9:$E$224)))) | N8: =$C7+1 -> 44066 | O8: =IF($D8="",NA(),($M8)/Dashboard!$R$21) -> #N/A
B9: =$B8+1 -> 7 | C9: =$C8+1 -> 44067 | G9: =IFERROR(VLOOKUP($C9,Calculator!$BY$2:$CB$2500,4,0),"") | H9: =$G9*1 -> #VALUE! | I9: =$C9 -> 44067 | J9: =IF($C9>(TODAY()),NA(),SUM($G$3:$G9)) -> 0 | K9: =IFERROR(VLOOKUP($C9,Calculator!$BY$2:$CD$2500,6,0),"") | L9: =IF($D9="","",$D9) | M9: =IF($D9="","",$L9-(Dashboard!$R$21-(SUM($E10:$E$224)))) | N9: =$C8+1 -> 44067 | O9: =IF($D9="",NA(),($M9)/Dashboard!$R$21) -> #N/A
B10: =$B9+1 -> 8 | C10: =$C9+1 -> 44068 | G10: =IFERROR(VLOOKUP($C10,Calculator!$BY$2:$CB$2500,4,0),"") | H10: =$G10*1 -> #VALUE! | I10: =$C10 -> 44068 | J10: =IF($C10>(TODAY()),NA(),SUM($G$3:$G10)) -> 0 | K10: =IFERROR(VLOOKUP($C10,Calculator!$BY$2:$CD$2500,6,0),"") | L10: =IF($D10="","",$D10) | M10: =IF($D10="","",$L10-(Dashboard!$R$21-(SUM($E11:$E$224)))) | N10: =$C9+1 -> 44068 | O10: =IF($D10="",NA(),($M10)/Dashboard!$R$21) -> #N/A
B11: =$B10+1 -> 9 | C11: =$C10+1 -> 44069 | G11: =IFERROR(VLOOKUP($C11,Calculator!$BY$2:$CB$2500,4,0),"") | H11: =$G11*1 -> #VALUE! | I11: =$C11 -> 44069 | J11: =IF($C11>(TODAY()),NA(),SUM($G$3:$G11)) -> 0 | K11: =IFERROR(VLOOKUP($C11,Calculator!$BY$2:$CD$2500,6,0),"") | L11: =IF($D11="","",$D11) | M11: =IF($D11="","",$L11-(Dashboard!$R$21-(SUM($E12:$E$224)))) | N11: =$C10+1 -> 44069 | O11: =IF($D11="",NA(),($M11)/Dashboard!$R$21) -> #N/A
B12: =$B11+1 -> 10 | C12: =$C11+1 -> 44070 | G12: =IFERROR(VLOOKUP($C12,Calculator!$BY$2:$CB$2500,4,0),"") | H12: =$G12*1 -> #VALUE! | I12: =$C12 -> 44070 | J12: =IF($C12>(TODAY()),NA(),SUM($G$3:$G12)) -> 0 | K12: =IFERROR(VLOOKUP($C12,Calculator!$BY$2:$CD$2500,6,0),"") | L12: =IF($D12="","",$D12) | M12: =IF($D12="","",$L12-(Dashboard!$R$21-(SUM($E13:$E$224)))) | N12: =$C11+1 -> 44070 | O12: =IF($D12="",NA(),($M12)/Dashboard!$R$21) -> #N/A
B13: =$B12+1 -> 11 | C13: =$C12+1 -> 44071 | G13: =IFERROR(VLOOKUP($C13,Calculator!$BY$2:$CB$2500,4,0),"") | H13: =$G13*1 -> #VALUE! | I13: =$C13 -> 44071 | J13: =IF($C13>(TODAY()),NA(),SUM($G$3:$G13)) -> 0 | K13: =IFERROR(VLOOKUP($C13,Calculator!$BY$2:$CD$2500,6,0),"") | L13: =IF($D13="","",$D13) | M13: =IF($D13="","",$L13-(Dashboard!$R$21-(SUM($E14:$E$224)))) | N13: =$C12+1 -> 44071 | O13: =IF($D13="",NA(),($M13)/Dashboard!$R$21) -> #N/A
B14: =$B13+1 -> 12 | C14: =$C13+1 -> 44072 | G14: =IFERROR(VLOOKUP($C14,Calculator!$BY$2:$CB$2500,4,0),"") | H14: =$G14*1 -> #VALUE! | I14: =$C14 -> 44072 | J14: =IF($C14>(TODAY()),NA(),SUM($G$3:$G14)) -> 0 | K14: =IFERROR(VLOOKUP($C14,Calculator!$BY$2:$CD$2500,6,0),"") | L14: =IF($D14="","",$D14) | M14: =IF($D14="","",$L14-(Dashboard!$R$21-(SUM($E15:$E$224)))) | N14: =$C13+1 -> 44072 | O14: =IF($D14="",NA(),($M14)/Dashboard!$R$21) -> #N/A
B15: =$B14+1 -> 13 | C15: =$C14+1 -> 44073 | G15: =IFERROR(VLOOKUP($C15,Calculator!$BY$2:$CB$2500,4,0),"") | H15: =$G15*1 -> #VALUE! | I15: =$C15 -> 44073 | J15: =IF($C15>(TODAY()),NA(),SUM($G$3:$G15)) -> 0 | K15: =IFERROR(VLOOKUP($C15,Calculator!$BY$2:$CD$2500,6,0),"") | L15: =IF($D15="","",$D15) | M15: =IF($D15="","",$L15-(Dashboard!$R$21-(SUM($E16:$E$224)))) | N15: =$C14+1 -> 44073 | O15: =IF($D15="",NA(),($M15)/Dashboard!$R$21) -> #N/A
... B116: =$B115+1 -> 114 | C116: =$C115+1 -> 44174 | G116: =IFERROR(VLOOKUP($C116,Calculator!$BY$2:$CB$2500,4,0),"") | H116: =$G116*1 -> #VALUE! | I116: =$C116 -> 44174 | J116: =IF($C116>(TODAY()),NA(),SUM($G$3:$G116)) -> 0 | K116: =IFERROR(VLOOKUP($C116,Calculator!$BY$2:$CD$2500,6,0),"") | L116: =IF($D116="","",$D116) | M116: =IF($D116="","",$L116-(Dashboard!$R$21-(SUM($E117:$E$224)))) | N116: =$C115+1 -> 44174 | O116: =IF($D116="",NA(),($M116)/Dashboard!$R$21) -> #N/A
B117: =$B116+1 -> 115 | C117: =$C116+1 -> 44175 | F117: 559.68 | G117: =IFERROR(VLOOKUP($C117,Calculator!$BY$2:$CB$2500,4,0),"") | H117: =$G117*1 -> #VALUE! | I117: =$C117 -> 44175 | J117: =IF($C117>(TODAY()),NA(),SUM($G$3:$G117)) -> 0 | K117: =IFERROR(VLOOKUP($C117,Calculator!$BY$2:$CD$2500,6,0),"") | L117: =IF($D117="","",$D117) | M117: =IF($D117="","",$L117-(Dashboard!$R$21-(SUM($E118:$E$224)))) | N117: =$C116+1 -> 44175 | O117: =IF($D117="",NA(),($M117)/Dashboard!$R$21) -> #N/A
B118: =$B117+1 -> 116 | C118: =$C117+1 -> 44176 | G118: =IFERROR(VLOOKUP($C118,Calculator!$BY$2:$CB$2500,4,0),"") | H118: =$G118*1 -> #VALUE! | I118: =$C118 -> 44176 | J118: =IF($C118>(TODAY()),NA(),SUM($G$3:$G118)) -> 0 | K118: =IFERROR(VLOOKUP($C118,Calculator!$BY$2:$CD$2500,6,0),"") | L118: =IF($D118="","",$D118) | M118: =IF($D118="","",$L118-(Dashboard!$R$21-(SUM($E119:$E$224)))) | N118: =$C117+1 -> 44176 | O118: =IF($D118="",NA(),($M118)/Dashboard!$R$21) -> #N/A
B119: =$B118+1 -> 117 | C119: =$C118+1 -> 44177 | G119: =IFERROR(VLOOKUP($C119,Calculator!$BY$2:$CB$2500,4,0),"") | H119: =$G119*1 -> #VALUE! | I119: =$C119 -> 44177 | J119: =IF($C119>(TODAY()),NA(),SUM($G$3:$G119)) -> 0 | K119: =IFERROR(VLOOKUP($C119,Calculator!$BY$2:$CD$2500,6,0),"") | L119: =IF($D119="","",$D119) | M119: =IF($D119="","",$L119-(Dashboard!$R$21-(SUM($E120:$E$224)))) | N119: =$C118+1 -> 44177 | O119: =IF($D119="",NA(),($M119)/Dashboard!$R$21) -> #N/A
B120: =$B119+1 -> 118 | C120: =$C119+1 -> 44178 | G120: =IFERROR(VLOOKUP($C120,Calculator!$BY$2:$CB$2500,4,0),"") | H120: =$G120*1 -> #VALUE! | I120: =$C120 -> 44178 | J120: =IF($C120>(TODAY()),NA(),SUM($G$3:$G120)) -> 0 | K120: =IFERROR(VLOOKUP($C120,Calculator!$BY$2:$CD$2500,6,0),"") | L120: =IF($D120="","",$D120) | M120: =IF($D120="","",$L120-(Dashboard!$R$21-(SUM($E121:$E$224)))) | N120: =$C119+1 -> 44178 | O120: =IF($D120="",NA(),($M120)/Dashboard!$R$21) -> #N/A
B121: =$B120+1 -> 119 | C121: =$C120+1 -> 44179 | G121: =IFERROR(VLOOKUP($C121,Calculator!$BY$2:$CB$2500,4,0),"") | H121: =$G121*1 -> #VALUE! | I121: =$C121 -> 44179 | J121: =IF($C121>(TODAY()),NA(),SUM($G$3:$G121)) -> 0 | K121: =IFERROR(VLOOKUP($C121,Calculator!$BY$2:$CD$2500,6,0),"") | L121: =IF($D121="","",$D121) | M121: =IF($D121="","",$L121-(Dashboard!$R$21-(SUM($E122:$E$224)))) | N121: =$C120+1 -> 44179 | O121: =IF($D121="",NA(),($M121)/Dashboard!$R$21) -> #N/A
B122: =$B121+1 -> 120 | C122: =$C121+1 -> 44180 | G122: =IFERROR(VLOOKUP($C122,Calculator!$BY$2:$CB$2500,4,0),"") | H122: =$G122*1 -> #VALUE! | I122: =$C122 -> 44180 | J122: =IF($C122>(TODAY()),NA(),SUM($G$3:$G122)) -> 0 | K122: =IFERROR(VLOOKUP($C122,Calculator!$BY$2:$CD$2500,6,0),"") | L122: =IF($D122="","",$D122) | M122: =IF($D122="","",$L122-(Dashboard!$R$21-(SUM($E123:$E$224)))) | N122: =$C121+1 -> 44180 | O122: =IF($D122="",NA(),($M122)/Dashboard!$R$21) -> #N/A
B123: =$B122+1 -> 121 | C123: =$C122+1 -> 44181 | G123: =IFERROR(VLOOKUP($C123,Calculator!$BY$2:$CB$2500,4,0),"") | H123: =$G123*1 -> #VALUE! | I123: =$C123 -> 44181 | J123: =IF($C123>(TODAY()),NA(),SUM($G$3:$G123)) -> 0 | K123: =IFERROR(VLOOKUP($C123,Calculator!$BY$2:$CD$2500,6,0),"") | L123: =IF($D123="","",$D123) | M123: =IF($D123="","",$L123-(Dashboard!$R$21-(SUM($E124:$E$224)))) | N123: =$C122+1 -> 44181 | O123: =IF($D123="",NA(),($M123)/Dashboard!$R$21) -> #N/A
B124: =$B123+1 -> 122 | C124: =$C123+1 -> 44182 | G124: =IFERROR(VLOOKUP($C124,Calculator!$BY$2:$CB$2500,4,0),"") | H124: =$G124*1 -> #VALUE! | I124: =$C124 -> 44182 | J124: =IF($C124>(TODAY()),NA(),SUM($G$3:$G124)) -> 0 | K124: =IFERROR(VLOOKUP($C124,Calculator!$BY$2:$CD$2500,6,0),"") | L124: =IF($D124="","",$D124) | M124: =IF($D124="","",$L124-(Dashboard!$R$21-(SUM($E125:$E$224)))) | N124: =$C123+1 -> 44182 | O124: =IF($D124="",NA(),($M124)/Dashboard!$R$21) -> #N/A
B125: =$B124+1 -> 123 | C125: =$C124+1 -> 44183 | G125: =IFERROR(VLOOKUP($C125,Calculator!$BY$2:$CB$2500,4,0),"") | H125: =$G125*1 -> #VALUE! | I125: =$C125 -> 44183 | J125: =IF($C125>(TODAY()),NA(),SUM($G$3:$G125)) -> 0 | K125: =IFERROR(VLOOKUP($C125,Calculator!$BY$2:$CD$2500,6,0),"") | L125: =IF($D125="","",$D125) | M125: =IF($D125="","",$L125-(Dashboard!$R$21-(SUM($E126:$E$224)))) | N125: =$C124+1 -> 44183 | O125: =IF($D125="",NA(),($M125)/Dashboard!$R$21) -> #N/A
B126: =$B125+1 -> 124 | C126: =$C125+1 -> 44184 | G126: =IFERROR(VLOOKUP($C126,Calculator!$BY$2:$CB$2500,4,0),"") | H126: =$G126*1 -> #VALUE! | I126: =$C126 -> 44184 | J126: =IF($C126>(TODAY()),NA(),SUM($G$3:$G126)) -> 0 | K126: =IFERROR(VLOOKUP($C126,Calculator!$BY$2:$CD$2500,6,0),"") | L126: =IF($D126="","",$D126) | M126: =IF($D126="","",$L126-(Dashboard!$R$21-(SUM($E127:$E$224)))) | N126: =$C125+1 -> 44184 | O126: =IF($D126="",NA(),($M126)/Dashboard!$R$21) -> #N/A
B127: =$B126+1 -> 125 | C127: =$C126+1 -> 44185 | G127: =IFERROR(VLOOKUP($C127,Calculator!$BY$2:$CB$2500,4,0),"") | H127: =$G127*1 -> #VALUE! | I127: =$C127 -> 44185 | J127: =IF($C127>(TODAY()),NA(),SUM($G$3:$G127)) -> 0 | K127: =IFERROR(VLOOKUP($C127,Calculator!$BY$2:$CD$2500,6,0),"") | L127: =IF($D127="","",$D127) | M127: =IF($D127="","",$L127-(Dashboard!$R$21-(SUM($E128:$E$224)))) | N127: =$C126+1 -> 44185 | O127: =IF($D127="",NA(),($M127)/Dashboard!$R$21) -> #N/A
B128: =$B127+1 -> 126 | C128: =$C127+1 -> 44186 | G128: =IFERROR(VLOOKUP($C128,Calculator!$BY$2:$CB$2500,4,0),"") | H128: =$G128*1 -> #VALUE! | I128: =$C128 -> 44186 | J128: =IF($C128>(TODAY()),NA(),SUM($G$3:$G128)) -> 0 | K128: =IFERROR(VLOOKUP($C128,Calculator!$BY$2:$CD$2500,6,0),"") | L128: =IF($D128="","",$D128) | M128: =IF($D128="","",$L128-(Dashboard!$R$21-(SUM($E129:$E$224)))) | N128: =$C127+1 -> 44186 | O128: =IF($D128="",NA(),($M128)/Dashboard!$R$21) -> #N/A
B129: =$B128+1 -> 127 | C129: =$C128+1 -> 44187 | G129: =IFERROR(VLOOKUP($C129,Calculator!$BY$2:$CB$2500,4,0),"") | H129: =$G129*1 -> #VALUE! | I129: =$C129 -> 44187 | J129: =IF($C129>(TODAY()),NA(),SUM($G$3:$G129)) -> 0 | K129: =IFERROR(VLOOKUP($C129,Calculator!$BY$2:$CD$2500,6,0),"") | L129: =IF($D129="","",$D129) | M129: =IF($D129="","",$L129-(Dashboard!$R$21-(SUM($E130:$E$224)))) | N129: =$C128+1 -> 44187 | O129: =IF($D129="",NA(),($M129)/Dashboard!$R$21) -> #N/A
... B223: =$B222+1 -> 221 | C223: =$C222+1 -> 44281 | G223: =IFERROR(VLOOKUP($C223,Calculator!$BY$2:$CB$2500,4,0),"") | H223: =$G223*1 -> #VALUE! | I223: =$C223 -> 44281 | J223: =IF($C223>(TODAY()),NA(),SUM($G$3:$G223)) -> #N/A | K223: =IFERROR(VLOOKUP($C223,Calculator!$BY$2:$CD$2500,6,0),"") | L223: =IF($D223="","",$D223) | M223: =IF($D223="","",$L223-(Dashboard!$R$21-(SUM($E224:$E$224)))) | N223: =$C222+1 -> 44281 | O223: =IF($D223="",NA(),($M223)/Dashboard!$R$21) -> #N/A
B224: =$B223+1 -> 222 | C224: =$C223+1 -> 44282 | G224: =IFERROR(VLOOKUP($C224,Calculator!$BY$2:$CB$2500,4,0),"") | H224: =$G224*1 -> #VALUE! | I224: =$C224 -> 44282 | J224: =IF($C224>(TODAY()),NA(),SUM($G$3:$G224)) -> #N/A | K224: =IFERROR(VLOOKUP($C224,Calculator!$BY$2:$CD$2500,6,0),"") | L224: =IF($D224="","",$D224) | M224: =IF($D224="","",$L224-(Dashboard!$R$21-(SUM($E$224:$E225)))) | N224: =$C223+1 -> 44282 | O224: =IF($D224="",NA(),($M224)/Dashboard!$R$21) -> #N/A
B225: =$B224+1 -> 223 | C225: =$C224+1 -> 44283 | G225: =IFERROR(VLOOKUP($C225,Calculator!$BY$2:$CB$2500,4,0),"") | H225: =$G225*1 -> #VALUE! | I225: =$C225 -> 44283 | J225: =IF($C225>(TODAY()),NA(),SUM($G$3:$G225)) -> #N/A | K225: =IFERROR(VLOOKUP($C225,Calculator!$BY$2:$CD$2500,6,0),"") | L225: =IF($D225="","",$D225) | M225: =IF($D225="","",$L225-(Dashboard!$R$21-(SUM($E$224:$E226)))) | N225: =$C224+1 -> 44283 | O225: =IF($D225="",NA(),($M225)/Dashboard!$R$21) -> #N/A
B226: =$B225+1 -> 224 | C226: =$C225+1 -> 44284 | G226: =IFERROR(VLOOKUP($C226,Calculator!$BY$2:$CB$2500,4,0),"") | H226: =$G226*1 -> #VALUE! | I226: =$C226 -> 44284 | J226: =IF($C226>(TODAY()),NA(),SUM($G$3:$G226)) -> #N/A | K226: =IFERROR(VLOOKUP($C226,Calculator!$BY$2:$CD$2500,6,0),"") | L226: =IF($D226="","",$D226) | M226: =IF($D226="","",$L226-(Dashboard!$R$21-(SUM($E$224:$E227)))) | N226: =$C225+1 -> 44284 | O226: =IF($D226="",NA(),($M226)/Dashboard!$R$21) -> #N/A
B227: =$B226+1 -> 225 | C227: =$C226+1 -> 44285 | G227: =IFERROR(VLOOKUP($C227,Calculator!$BY$2:$CB$2500,4,0),"") | H227: =$G227*1 -> #VALUE! | I227: =$C227 -> 44285 | J227: =IF($C227>(TODAY()),NA(),SUM($G$3:$G227)) -> #N/A | K227: =IFERROR(VLOOKUP($C227,Calculator!$BY$2:$CD$2500,6,0),"") | L227: =IF($D227="","",$D227) | M227: =IF($D227="","",$L227-(Dashboard!$R$21-(SUM($E$224:$E228)))) | N227: =$C226+1 -> 44285 | O227: =IF($D227="",NA(),($M227)/Dashboard!$R$21) -> #N/A
B228: =$B227+1 -> 226 | C228: =$C227+1 -> 44286 | G228: =IFERROR(VLOOKUP($C228,Calculator!$BY$2:$CB$2500,4,0),"") | H228: =$G228*1 -> #VALUE! | I228: =$C228 -> 44286 | J228: =IF($C228>(TODAY()),NA(),SUM($G$3:$G228)) -> #N/A | K228: =IFERROR(VLOOKUP($C228,Calculator!$BY$2:$CD$2500,6,0),"") | L228: =IF($D228="","",$D228) | M228: =IF($D228="","",$L228-(Dashboard!$R$21-(SUM($E$224:$E229)))) | N228: =$C227+1 -> 44286 | O228: =IF($D228="",NA(),($M228)/Dashboard!$R$21) -> #N/A
B229: =$B228+1 -> 227 | C229: =$C228+1 -> 44287 | G229: =IFERROR(VLOOKUP($C229,Calculator!$BY$2:$CB$2500,4,0),"") | H229: =$G229*1 -> #VALUE! | I229: =$C229 -> 44287 | J229: =IF($C229>(TODAY()),NA(),SUM($G$3:$G229)) -> #N/A | K229: =IFERROR(VLOOKUP($C229,Calculator!$BY$2:$CD$2500,6,0),"") | L229: =IF($D229="","",$D229) | M229: =IF($D229="","",$L229-(Dashboard!$R$21-(SUM($E$224:$E230)))) | N229: =$C228+1 -> 44287 | O229: =IF($D229="",NA(),($M229)/Dashboard!$R$21) -> #N/A
B230: =$B229+1 -> 228 | C230: =$C229+1 -> 44288 | G230: =IFERROR(VLOOKUP($C230,Calculator!$BY$2:$CB$2500,4,0),"") | H230: =$G230*1 -> #VALUE! | I230: =$C230 -> 44288 | J230: =IF($C230>(TODAY()),NA(),SUM($G$3:$G230)) -> #N/A | K230: =IFERROR(VLOOKUP($C230,Calculator!$BY$2:$CD$2500,6,0),"") | L230: =IF($D230="","",$D230) | M230: =IF($D230="","",$L230-(Dashboard!$R$21-(SUM($E$224:$E231)))) | N230: =$C229+1 -> 44288 | O230: =IF($D230="",NA(),($M230)/Dashboard!$R$21) -> #N/A
B231: =$B230+1 -> 229 | C231: =$C230+1 -> 44289 | G231: =IFERROR(VLOOKUP($C231,Calculator!$BY$2:$CB$2500,4,0),"") | H231: =$G231*1 -> #VALUE! | I231: =$C231 -> 44289 | J231: =IF($C231>(TODAY()),NA(),SUM($G$3:$G231)) -> #N/A | K231: =IFERROR(VLOOKUP($C231,Calculator!$BY$2:$CD$2500,6,0),"") | L231: =IF($D231="","",$D231) | M231: =IF($D231="","",$L231-(Dashboard!$R$21-(SUM($E$224:$E232)))) | N231: =$C230+1 -> 44289 | O231: =IF($D231="",NA(),($M231)/Dashboard!$R$21) -> #N/A
B232: =$B231+1 -> 230 | C232: =$C231+1 -> 44290 | G232: =IFERROR(VLOOKUP($C232,Calculator!$BY$2:$CB$2500,4,0),"") | H232: =$G232*1 -> #VALUE! | I232: =$C232 -> 44290 | J232: =IF($C232>(TODAY()),NA(),SUM($G$3:$G232)) -> #N/A | K232: =IFERROR(VLOOKUP($C232,Calculator!$BY$2:$CD$2500,6,0),"") | L232: =IF($D232="","",$D232) | M232: =IF($D232="","",$L232-(Dashboard!$R$21-(SUM($E$224:$E233)))) | N232: =$C231+1 -> 44290 | O232: =IF($D232="",NA(),($M232)/Dashboard!$R$21) -> #N/A
B233: =$B232+1 -> 231 | C233: =$C232+1 -> 44291 | G233: =IFERROR(VLOOKUP($C233,Calculator!$BY$2:$CB$2500,4,0),"") | H233: =$G233*1 -> #VALUE! | I233: =$C233 -> 44291 | J233: =IF($C233>(TODAY()),NA(),SUM($G$3:$G233)) -> #N/A | K233: =IFERROR(VLOOKUP($C233,Calculator!$BY$2:$CD$2500,6,0),"") | L233: =IF($D233="","",$D233) | M233: =IF($D233="","",$L233-(Dashboard!$R$21-(SUM($E$224:$E234)))) | N233: =$C232+1 -> 44291 | O233: =IF($D233="",NA(),($M233)/Dashboard!$R$21) -> #N/A
B234: =$B233+1 -> 232 | C234: =$C233+1 -> 44292 | G234: =IFERROR(VLOOKUP($C234,Calculator!$BY$2:$CB$2500,4,0),"") | H234: =$G234*1 -> #VALUE! | I234: =$C234 -> 44292 | J234: =IF($C234>(TODAY()),NA(),SUM($G$3:$G234)) -> #N/A | K234: =IFERROR(VLOOKUP($C234,Calculator!$BY$2:$CD$2500,6,0),"") | L234: =IF($D234="","",$D234) | M234: =IF($D234="","",$L234-(Dashboard!$R$21-(SUM($E$224:$E235)))) | N234: =$C233+1 -> 44292 | O234: =IF($D234="",NA(),($M234)/Dashboard!$R$21) -> #N/A
B235: =$B234+1 -> 233 | C235: =$C234+1 -> 44293 | G235: =IFERROR(VLOOKUP($C235,Calculator!$BY$2:$CB$2500,4,0),"") | H235: =$G235*1 -> #VALUE! | I235: =$C235 -> 44293 | J235: =IF($C235>(TODAY()),NA(),SUM($G$3:$G235)) -> #N/A | K235: =IFERROR(VLOOKUP($C235,Calculator!$BY$2:$CD$2500,6,0),"") | L235: =IF($D235="","",$D235) | M235: =IF($D235="","",$L235-(Dashboard!$R$21-(SUM($E$224:$E236)))) | N235: =$C234+1 -> 44293 | O235: =IF($D235="",NA(),($M235)/Dashboard!$R$21) -> #N/A
... B1000: =$B999+1 -> 998 | C1000: =$C999+1 -> 45058 | G1000: =IFERROR(VLOOKUP($C1000,Calculator!$BY$2:$CB$2500,4,0),"") | H1000: =$G1000*1 -> #VALUE! | I1000: =$C1000 -> 45058 | J1000: =IF($C1000>(TODAY()),NA(),SUM($G$3:$G1000)) -> #N/A | K1000: =IFERROR(VLOOKUP($C1000,Calculator!$BY$2:$CD$2500,6,0),"") | L1000: =IF($D1000="","",$D1000) | M1000: =IF($D1000="","",$L1000-(Dashboard!$R$21-(SUM($E$224:$E1001)))) | N1000: =$C999+1 -> 45058 | O1000: =IF($D1000="",NA(),($M1000)/Dashboard!$R$21) -> #N/A

Sheet Calculator
A1: 1 | B1: Date(UTC) | C1: Date(2) | D1: Date(3) | E1: Market | F1: Date_Currency(1) | G1: Assign_Duplicates | H1: Date_Currency(3) | I1: Type | J1: Price | K1: Price(2) | L1: Amount | M1: Amount_2 | N1: Total | O1: Total$ | P1: Fee | Q1: Fee Coin | R1: Fee$1 | S1: Fee$2 | U1: Mining_Deposit | V1: Mining_Deposit_Date | W1: Mining_Date | X1: Date_Value | Y1: Date_Mod | Z1: Mining_Coin | AA1: Mining_Amount | AB1: Mining_Amount_Mod | AC1: Mined_Recent | AD1: Current_Value | AE1: Mining_Transaction_Fee | AF1: Mining_Address | AG1: Mining_TXID | AH1: Mining_Source_Address | AI1: Mining_Payment_ID | AJ1: Mining_Status | AL1: Unique Currencies | AM1: Short Name | AN1: Most Recent Purchase | AO1: Date_Currency(2) | AP1: Copy | AQ1: Price(3) | AR1: Price(4) | AS1: Total_Costs | AT1: Total_Sales | AU1: Total_Fees | AV1: Amount_Bought | AW1: Amount_Sold | AX1: Amount_Owned | AY1: Currency | AZ1: Current_Check_Amount_Owned | BA1: Current_Investments | BB1: Previous_Costs | BC1: Profit | BD1: Costs_of_Owned | BF1: Dashboard_Current | BG1: =$BF1 & " Revised" -> Dashboard_Current Revised | BH1: Mod | BI1: Total Costs | BJ1: Total Sales | BK1: Cost of Sales | BL1: Profit from Sales | BM1: Total Fees | BN1: Transactions | BO1: Mining_Deposits | BP1: Mined_ETH_Total | BQ1: Currently_Mined | BR1: coinmarketcap.com_prices | BS1: Crypto | BT1: Symbol | BU1: Current_Prices | BV1: CoinMarket_Prices | BW1: 24hr_Change | BY1: Date_ETH_Mined | BZ1: Mined_Amount | CA1: Price_on_mining_date | CB1: Mined_Value | CC1: Total_Mined | CD1: ETH_Ttl_Value
A2: =IF($B2="","",$A1+1) | B2: =IF(Investments_Import!A2="","",Investments_Import!A2) | C2: =IF(B2="","",B2*1) | D2: =$C2 | E2: =IF(Investments_Import!B2="","",Investments_Import!B2) | F2: =CONCATENATE(TEXT($D2,"dd-mmm-yyyy")," ",$E2) | G2: =IF($B2="","",COUNTIF($F$2:$F2,$F2)) | H2: =CONCATENATE(TEXT($D2,"dd-mmm-yyyy")," ",$E2," ",$G2) | I2: =IF(Investments_Import!C2="","",Investments_Import!C2) | J2: =IF(Investments_Import!D2="","",Investments_Import!D2) | K2: =IF($B2="","",$J2*1) | L2: =IF(Investments_Import!E2="","",Investments_Import!E2) | M2: =IF($L2="","",$L2*1) | N2: =IF(Investments_Import!F2="","",Investments_Import!F2) | O2: =IF($N2="","",$N2*1) | P2: =IF(Investments_Import!G2="","",Investments_Import!G2) | Q2: =IF(Investments_Import!H2="","",Investments_Import!H2) | R2: =IF($Q2="","",IF($Q2="USD",$P2,$P2*$J2)) | S2: =IF($R2="","",$R2*1) | U2: =IF(Mining_Import!A2="","",Mining_Import!A2) | V2: =IF(U2="","",U2*1) | W2: =V2 | X2: =IFERROR(INT($W2),"") | Y2: =$X2 | Z2: =IF(Mining_Import!B2="","",Mining_Import!B2) | AA2: =IF(Mining_Import!$C2="","",Mining_Import!$C2) | AB2: =IFERROR($AA2*1,"") | AC2: =IF($Y2>Dashboard!$Q$19,$AB2,"") | AD2: =IFERROR($AB2*$BU$19,"") | AE2: =IF(Mining_Import!D2="","",Mining_Import!D2) | AF2: =IF(Mining_Import!E2="","",Mining_Import!E2) | AG2: =IF(Mining_Import!F2="","",Mining_Import!F2) | AH2: =IF(Mining_Import!G2="","",Mining_Import!G2) | AI2: =IF(Mining_Import!H2="","",Mining_Import!H2) | AJ2: =IF(Mining_Import!I2="","",Mining_Import!I2) | AL2: =IFERROR(INDEX($E$2:$E$2500, MATCH(0, INDEX(COUNTIF($AL$1:AL1, $E$2:$E$2500), 0, 0), 0)), "") | AM2: =IF(Calculator!$AL2="","",LEFT(Calculator!$AL2, LEN(Calculator!$AL2)-3)) | AN2: {=IF($AL2="","",MAX(IF($E$2:$E$2500=$AL2,$C$2:$C$2500)))} | AO2: =IF($AN2="","",(TEXT($AN2,"dd-mmm-yyyy")&" "&$AL2&" "&"1")) | AP2: =$AO2 | AQ2: =IF($AL2="","",VLOOKUP($AO2, $H:$K, 3, 0)) | AR2: =IF($AQ2="","",$AQ2*1) | AS2: =IF($AL2="","",SUMIFS($O:$O,$E:$E,$AL2,$I:$I,"BUY")) | AT2: =IF($AL2="","",SUMIFS($O:$O,$E:$E,$AL2,$I:$I,"SELL")) | AU2: =IF($AL2="","",SUMIF($E:$E,$AL2,$S:$S)) | AV2: =IF($AL2="","",SUMIFS($M:$M,$E:$E,$AL2,$I:$I,"BUY")) | AW2: =IF($AL2="","",SUMIFS($M:$M,$E:$E,$AL2,$I:$I,"SELL")) | AX2: =IF($AZ2=1,$AV2-$AW2,"") | AY2: =$AM2 | AZ2: =IF($AY2="","",IFERROR(VLOOKUP($AP2,$BG$2:$BH$13,2, FALSE),"")) | BA2: =IF($AZ2=1, "CURRENT","") | BB2: =IF($AW2=0,"",IFERROR($AS2-$BD2,"")) | BC2: =IFERROR(IF($BA2="CURRENT",(($AT2-$BB2)-$AU2),IF($AW2=0,"",($AT2-$AS2)-$AU2)),"") | BD2: =IF($BA2="CURRENT",($AX2*$AR2),"") | BF2: =CONCATENATE(TEXT(Dashboard!$Q8,"dd-mmm-yyyy")," ",Dashboard!$P8,"USD"," ",1) -> 05-Feb-2021 USDUSD 1 | BG2: =IF($BF2="00-Jan-1900 USD 1","",$BF2) -> 05-Feb-2021 USDUSD 1 | BH2: 1 | BI2: =SUMIF($I:$I,"BUY",$O:$O) -> 0 | BJ2: =SUMIF($I:$I,"SELL",$O:$O) -> 0 | BK2: =$BI$2-(SUM($BD:$BD)) -> 0 | BL2: =SUM(($BC$2:$BC$50),(-$BM$2)) -> 0 | BM2: =SUM($S:$S) -> 0 | BN2: =(SUMPRODUCT(1/COUNTIF($F$2:$F$2500,$F$2:$F$2500))-1) -> 4.9515947e-14 | BO2: =COUNTIF(Calculator!$W:$W,">0") -> 0 | BP2: =SUM($AB:$AB) -> 0 | BQ2: =SUM($AC:$AC) -> 0 | BR2: http://coinmarketcap.com/currencies/litecoin/ | BS2: =IF(Stock_Connector!B2="","",Stock_Connector!B2) -> LTC | BT2: =IF(Stock_Connector!C2="","",Stock_Connector!C2) -> 151.8 | BU2: =IF(Stock_Connector!C2="","",Stock_Connector!C2) -> 151.8 | BV2: =IF(Stock_Connector!E2="","",Stock_Connector!E2) | BW2: =IF(Stock_Connector!D2="","",Stock_Connector!D2) -> -0.056322268 | BY2: =Y2 | BZ2: =AB2 | CA2: =IFERROR(VLOOKUP($BY2,Account_Value!$C$2:$F$2500,4,0),"") | CB2: =IF(BZ2="","",BZ2*CA2) | CC2: =IF($BZ2="","",SUM($BZ$2:$BZ2)) | CD2: =IF($BZ2="","",$CA2*(SUM($BZ$2:$BZ2)))
A3: =IF($B3="","",$A2+1) | B3: =IF(Investments_Import!A3="","",Investments_Import!A3) | C3: =IF(B3="","",B3*1) | D3: =$C3 | E3: =IF(Investments_Import!B3="","",Investments_Import!B3) | F3: =CONCATENATE(TEXT($D3,"dd-mmm-yyyy")," ",$E3) | G3: =IF($B3="","",COUNTIF($F$2:$F3,$F3)) | H3: =CONCATENATE(TEXT($D3,"dd-mmm-yyyy")," ",$E3," ",$G3) | I3: =IF(Investments_Import!C3="","",Investments_Import!C3) | J3: =IF(Investments_Import!D3="","",Investments_Import!D3) | K3: =IF($B3="","",$J3*1) | L3: =IF(Investments_Import!E3="","",Investments_Import!E3) | M3: =IF($L3="","",$L3*1) | N3: =IF(Investments_Import!F3="","",Investments_Import!F3) | O3: =IF($N3="","",$N3*1) | P3: =IF(Investments_Import!G3="","",Investments_Import!G3) | Q3: =IF(Investments_Import!H3="","",Investments_Import!H3) | R3: =IF($Q3="","",IF($Q3="USD",$P3,$P3*$J3)) | S3: =IF($R3="","",$R3*1) | U3: =IF(Mining_Import!A3="","",Mining_Import!A3) | V3: =IF(U3="","",U3*1) | W3: =V3 | X3: =IFERROR(INT($W3),"") | Y3: =$X3 | Z3: =IF(Mining_Import!B3="","",Mining_Import!B3) | AA3: =IF(Mining_Import!$C3="","",Mining_Import!$C3) | AB3: =IFERROR($AA3*1,"") | AC3: =IF($Y3>Dashboard!$Q$19,$AB3,"") | AD3: =IFERROR($AB3*$BU$19,"") | AE3: =IF(Mining_Import!D3="","",Mining_Import!D3) | AF3: =IF(Mining_Import!E3="","",Mining_Import!E3) | AG3: =IF(Mining_Import!F3="","",Mining_Import!F3) | AH3: =IF(Mining_Import!G3="","",Mining_Import!G3) | AI3: =IF(Mining_Import!H3="","",Mining_Import!H3) | AJ3: =IF(Mining_Import!I3="","",Mining_Import!I3) | AL3: =IFERROR(INDEX($E$2:$E$2500, MATCH(0, INDEX(COUNTIF($AL$1:AL2, $E$2:$E$2500), 0, 0), 0)), "") | AM3: =IF(Calculator!$AL3="","",LEFT(Calculator!$AL3, LEN(Calculator!$AL3)-3)) | AN3: {=IF($AL3="","",MAX(IF($E$2:$E$2500=$AL3,$C$2:$C$2500)))} | AO3: =IF($AN3="","",(TEXT($AN3,"dd-mmm-yyyy")&" "&$AL3&" "&"1")) | AP3: =$AO3 | AQ3: =IF($AL3="","",VLOOKUP($AO3, $H:$K, 3, 0)) | AR3: =IF($AQ3="","",$AQ3*1) | AS3: =IF($AL3="","",SUMIFS($O:$O,$E:$E,$AL3,$I:$I,"BUY")) | AT3: =IF($AL3="","",SUMIFS($O:$O,$E:$E,$AL3,$I:$I,"SELL")) | AU3: =IF($AL3="","",SUMIF($E:$E,$AL3,$S:$S)) | AV3: =IF($AL3="","",SUMIFS($M:$M,$E:$E,$AL3,$I:$I,"BUY")) | AW3: =IF($AL3="","",SUMIFS($M:$M,$E:$E,$AL3,$I:$I,"SELL")) | AX3: =IF($AZ3=1,$AV3-$AW3,"") | AY3: =$AM3 | AZ3: =IF($AY3="","",IFERROR(VLOOKUP($AP3,$BG$2:$BH$13,2, FALSE),"")) | BA3: =IF($AZ3=1, "CURRENT","") | BB3: =IF($AW3=0,"",IFERROR($AS3-$BD3,"")) | BC3: =IFERROR(IF($BA3="CURRENT",(($AT3-$BB3)-$AU3),IF($AW3=0,"",($AT3-$AS3)-$AU3)),"") | BD3: =IF($BA3="CURRENT",($AX3*$AR3),"") | BF3: =CONCATENATE(TEXT(Dashboard!$Q9,"dd-mmm-yyyy")," ",Dashboard!$P9,"USD"," ",1) -> 00-Jan-1900 USD 1 | BG3: =IF($BF3="00-Jan-1900 USD 1","",$BF3) | BH3: 1 | BR3: https://coinmarketcap.com/currencies/zcash/ | BS3: =IF(Stock_Connector!B3="","",Stock_Connector!B3) -> ZEC | BT3: =IF(Stock_Connector!C3="","",Stock_Connector!C3) -> 92.93284 | BU3: =IF(Stock_Connector!C3="","",Stock_Connector!C3) -> 92.93284 | BV3: =IF(Stock_Connector!E3="","",Stock_Connector!E3) | BW3: =IF(Stock_Connector!D3="","",Stock_Connector!D3) -> -0.046495885 | BY3: =Y3 | BZ3: =AB3 | CA3: =IFERROR(VLOOKUP($BY3,Account_Value!$C$2:$F$2500,4,0),"") | CB3: =IF(BZ3="","",BZ3*CA3) | CC3: =IF($BZ3="","",SUM($BZ$2:$BZ3)) | CD3: =IF($BZ3="","",$CA3*(SUM($BZ$2:$BZ3)))
A4: =IF($B4="","",$A3+1) | B4: =IF(Investments_Import!A4="","",Investments_Import!A4) | C4: =IF(B4="","",B4*1) | D4: =$C4 | E4: =IF(Investments_Import!B4="","",Investments_Import!B4) | F4: =CONCATENATE(TEXT($D4,"dd-mmm-yyyy")," ",$E4) | G4: =IF($B4="","",COUNTIF($F$2:$F4,$F4)) | H4: =CONCATENATE(TEXT($D4,"dd-mmm-yyyy")," ",$E4," ",$G4) | I4: =IF(Investments_Import!C4="","",Investments_Import!C4) | J4: =IF(Investments_Import!D4="","",Investments_Import!D4) | K4: =IF($B4="","",$J4*1) | L4: =IF(Investments_Import!E4="","",Investments_Import!E4) | M4: =IF($L4="","",$L4*1) | N4: =IF(Investments_Import!F4="","",Investments_Import!F4) | O4: =IF($N4="","",$N4*1) | P4: =IF(Investments_Import!G4="","",Investments_Import!G4) | Q4: =IF(Investments_Import!H4="","",Investments_Import!H4) | R4: =IF($Q4="","",IF($Q4="USD",$P4,$P4*$J4)) | S4: =IF($R4="","",$R4*1) | U4: =IF(Mining_Import!A4="","",Mining_Import!A4) | V4: =IF(U4="","",U4*1) | W4: =V4 | X4: =IFERROR(INT($W4),"") | Y4: =$X4 | Z4: =IF(Mining_Import!B4="","",Mining_Import!B4) | AA4: =IF(Mining_Import!$C4="","",Mining_Import!$C4) | AB4: =IFERROR($AA4*1,"") | AC4: =IF($Y4>Dashboard!$Q$19,$AB4,"") | AD4: =IFERROR($AB4*$BU$19,"") | AE4: =IF(Mining_Import!D4="","",Mining_Import!D4) | AF4: =IF(Mining_Import!E4="","",Mining_Import!E4) | AG4: =IF(Mining_Import!F4="","",Mining_Import!F4) | AH4: =IF(Mining_Import!G4="","",Mining_Import!G4) | AI4: =IF(Mining_Import!H4="","",Mining_Import!H4) | AJ4: =IF(Mining_Import!I4="","",Mining_Import!I4) | AL4: =IFERROR(INDEX($E$2:$E$2500, MATCH(0, INDEX(COUNTIF($AL$1:AL3, $E$2:$E$2500), 0, 0), 0)), "") | AM4: =IF(Calculator!$AL4="","",LEFT(Calculator!$AL4, LEN(Calculator!$AL4)-3)) | AN4: {=IF($AL4="","",MAX(IF($E$2:$E$2500=$AL4,$C$2:$C$2500)))} | AO4: =IF($AN4="","",(TEXT($AN4,"dd-mmm-yyyy")&" "&$AL4&" "&"1")) | AP4: =$AO4 | AQ4: =IF($AL4="","",VLOOKUP($AO4, $H:$K, 3, 0)) | AR4: =IF($AQ4="","",$AQ4*1) | AS4: =IF($AL4="","",SUMIFS($O:$O,$E:$E,$AL4,$I:$I,"BUY")) | AT4: =IF($AL4="","",SUMIFS($O:$O,$E:$E,$AL4,$I:$I,"SELL")) | AU4: =IF($AL4="","",SUMIF($E:$E,$AL4,$S:$S)) | AV4: =IF($AL4="","",SUMIFS($M:$M,$E:$E,$AL4,$I:$I,"BUY")) | AW4: =IF($AL4="","",SUMIFS($M:$M,$E:$E,$AL4,$I:$I,"SELL")) | AX4: =IF($AZ4=1,$AV4-$AW4,"") | AY4: =$AM4 | AZ4: =IF($AY4="","",IFERROR(VLOOKUP($AP4,$BG$2:$BH$13,2, FALSE),"")) | BA4: =IF($AZ4=1, "CURRENT","") | BB4: =IF($AW4=0,"",IFERROR($AS4-$BD4,"")) | BC4: =IFERROR(IF($BA4="CURRENT",(($AT4-$BB4)-$AU4),IF($AW4=0,"",($AT4-$AS4)-$AU4)),"") | BD4: =IF($BA4="CURRENT",($AX4*$AR4),"") | BF4: =CONCATENATE(TEXT(Dashboard!$Q10,"dd-mmm-yyyy")," ",Dashboard!$P10,"USD"," ",1) -> 00-Jan-1900 USD 1 | BG4: =IF($BF4="00-Jan-1900 USD 1","",$BF4) | BH4: 1 | BR4: https://coinmarketcap.com/currencies/ethereum-classic/ | BS4: =IF(Stock_Connector!B4="","",Stock_Connector!B4) -> ETC | BT4: =IF(Stock_Connector!C4="","",Stock_Connector!C4) -> 8.326 | BU4: =IF(Stock_Connector!C4="","",Stock_Connector!C4) -> 8.326 | BV4: =IF(Stock_Connector!E4="","",Stock_Connector!E4) | BW4: =IF(Stock_Connector!D4="","",Stock_Connector!D4) -> -0.035896248 | BY4: =Y4 | BZ4: =AB4 | CA4: =IFERROR(VLOOKUP($BY4,Account_Value!$C$2:$F$2500,4,0),"") | CB4: =IF(BZ4="","",BZ4*CA4) | CC4: =IF($BZ4="","",SUM($BZ$2:$BZ4)) | CD4: =IF($BZ4="","",$CA4*(SUM($BZ$2:$BZ4)))
A5: =IF($B5="","",$A4+1) | B5: =IF(Investments_Import!A5="","",Investments_Import!A5) | C5: =IF(B5="","",B5*1) | D5: =$C5 | E5: =IF(Investments_Import!B5="","",Investments_Import!B5) | F5: =CONCATENATE(TEXT($D5,"dd-mmm-yyyy")," ",$E5) | G5: =IF($B5="","",COUNTIF($F$2:$F5,$F5)) | H5: =CONCATENATE(TEXT($D5,"dd-mmm-yyyy")," ",$E5," ",$G5) | I5: =IF(Investments_Import!C5="","",Investments_Import!C5) | J5: =IF(Investments_Import!D5="","",Investments_Import!D5) | K5: =IF($B5="","",$J5*1) | L5: =IF(Investments_Import!E5="","",Investments_Import!E5) | M5: =IF($L5="","",$L5*1) | N5: =IF(Investments_Import!F5="","",Investments_Import!F5) | O5: =IF($N5="","",$N5*1) | P5: =IF(Investments_Import!G5="","",Investments_Import!G5) | Q5: =IF(Investments_Import!H5="","",Investments_Import!H5) | R5: =IF($Q5="","",IF($Q5="USD",$P5,$P5*$J5)) | S5: =IF($R5="","",$R5*1) | U5: =IF(Mining_Import!A5="","",Mining_Import!A5) | V5: =IF(U5="","",U5*1) | W5: =V5 | X5: =IFERROR(INT($W5),"") | Y5: =$X5 | Z5: =IF(Mining_Import!B5="","",Mining_Import!B5) | AA5: =IF(Mining_Import!$C5="","",Mining_Import!$C5) | AB5: =IFERROR($AA5*1,"") | AC5: =IF($Y5>Dashboard!$Q$19,$AB5,"") | AD5: =IFERROR($AB5*$BU$19,"") | AE5: =IF(Mining_Import!D5="","",Mining_Import!D5) | AF5: =IF(Mining_Import!E5="","",Mining_Import!E5) | AG5: =IF(Mining_Import!F5="","",Mining_Import!F5) | AH5: =IF(Mining_Import!G5="","",Mining_Import!G5) | AI5: =IF(Mining_Import!H5="","",Mining_Import!H5) | AJ5: =IF(Mining_Import!I5="","",Mining_Import!I5) | AL5: =IFERROR(INDEX($E$2:$E$2500, MATCH(0, INDEX(COUNTIF($AL$1:AL4, $E$2:$E$2500), 0, 0), 0)), "") | AM5: =IF(Calculator!$AL5="","",LEFT(Calculator!$AL5, LEN(Calculator!$AL5)-3)) | AN5: {=IF($AL5="","",MAX(IF($E$2:$E$2500=$AL5,$C$2:$C$2500)))} | AO5: =IF($AN5="","",(TEXT($AN5,"dd-mmm-yyyy")&" "&$AL5&" "&"1")) | AP5: =$AO5 | AQ5: =IF($AL5="","",VLOOKUP($AO5, $H:$K, 3, 0)) | AR5: =IF($AQ5="","",$AQ5*1) | AS5: =IF($AL5="","",SUMIFS($O:$O,$E:$E,$AL5,$I:$I,"BUY")) | AT5: =IF($AL5="","",SUMIFS($O:$O,$E:$E,$AL5,$I:$I,"SELL")) | AU5: =IF($AL5="","",SUMIF($E:$E,$AL5,$S:$S)) | AV5: =IF($AL5="","",SUMIFS($M:$M,$E:$E,$AL5,$I:$I,"BUY")) | AW5: =IF($AL5="","",SUMIFS($M:$M,$E:$E,$AL5,$I:$I,"SELL")) | AX5: =IF($AZ5=1,$AV5-$AW5,"") | AY5: =$AM5 | AZ5: =IF($AY5="","",IFERROR(VLOOKUP($AP5,$BG$2:$BH$13,2, FALSE),"")) | BA5: =IF($AZ5=1, "CURRENT","") | BB5: =IF($AW5=0,"",IFERROR($AS5-$BD5,"")) | BC5: =IFERROR(IF($BA5="CURRENT",(($AT5-$BB5)-$AU5),IF($AW5=0,"",($AT5-$AS5)-$AU5)),"") | BD5: =IF($BA5="CURRENT",($AX5*$AR5),"") | BF5: =CONCATENATE(TEXT(Dashboard!$Q11,"dd-mmm-yyyy")," ",Dashboard!$P11,"USD"," ",1) -> 00-Jan-1900 USD 1 | BG5: =IF($BF5="00-Jan-1900 USD 1","",$BF5) | BH5: 1 | BR5: https://coinmarketcap.com/currencies/icon/ | BS5: =IF(Stock_Connector!B5="","",Stock_Connector!B5) -> ICX | BT5: =IF(Stock_Connector!C5="","",Stock_Connector!C5) -> 0.8524516 | BU5: =IF(Stock_Connector!C5="","",Stock_Connector!C5) -> 0.8524516 | BV5: =IF(Stock_Connector!E5="","",Stock_Connector!E5) | BW5: =IF(Stock_Connector!D5="","",Stock_Connector!D5) -> 0.087359535 | BY5: =Y5 | BZ5: =AB5 | CA5: =IFERROR(VLOOKUP($BY5,Account_Value!$C$2:$F$2500,4,0),"") | CB5: =IF(BZ5="","",BZ5*CA5) | CC5: =IF($BZ5="","",SUM($BZ$2:$BZ5)) | CD5: =IF($BZ5="","",$CA5*(SUM($BZ$2:$BZ5)))
A6: =IF($B6="","",$A5+1) | B6: =IF(Investments_Import!A6="","",Investments_Import!A6) | C6: =IF(B6="","",B6*1) | D6: =$C6 | E6: =IF(Investments_Import!B6="","",Investments_Import!B6) | F6: =CONCATENATE(TEXT($D6,"dd-mmm-yyyy")," ",$E6) | G6: =IF($B6="","",COUNTIF($F$2:$F6,$F6)) | H6: =CONCATENATE(TEXT($D6,"dd-mmm-yyyy")," ",$E6," ",$G6) | I6: =IF(Investments_Import!C6="","",Investments_Import!C6) | J6: =IF(Investments_Import!D6="","",Investments_Import!D6) | K6: =IF($B6="","",$J6*1) | L6: =IF(Investments_Import!E6="","",Investments_Import!E6) | M6: =IF($L6="","",$L6*1) | N6: =IF(Investments_Import!F6="","",Investments_Import!F6) | O6: =IF($N6="","",$N6*1) | P6: =IF(Investments_Import!G6="","",Investments_Import!G6) | Q6: =IF(Investments_Import!H6="","",Investments_Import!H6) | R6: =IF($Q6="","",IF($Q6="USD",$P6,$P6*$J6)) | S6: =IF($R6="","",$R6*1) | U6: =IF(Mining_Import!A6="","",Mining_Import!A6) | V6: =IF(U6="","",U6*1) | W6: =V6 | X6: =IFERROR(INT($W6),"") | Y6: =$X6 | Z6: =IF(Mining_Import!B6="","",Mining_Import!B6) | AA6: =IF(Mining_Import!$C6="","",Mining_Import!$C6) | AB6: =IFERROR($AA6*1,"") | AC6: =IF($Y6>Dashboard!$Q$19,$AB6,"") | AD6: =IFERROR($AB6*$BU$19,"") | AE6: =IF(Mining_Import!D6="","",Mining_Import!D6) | AF6: =IF(Mining_Import!E6="","",Mining_Import!E6) | AG6: =IF(Mining_Import!F6="","",Mining_Import!F6) | AH6: =IF(Mining_Import!G6="","",Mining_Import!G6) | AI6: =IF(Mining_Import!H6="","",Mining_Import!H6) | AJ6: =IF(Mining_Import!I6="","",Mining_Import!I6) | AL6: =IFERROR(INDEX($E$2:$E$2500, MATCH(0, INDEX(COUNTIF($AL$1:AL5, $E$2:$E$2500), 0, 0), 0)), "") | AM6: =IF(Calculator!$AL6="","",LEFT(Calculator!$AL6, LEN(Calculator!$AL6)-3)) | AN6: {=IF($AL6="","",MAX(IF($E$2:$E$2500=$AL6,$C$2:$C$2500)))} | AO6: =IF($AN6="","",(TEXT($AN6,"dd-mmm-yyyy")&" "&$AL6&" "&"1")) | AP6: =$AO6 | AQ6: =IF($AL6="","",VLOOKUP($AO6, $H:$K, 3, 0)) | AR6: =IF($AQ6="","",$AQ6*1) | AS6: =IF($AL6="","",SUMIFS($O:$O,$E:$E,$AL6,$I:$I,"BUY")) | AT6: =IF($AL6="","",SUMIFS($O:$O,$E:$E,$AL6,$I:$I,"SELL")) | AU6: =IF($AL6="","",SUMIF($E:$E,$AL6,$S:$S)) | AV6: =IF($AL6="","",SUMIFS($M:$M,$E:$E,$AL6,$I:$I,"BUY")) | AW6: =IF($AL6="","",SUMIFS($M:$M,$E:$E,$AL6,$I:$I,"SELL")) | AX6: =IF($AZ6=1,$AV6-$AW6,"") | AY6: =$AM6 | AZ6: =IF($AY6="","",IFERROR(VLOOKUP($AP6,$BG$2:$BH$13,2, FALSE),"")) | BA6: =IF($AZ6=1, "CURRENT","") | BB6: =IF($AW6=0,"",IFERROR($AS6-$BD6,"")) | BC6: =IFERROR(IF($BA6="CURRENT",(($AT6-$BB6)-$AU6),IF($AW6=0,"",($AT6-$AS6)-$AU6)),"") | BD6: =IF($BA6="CURRENT",($AX6*$AR6),"") | BF6: =CONCATENATE(TEXT(Dashboard!$Q12,"dd-mmm-yyyy")," ",Dashboard!$P12,"USD"," ",1) -> 00-Jan-1900 USD 1 | BG6: =IF($BF6="00-Jan-1900 USD 1","",$BF6) | BH6: 1 | BR6: https://coinmarketcap.com/currencies/bitcoin-cash/ | BS6: =IF(Stock_Connector!B6="","",Stock_Connector!B6) -> BCH | BT6: =IF(Stock_Connector!C6="","",Stock_Connector!C6) -> 454.29 | BU6: =IF(Stock_Connector!C6="","",Stock_Connector!C6) -> 454.29 | BV6: =IF(Stock_Connector!E6="","",Stock_Connector!E6) | BW6: =IF(Stock_Connector!D6="","",Stock_Connector!D6) -> -0.054114267 | BY6: =Y6 | BZ6: =AB6 | CA6: =IFERROR(VLOOKUP($BY6,Account_Value!$C$2:$F$2500,4,0),"") | CB6: =IF(BZ6="","",BZ6*CA6) | CC6: =IF($BZ6="","",SUM($BZ$2:$BZ6)) | CD6: =IF($BZ6="","",$CA6*(SUM($BZ$2:$BZ6)))
A7: =IF($B7="","",$A6+1) | B7: =IF(Investments_Import!A7="","",Investments_Import!A7) | C7: =IF(B7="","",B7*1) | D7: =$C7 | E7: =IF(Investments_Import!B7="","",Investments_Import!B7) | F7: =CONCATENATE(TEXT($D7,"dd-mmm-yyyy")," ",$E7) | G7: =IF($B7="","",COUNTIF($F$2:$F7,$F7)) | H7: =CONCATENATE(TEXT($D7,"dd-mmm-yyyy")," ",$E7," ",$G7) | I7: =IF(Investments_Import!C7="","",Investments_Import!C7) | J7: =IF(Investments_Import!D7="","",Investments_Import!D7) | K7: =IF($B7="","",$J7*1) | L7: =IF(Investments_Import!E7="","",Investments_Import!E7) | M7: =IF($L7="","",$L7*1) | N7: =IF(Investments_Import!F7="","",Investments_Import!F7) | O7: =IF($N7="","",$N7*1) | P7: =IF(Investments_Import!G7="","",Investments_Import!G7) | Q7: =IF(Investments_Import!H7="","",Investments_Import!H7) | R7: =IF($Q7="","",IF($Q7="USD",$P7,$P7*$J7)) | S7: =IF($R7="","",$R7*1) | U7: =IF(Mining_Import!A7="","",Mining_Import!A7) | V7: =IF(U7="","",U7*1) | W7: =V7 | X7: =IFERROR(INT($W7),"") | Y7: =$X7 | Z7: =IF(Mining_Import!B7="","",Mining_Import!B7) | AA7: =IF(Mining_Import!$C7="","",Mining_Import!$C7) | AB7: =IFERROR($AA7*1,"") | AC7: =IF($Y7>Dashboard!$Q$19,$AB7,"") | AD7: =IFERROR($AB7*$BU$19,"") | AE7: =IF(Mining_Import!D7="","",Mining_Import!D7) | AF7: =IF(Mining_Import!E7="","",Mining_Import!E7) | AG7: =IF(Mining_Import!F7="","",Mining_Import!F7) | AH7: =IF(Mining_Import!G7="","",Mining_Import!G7) | AI7: =IF(Mining_Import!H7="","",Mining_Import!H7) | AJ7: =IF(Mining_Import!I7="","",Mining_Import!I7) | AL7: =IFERROR(INDEX($E$2:$E$2500, MATCH(0, INDEX(COUNTIF($AL$1:AL6, $E$2:$E$2500), 0, 0), 0)), "") | AM7: =IF(Calculator!$AL7="","",LEFT(Calculator!$AL7, LEN(Calculator!$AL7)-3)) | AN7: {=IF($AL7="","",MAX(IF($E$2:$E$2500=$AL7,$C$2:$C$2500)))} | AO7: =IF($AN7="","",(TEXT($AN7,"dd-mmm-yyyy")&" "&$AL7&" "&"1")) | AP7: =$AO7 | AQ7: =IF($AL7="","",VLOOKUP($AO7, $H:$K, 3, 0)) | AR7: =IF($AQ7="","",$AQ7*1) | AS7: =IF($AL7="","",SUMIFS($O:$O,$E:$E,$AL7,$I:$I,"BUY")) | AT7: =IF($AL7="","",SUMIFS($O:$O,$E:$E,$AL7,$I:$I,"SELL")) | AU7: =IF($AL7="","",SUMIF($E:$E,$AL7,$S:$S)) | AV7: =IF($AL7="","",SUMIFS($M:$M,$E:$E,$AL7,$I:$I,"BUY")) | AW7: =IF($AL7="","",SUMIFS($M:$M,$E:$E,$AL7,$I:$I,"SELL")) | AX7: =IF($AZ7=1,$AV7-$AW7,"") | AY7: =$AM7 | AZ7: =IF($AY7="","",IFERROR(VLOOKUP($AP7,$BG$2:$BH$13,2, FALSE),"")) | BA7: =IF($AZ7=1, "CURRENT","") | BB7: =IF($AW7=0,"",IFERROR($AS7-$BD7,"")) | BC7: =IFERROR(IF($BA7="CURRENT",(($AT7-$BB7)-$AU7),IF($AW7=0,"",($AT7-$AS7)-$AU7)),"") | BD7: =IF($BA7="CURRENT",($AX7*$AR7),"") | BF7: =CONCATENATE(TEXT(Dashboard!$Q13,"dd-mmm-yyyy")," ",Dashboard!$P13,"USD"," ",1) -> 00-Jan-1900 USD 1 | BG7: =IF($BF7="00-Jan-1900 USD 1","",$BF7) | BH7: 1 | BR7: https://coinmarketcap.com/currencies/qtum/ | BS7: =IF(Stock_Connector!B7="","",Stock_Connector!B7) -> QTUM | BT7: =IF(Stock_Connector!C7="","",Stock_Connector!C7) -> 4.359355 | BU7: =IF(Stock_Connector!C7="","",Stock_Connector!C7) -> 4.359355 | BV7: =IF(Stock_Connector!E7="","",Stock_Connector!E7) | BW7: =IF(Stock_Connector!D7="","",Stock_Connector!D7) -> 0.14460765 | BY7: =Y7 | BZ7: =AB7 | CA7: =IFERROR(VLOOKUP($BY7,Account_Value!$C$2:$F$2500,4,0),"") | CB7: =IF(BZ7="","",BZ7*CA7) | CC7: =IF($BZ7="","",SUM($BZ$2:$BZ7)) | CD7: =IF($BZ7="","",$CA7*(SUM($BZ$2:$BZ7)))
A8: =IF($B8="","",$A7+1) | B8: =IF(Investments_Import!A8="","",Investments_Import!A8) | C8: =IF(B8="","",B8*1) | D8: =$C8 | E8: =IF(Investments_Import!B8="","",Investments_Import!B8) | F8: =CONCATENATE(TEXT($D8,"dd-mmm-yyyy")," ",$E8) | G8: =IF($B8="","",COUNTIF($F$2:$F8,$F8)) | H8: =CONCATENATE(TEXT($D8,"dd-mmm-yyyy")," ",$E8," ",$G8) | I8: =IF(Investments_Import!C8="","",Investments_Import!C8) | J8: =IF(Investments_Import!D8="","",Investments_Import!D8) | K8: =IF($B8="","",$J8*1) | L8: =IF(Investments_Import!E8="","",Investments_Import!E8) | M8: =IF($L8="","",$L8*1) | N8: =IF(Investments_Import!F8="","",Investments_Import!F8) | O8: =IF($N8="","",$N8*1) | P8: =IF(Investments_Import!G8="","",Investments_Import!G8) | Q8: =IF(Investments_Import!H8="","",Investments_Import!H8) | R8: =IF($Q8="","",IF($Q8="USD",$P8,$P8*$J8)) | S8: =IF($R8="","",$R8*1) | U8: =IF(Mining_Import!A8="","",Mining_Import!A8) | V8: =IF(U8="","",U8*1) | W8: =V8 | X8: =IFERROR(INT($W8),"") | Y8: =$X8 | Z8: =IF(Mining_Import!B8="","",Mining_Import!B8) | AA8: =IF(Mining_Import!$C8="","",Mining_Import!$C8) | AB8: =IFERROR($AA8*1,"") | AC8: =IF($Y8>Dashboard!$Q$19,$AB8,"") | AD8: =IFERROR($AB8*$BU$19,"") | AE8: =IF(Mining_Import!D8="","",Mining_Import!D8) | AF8: =IF(Mining_Import!E8="","",Mining_Import!E8) | AG8: =IF(Mining_Import!F8="","",Mining_Import!F8) | AH8: =IF(Mining_Import!G8="","",Mining_Import!G8) | AI8: =IF(Mining_Import!H8="","",Mining_Import!H8) | AJ8: =IF(Mining_Import!I8="","",Mining_Import!I8) | AL8: =IFERROR(INDEX($E$2:$E$2500, MATCH(0, INDEX(COUNTIF($AL$1:AL7, $E$2:$E$2500), 0, 0), 0)), "") | AM8: =IF(Calculator!$AL8="","",LEFT(Calculator!$AL8, LEN(Calculator!$AL8)-3)) | AN8: {=IF($AL8="","",MAX(IF($E$2:$E$2500=$AL8,$C$2:$C$2500)))} | AO8: =IF($AN8="","",(TEXT($AN8,"dd-mmm-yyyy")&" "&$AL8&" "&"1")) | AP8: =$AO8 | AQ8: =IF($AL8="","",VLOOKUP($AO8, $H:$K, 3, 0)) | AR8: =IF($AQ8="","",$AQ8*1) | AS8: =IF($AL8="","",SUMIFS($O:$O,$E:$E,$AL8,$I:$I,"BUY")) | AT8: =IF($AL8="","",SUMIFS($O:$O,$E:$E,$AL8,$I:$I,"SELL")) | AU8: =IF($AL8="","",SUMIF($E:$E,$AL8,$S:$S)) | AV8: =IF($AL8="","",SUMIFS($M:$M,$E:$E,$AL8,$I:$I,"BUY")) | AW8: =IF($AL8="","",SUMIFS($M:$M,$E:$E,$AL8,$I:$I,"SELL")) | AX8: =IF($AZ8=1,$AV8-$AW8,"") | AY8: =$AM8 | AZ8: =IF($AY8="","",IFERROR(VLOOKUP($AP8,$BG$2:$BH$13,2, FALSE),"")) | BA8: =IF($AZ8=1, "CURRENT","") | BB8: =IF($AW8=0,"",IFERROR($AS8-$BD8,"")) | BC8: =IFERROR(IF($BA8="CURRENT",(($AT8-$BB8)-$AU8),IF($AW8=0,"",($AT8-$AS8)-$AU8)),"") | BD8: =IF($BA8="CURRENT",($AX8*$AR8),"") | BF8: =CONCATENATE(TEXT(Dashboard!$Q14,"dd-mmm-yyyy")," ",Dashboard!$P14,"USD"," ",1) -> 00-Jan-1900 USD 1 | BG8: =IF($BF8="00-Jan-1900 USD 1","",$BF8) | BH8: 1 | BR8: https://coinmarketcap.com/currencies/neo/ | BS8: =IF(Stock_Connector!B8="","",Stock_Connector!B8) -> NEO | BT8: =IF(Stock_Connector!C8="","",Stock_Connector!C8) -> 24.84482 | BU8: =IF(Stock_Connector!C8="","",Stock_Connector!C8) -> 24.84482 | BV8: =IF(Stock_Connector!E8="","",Stock_Connector!E8) | BW8: =IF(Stock_Connector!D8="","",Stock_Connector!D8) -> 0.010400552 | BY8: =Y8 | BZ8: =AB8 | CA8: =IFERROR(VLOOKUP($BY8,Account_Value!$C$2:$F$2500,4,0),"") | CB8: =IF(BZ8="","",BZ8*CA8) | CC8: =IF($BZ8="","",SUM($BZ$2:$BZ8)) | CD8: =IF($BZ8="","",$CA8*(SUM($BZ$2:$BZ8)))
A9: =IF($B9="","",$A8+1) | B9: =IF(Investments_Import!A9="","",Investments_Import!A9) | C9: =IF(B9="","",B9*1) | D9: =$C9 | E9: =IF(Investments_Import!B9="","",Investments_Import!B9) | F9: =CONCATENATE(TEXT($D9,"dd-mmm-yyyy")," ",$E9) | G9: =IF($B9="","",COUNTIF($F$2:$F9,$F9)) | H9: =CONCATENATE(TEXT($D9,"dd-mmm-yyyy")," ",$E9," ",$G9) | I9: =IF(Investments_Import!C9="","",Investments_Import!C9) | J9: =IF(Investments_Import!D9="","",Investments_Import!D9) | K9: =IF($B9="","",$J9*1) | L9: =IF(Investments_Import!E9="","",Investments_Import!E9) | M9: =IF($L9="","",$L9*1) | N9: =IF(Investments_Import!F9="","",Investments_Import!F9) | O9: =IF($N9="","",$N9*1) | P9: =IF(Investments_Import!G9="","",Investments_Import!G9) | Q9: =IF(Investments_Import!H9="","",Investments_Import!H9) | R9: =IF($Q9="","",IF($Q9="USD",$P9,$P9*$J9)) | S9: =IF($R9="","",$R9*1) | U9: =IF(Mining_Import!A9="","",Mining_Import!A9) | V9: =IF(U9="","",U9*1) | W9: =V9 | X9: =IFERROR(INT($W9),"") | Y9: =$X9 | Z9: =IF(Mining_Import!B9="","",Mining_Import!B9) | AA9: =IF(Mining_Import!$C9="","",Mining_Import!$C9) | AB9: =IFERROR($AA9*1,"") | AC9: =IF($Y9>Dashboard!$Q$19,$AB9,"") | AD9: =IFERROR($AB9*$BU$19,"") | AE9: =IF(Mining_Import!D9="","",Mining_Import!D9) | AF9: =IF(Mining_Import!E9="","",Mining_Import!E9) | AG9: =IF(Mining_Import!F9="","",Mining_Import!F9) | AH9: =IF(Mining_Import!G9="","",Mining_Import!G9) | AI9: =IF(Mining_Import!H9="","",Mining_Import!H9) | AJ9: =IF(Mining_Import!I9="","",Mining_Import!I9) | AL9: =IFERROR(INDEX($E$2:$E$2500, MATCH(0, INDEX(COUNTIF($AL$1:AL8, $E$2:$E$2500), 0, 0), 0)), "") | AM9: =IF(Calculator!$AL9="","",LEFT(Calculator!$AL9, LEN(Calculator!$AL9)-3)) | AN9: {=IF($AL9="","",MAX(IF($E$2:$E$2500=$AL9,$C$2:$C$2500)))} | AO9: =IF($AN9="","",(TEXT($AN9,"dd-mmm-yyyy")&" "&$AL9&" "&"1")) | AP9: =$AO9 | AQ9: =IF($AL9="","",VLOOKUP($AO9, $H:$K, 3, 0)) | AR9: =IF($AQ9="","",$AQ9*1) | AS9: =IF($AL9="","",SUMIFS($O:$O,$E:$E,$AL9,$I:$I,"BUY")) | AT9: =IF($AL9="","",SUMIFS($O:$O,$E:$E,$AL9,$I:$I,"SELL")) | AU9: =IF($AL9="","",SUMIF($E:$E,$AL9,$S:$S)) | AV9: =IF($AL9="","",SUMIFS($M:$M,$E:$E,$AL9,$I:$I,"BUY")) | AW9: =IF($AL9="","",SUMIFS($M:$M,$E:$E,$AL9,$I:$I,"SELL")) | AX9: =IF($AZ9=1,$AV9-$AW9,"") | AY9: =$AM9 | AZ9: =IF($AY9="","",IFERROR(VLOOKUP($AP9,$BG$2:$BH$13,2, FALSE),"")) | BA9: =IF($AZ9=1, "CURRENT","") | BB9: =IF($AW9=0,"",IFERROR($AS9-$BD9,"")) | BC9: =IFERROR(IF($BA9="CURRENT",(($AT9-$BB9)-$AU9),IF($AW9=0,"",($AT9-$AS9)-$AU9)),"") | BD9: =IF($BA9="CURRENT",($AX9*$AR9),"") | BF9: =CONCATENATE(TEXT(Dashboard!$Q15,"dd-mmm-yyyy")," ",Dashboard!$P15,"USD"," ",1) -> 00-Jan-1900 USD 1 | BG9: =IF($BF9="00-Jan-1900 USD 1","",$BF9) | BH9: 1 | BR9: https://coinmarketcap.com/currencies/omg/ | BS9: =IF(Stock_Connector!B9="","",Stock_Connector!B9) -> OMG | BT9: =IF(Stock_Connector!C9="","",Stock_Connector!C9) -> 4.745 | BU9: =IF(Stock_Connector!C9="","",Stock_Connector!C9) -> 4.745 | BV9: =IF(Stock_Connector!E9="","",Stock_Connector!E9) | BW9: =IF(Stock_Connector!D9="","",Stock_Connector!D9) -> -0.014742525 | BY9: =Y9 | BZ9: =AB9 | CA9: =IFERROR(VLOOKUP($BY9,Account_Value!$C$2:$F$2500,4,0),"") | CB9: =IF(BZ9="","",BZ9*CA9) | CC9: =IF($BZ9="","",SUM($BZ$2:$BZ9)) | CD9: =IF($BZ9="","",$CA9*(SUM($BZ$2:$BZ9)))
A10: =IF($B10="","",$A9+1) | B10: =IF(Investments_Import!A10="","",Investments_Import!A10) | C10: =IF(B10="","",B10*1) | D10: =$C10 | E10: =IF(Investments_Import!B10="","",Investments_Import!B10) | F10: =CONCATENATE(TEXT($D10,"dd-mmm-yyyy")," ",$E10) | G10: =IF($B10="","",COUNTIF($F$2:$F10,$F10)) | H10: =CONCATENATE(TEXT($D10,"dd-mmm-yyyy")," ",$E10," ",$G10) | I10: =IF(Investments_Import!C10="","",Investments_Import!C10) | J10: =IF(Investments_Import!D10="","",Investments_Import!D10) | K10: =IF($B10="","",$J10*1) | L10: =IF(Investments_Import!E10="","",Investments_Import!E10) | M10: =IF($L10="","",$L10*1) | N10: =IF(Investments_Import!F10="","",Investments_Import!F10) | O10: =IF($N10="","",$N10*1) | P10: =IF(Investments_Import!G10="","",Investments_Import!G10) | Q10: =IF(Investments_Import!H10="","",Investments_Import!H10) | R10: =IF($Q10="","",IF($Q10="USD",$P10,$P10*$J10)) | S10: =IF($R10="","",$R10*1) | U10: =IF(Mining_Import!A10="","",Mining_Import!A10) | V10: =IF(U10="","",U10*1) | W10: =V10 | X10: =IFERROR(INT($W10),"") | Y10: =$X10 | Z10: =IF(Mining_Import!B10="","",Mining_Import!B10) | AA10: =IF(Mining_Import!$C10="","",Mining_Import!$C10) | AB10: =IFERROR($AA10*1,"") | AC10: =IF($Y10>Dashboard!$Q$19,$AB10,"") | AD10: =IFERROR($AB10*$BU$19,"") | AE10: =IF(Mining_Import!D10="","",Mining_Import!D10) | AF10: =IF(Mining_Import!E10="","",Mining_Import!E10) | AG10: =IF(Mining_Import!F10="","",Mining_Import!F10) | AH10: =IF(Mining_Import!G10="","",Mining_Import!G10) | AI10: =IF(Mining_Import!H10="","",Mining_Import!H10) | AJ10: =IF(Mining_Import!I10="","",Mining_Import!I10) | AL10: =IFERROR(INDEX($E$2:$E$2500, MATCH(0, INDEX(COUNTIF($AL$1:AL9, $E$2:$E$2500), 0, 0), 0)), "") | AM10: =IF(Calculator!$AL10="","",LEFT(Calculator!$AL10, LEN(Calculator!$AL10)-3)) | AN10: {=IF($AL10="","",MAX(IF($E$2:$E$2500=$AL10,$C$2:$C$2500)))} | AO10: =IF($AN10="","",(TEXT($AN10,"dd-mmm-yyyy")&" "&$AL10&" "&"1")) | AP10: =$AO10 | AQ10: =IF($AL10="","",VLOOKUP($AO10, $H:$K, 3, 0)) | AR10: =IF($AQ10="","",$AQ10*1) | AS10: =IF($AL10="","",SUMIFS($O:$O,$E:$E,$AL10,$I:$I,"BUY")) | AT10: =IF($AL10="","",SUMIFS($O:$O,$E:$E,$AL10,$I:$I,"SELL")) | AU10: =IF($AL10="","",SUMIF($E:$E,$AL10,$S:$S)) | AV10: =IF($AL10="","",SUMIFS($M:$M,$E:$E,$AL10,$I:$I,"BUY")) | AW10: =IF($AL10="","",SUMIFS($M:$M,$E:$E,$AL10,$I:$I,"SELL")) | AX10: =IF($AZ10=1,$AV10-$AW10,"") | AY10: =$AM10 | AZ10: =IF($AY10="","",IFERROR(VLOOKUP($AP10,$BG$2:$BH$13,2, FALSE),"")) | BA10: =IF($AZ10=1, "CURRENT","") | BB10: =IF($AW10=0,"",IFERROR($AS10-$BD10,"")) | BC10: =IFERROR(IF($BA10="CURRENT",(($AT10-$BB10)-$AU10),IF($AW10=0,"",($AT10-$AS10)-$AU10)),"") | BD10: =IF($BA10="CURRENT",($AX10*$AR10),"") | BF10: =CONCATENATE(TEXT(Dashboard!$Q16,"dd-mmm-yyyy")," ",Dashboard!$P16,"USD"," ",1) -> 00-Jan-1900 USD 1 | BG10: =IF($BF10="00-Jan-1900 USD 1","",$BF10) | BH10: 1 | BR10: https://coinmarketcap.com/currencies/cosmos/ | BS10: =IF(Stock_Connector!B10="","",Stock_Connector!B10) -> ATOM | BT10: =IF(Stock_Connector!C10="","",Stock_Connector!C10) -> 13.28 | BU10: =IF(Stock_Connector!C10="","",Stock_Connector!C10) -> 13.28 | BV10: =IF(Stock_Connector!E10="","",Stock_Connector!E10) | BW10: =IF(Stock_Connector!D10="","",Stock_Connector!D10) -> 0.15478261 | BY10: =Y10 | BZ10: =AB10 | CA10: =IFERROR(VLOOKUP($BY10,Account_Value!$C$2:$F$2500,4,0),"") | CB10: =IF(BZ10="","",BZ10*CA10) | CC10: =IF($BZ10="","",SUM($BZ$2:$BZ10)) | CD10: =IF($BZ10="","",$CA10*(SUM($BZ$2:$BZ10)))
A11: =IF($B11="","",$A10+1) | B11: =IF(Investments_Import!A11="","",Investments_Import!A11) | C11: =IF(B11="","",B11*1) | D11: =$C11 | E11: =IF(Investments_Import!B11="","",Investments_Import!B11) | F11: =CONCATENATE(TEXT($D11,"dd-mmm-yyyy")," ",$E11) | G11: =IF($B11="","",COUNTIF($F$2:$F11,$F11)) | H11: =CONCATENATE(TEXT($D11,"dd-mmm-yyyy")," ",$E11," ",$G11) | I11: =IF(Investments_Import!C11="","",Investments_Import!C11) | J11: =IF(Investments_Import!D11="","",Investments_Import!D11) | K11: =IF($B11="","",$J11*1) | L11: =IF(Investments_Import!E11="","",Investments_Import!E11) | M11: =IF($L11="","",$L11*1) | N11: =IF(Investments_Import!F11="","",Investments_Import!F11) | O11: =IF($N11="","",$N11*1) | P11: =IF(Investments_Import!G11="","",Investments_Import!G11) | Q11: =IF(Investments_Import!H11="","",Investments_Import!H11) | R11: =IF($Q11="","",IF($Q11="USD",$P11,$P11*$J11)) | S11: =IF($R11="","",$R11*1) | U11: =IF(Mining_Import!A11="","",Mining_Import!A11) | V11: =IF(U11="","",U11*1) | W11: =V11 | X11: =IFERROR(INT($W11),"") | Y11: =$X11 | Z11: =IF(Mining_Import!B11="","",Mining_Import!B11) | AA11: =IF(Mining_Import!$C11="","",Mining_Import!$C11) | AB11: =IFERROR($AA11*1,"") | AC11: =IF($Y11>Dashboard!$Q$19,$AB11,"") | AD11: =IFERROR($AB11*$BU$19,"") | AE11: =IF(Mining_Import!D11="","",Mining_Import!D11) | AF11: =IF(Mining_Import!E11="","",Mining_Import!E11) | AG11: =IF(Mining_Import!F11="","",Mining_Import!F11) | AH11: =IF(Mining_Import!G11="","",Mining_Import!G11) | AI11: =IF(Mining_Import!H11="","",Mining_Import!H11) | AJ11: =IF(Mining_Import!I11="","",Mining_Import!I11) | AL11: =IFERROR(INDEX($E$2:$E$2500, MATCH(0, INDEX(COUNTIF($AL$1:AL10, $E$2:$E$2500), 0, 0), 0)), "") | AM11: =IF(Calculator!$AL11="","",LEFT(Calculator!$AL11, LEN(Calculator!$AL11)-3)) | AN11: {=IF($AL11="","",MAX(IF($E$2:$E$2500=$AL11,$C$2:$C$2500)))} | AO11: =IF($AN11="","",(TEXT($AN11,"dd-mmm-yyyy")&" "&$AL11&" "&"1")) | AP11: =$AO11 | AQ11: =IF($AL11="","",VLOOKUP($AO11, $H:$K, 3, 0)) | AR11: =IF($AQ11="","",$AQ11*1) | AS11: =IF($AL11="","",SUMIFS($O:$O,$E:$E,$AL11,$I:$I,"BUY")) | AT11: =IF($AL11="","",SUMIFS($O:$O,$E:$E,$AL11,$I:$I,"SELL")) | AU11: =IF($AL11="","",SUMIF($E:$E,$AL11,$S:$S)) | AV11: =IF($AL11="","",SUMIFS($M:$M,$E:$E,$AL11,$I:$I,"BUY")) | AW11: =IF($AL11="","",SUMIFS($M:$M,$E:$E,$AL11,$I:$I,"SELL")) | AX11: =IF($AZ11=1,$AV11-$AW11,"") | AY11: =$AM11 | AZ11: =IF($AY11="","",IFERROR(VLOOKUP($AP11,$BG$2:$BH$13,2, FALSE),"")) | BA11: =IF($AZ11=1, "CURRENT","") | BB11: =IF($AW11=0,"",IFERROR($AS11-$BD11,"")) | BC11: =IFERROR(IF($BA11="CURRENT",(($AT11-$BB11)-$AU11),IF($AW11=0,"",($AT11-$AS11)-$AU11)),"") | BD11: =IF($BA11="CURRENT",($AX11*$AR11),"") | BF11: =CONCATENATE(TEXT(Dashboard!$Q17,"dd-mmm-yyyy")," ",Dashboard!$P17,"USD"," ",1) -> 00-Jan-1900 USD 1 | BG11: =IF($BF11="00-Jan-1900 USD 1","",$BF11) | BH11: 1 | BR11: https://coinmarketcap.com/currencies/chainlink/ | BS11: =IF(Stock_Connector!B11="","",Stock_Connector!B11) -> LINK | BT11: =IF(Stock_Connector!C11="","",Stock_Connector!C11) -> 24.69 | BU11: =IF(Stock_Connector!C11="","",Stock_Connector!C11) -> 24.69 | BV11: =IF(Stock_Connector!E11="","",Stock_Connector!E11) | BW11: =IF(Stock_Connector!D11="","",Stock_Connector!D11) -> -0.016334661 | BY11: =Y11 | BZ11: =AB11 | CA11: =IFERROR(VLOOKUP($BY11,Account_Value!$C$2:$F$2500,4,0),"") | CB11: =IF(BZ11="","",BZ11*CA11) | CC11: =IF($BZ11="","",SUM($BZ$2:$BZ11)) | CD11: =IF($BZ11="","",$CA11*(SUM($BZ$2:$BZ11)))
A12: =IF($B12="","",$A11+1) | B12: =IF(Investments_Import!A12="","",Investments_Import!A12) | C12: =IF(B12="","",B12*1) | D12: =$C12 | E12: =IF(Investments_Import!B12="","",Investments_Import!B12) | F12: =CONCATENATE(TEXT($D12,"dd-mmm-yyyy")," ",$E12) | G12: =IF($B12="","",COUNTIF($F$2:$F12,$F12)) | H12: =CONCATENATE(TEXT($D12,"dd-mmm-yyyy")," ",$E12," ",$G12) | I12: =IF(Investments_Import!C12="","",Investments_Import!C12) | J12: =IF(Investments_Import!D12="","",Investments_Import!D12) | K12: =IF($B12="","",$J12*1) | L12: =IF(Investments_Import!E12="","",Investments_Import!E12) | M12: =IF($L12="","",$L12*1) | N12: =IF(Investments_Import!F12="","",Investments_Import!F12) | O12: =IF($N12="","",$N12*1) | P12: =IF(Investments_Import!G12="","",Investments_Import!G12) | Q12: =IF(Investments_Import!H12="","",Investments_Import!H12) | R12: =IF($Q12="","",IF($Q12="USD",$P12,$P12*$J12)) | S12: =IF($R12="","",$R12*1) | U12: =IF(Mining_Import!A12="","",Mining_Import!A12) | V12: =IF(U12="","",U12*1) | W12: =V12 | X12: =IFERROR(INT($W12),"") | Y12: =$X12 | Z12: =IF(Mining_Import!B12="","",Mining_Import!B12) | AA12: =IF(Mining_Import!$C12="","",Mining_Import!$C12) | AB12: =IFERROR($AA12*1,"") | AC12: =IF($Y12>Dashboard!$Q$19,$AB12,"") | AD12: =IFERROR($AB12*$BU$19,"") | AE12: =IF(Mining_Import!D12="","",Mining_Import!D12) | AF12: =IF(Mining_Import!E12="","",Mining_Import!E12) | AG12: =IF(Mining_Import!F12="","",Mining_Import!F12) | AH12: =IF(Mining_Import!G12="","",Mining_Import!G12) | AI12: =IF(Mining_Import!H12="","",Mining_Import!H12) | AJ12: =IF(Mining_Import!I12="","",Mining_Import!I12) | AL12: =IFERROR(INDEX($E$2:$E$2500, MATCH(0, INDEX(COUNTIF($AL$1:AL11, $E$2:$E$2500), 0, 0), 0)), "") | AM12: =IF(Calculator!$AL12="","",LEFT(Calculator!$AL12, LEN(Calculator!$AL12)-3)) | AN12: {=IF($AL12="","",MAX(IF($E$2:$E$2500=$AL12,$C$2:$C$2500)))} | AO12: =IF($AN12="","",(TEXT($AN12,"dd-mmm-yyyy")&" "&$AL12&" "&"1")) | AP12: =$AO12 | AQ12: =IF($AL12="","",VLOOKUP($AO12, $H:$K, 3, 0)) | AR12: =IF($AQ12="","",$AQ12*1) | AS12: =IF($AL12="","",SUMIFS($O:$O,$E:$E,$AL12,$I:$I,"BUY")) | AT12: =IF($AL12="","",SUMIFS($O:$O,$E:$E,$AL12,$I:$I,"SELL")) | AU12: =IF($AL12="","",SUMIF($E:$E,$AL12,$S:$S)) | AV12: =IF($AL12="","",SUMIFS($M:$M,$E:$E,$AL12,$I:$I,"BUY")) | AW12: =IF($AL12="","",SUMIFS($M:$M,$E:$E,$AL12,$I:$I,"SELL")) | AX12: =IF($AZ12=1,$AV12-$AW12,"") | AY12: =$AM12 | AZ12: =IF($AY12="","",IFERROR(VLOOKUP($AP12,$BG$2:$BH$13,2, FALSE),"")) | BA12: =IF($AZ12=1, "CURRENT","") | BB12: =IF($AW12=0,"",IFERROR($AS12-$BD12,"")) | BC12: =IFERROR(IF($BA12="CURRENT",(($AT12-$BB12)-$AU12),IF($AW12=0,"",($AT12-$AS12)-$AU12)),"") | BD12: =IF($BA12="CURRENT",($AX12*$AR12),"") | BF12: =CONCATENATE(TEXT(Dashboard!$Q18,"dd-mmm-yyyy")," ",Dashboard!$P18,"USD"," ",1) -> 00-Jan-1900 USD 1 | BG12: =IF($BF12="00-Jan-1900 USD 1","",$BF12) | BH12: 1 | BS12: =IF(Stock_Connector!B12="","",Stock_Connector!B12) -> REP | BT12: =IF(Stock_Connector!C12="","",Stock_Connector!C12) -> 22.79 | BU12: =IF(Stock_Connector!C12="","",Stock_Connector!C12) -> 22.79 | BV12: =IF(Stock_Connector!E12="","",Stock_Connector!E12) | BW12: =IF(Stock_Connector!D12="","",Stock_Connector!D12) -> 0.031688547 | BY12: =Y12 | BZ12: =AB12 | CA12: =IFERROR(VLOOKUP($BY12,Account_Value!$C$2:$F$2500,4,0),"") | CB12: =IF(BZ12="","",BZ12*CA12) | CC12: =IF($BZ12="","",SUM($BZ$2:$BZ12)) | CD12: =IF($BZ12="","",$CA12*(SUM($BZ$2:$BZ12)))
A13: =IF($B13="","",$A12+1) | B13: =IF(Investments_Import!A13="","",Investments_Import!A13) | C13: =IF(B13="","",B13*1) | D13: =$C13 | E13: =IF(Investments_Import!B13="","",Investments_Import!B13) | F13: =CONCATENATE(TEXT($D13,"dd-mmm-yyyy")," ",$E13) | G13: =IF($B13="","",COUNTIF($F$2:$F13,$F13)) | H13: =CONCATENATE(TEXT($D13,"dd-mmm-yyyy")," ",$E13," ",$G13) | I13: =IF(Investments_Import!C13="","",Investments_Import!C13) | J13: =IF(Investments_Import!D13="","",Investments_Import!D13) | K13: =IF($B13="","",$J13*1) | L13: =IF(Investments_Import!E13="","",Investments_Import!E13) | M13: =IF($L13="","",$L13*1) | N13: =IF(Investments_Import!F13="","",Investments_Import!F13) | O13: =IF($N13="","",$N13*1) | P13: =IF(Investments_Import!G13="","",Investments_Import!G13) | Q13: =IF(Investments_Import!H13="","",Investments_Import!H13) | R13: =IF($Q13="","",IF($Q13="USD",$P13,$P13*$J13)) | S13: =IF($R13="","",$R13*1) | U13: =IF(Mining_Import!A13="","",Mining_Import!A13) | V13: =IF(U13="","",U13*1) | W13: =V13 | X13: =IFERROR(INT($W13),"") | Y13: =$X13 | Z13: =IF(Mining_Import!B13="","",Mining_Import!B13) | AA13: =IF(Mining_Import!$C13="","",Mining_Import!$C13) | AB13: =IFERROR($AA13*1,"") | AC13: =IF($Y13>Dashboard!$Q$19,$AB13,"") | AD13: =IFERROR($AB13*$BU$19,"") | AE13: =IF(Mining_Import!D13="","",Mining_Import!D13) | AF13: =IF(Mining_Import!E13="","",Mining_Import!E13) | AG13: =IF(Mining_Import!F13="","",Mining_Import!F13) | AH13: =IF(Mining_Import!G13="","",Mining_Import!G13) | AI13: =IF(Mining_Import!H13="","",Mining_Import!H13) | AJ13: =IF(Mining_Import!I13="","",Mining_Import!I13) | AL13: =IFERROR(INDEX($E$2:$E$2500, MATCH(0, INDEX(COUNTIF($AL$1:AL12, $E$2:$E$2500), 0, 0), 0)), "") | AM13: =IF(Calculator!$AL13="","",LEFT(Calculator!$AL13, LEN(Calculator!$AL13)-3)) | AN13: {=IF($AL13="","",MAX(IF($E$2:$E$2500=$AL13,$C$2:$C$2500)))} | AO13: =IF($AN13="","",(TEXT($AN13,"dd-mmm-yyyy")&" "&$AL13&" "&"1")) | AP13: =$AO13 | AQ13: =IF($AL13="","",VLOOKUP($AO13, $H:$K, 3, 0)) | AR13: =IF($AQ13="","",$AQ13*1) | AS13: =IF($AL13="","",SUMIFS($O:$O,$E:$E,$AL13,$I:$I,"BUY")) | AT13: =IF($AL13="","",SUMIFS($O:$O,$E:$E,$AL13,$I:$I,"SELL")) | AU13: =IF($AL13="","",SUMIF($E:$E,$AL13,$S:$S)) | AV13: =IF($AL13="","",SUMIFS($M:$M,$E:$E,$AL13,$I:$I,"BUY")) | AW13: =IF($AL13="","",SUMIFS($M:$M,$E:$E,$AL13,$I:$I,"SELL")) | AX13: =IF($AZ13=1,$AV13-$AW13,"") | AY13: =$AM13 | AZ13: =IF($AY13="","",IFERROR(VLOOKUP($AP13,$BG$2:$BH$13,2, FALSE),"")) | BA13: =IF($AZ13=1, "CURRENT","") | BB13: =IF($AW13=0,"",IFERROR($AS13-$BD13,"")) | BC13: =IFERROR(IF($BA13="CURRENT",(($AT13-$BB13)-$AU13),IF($AW13=0,"",($AT13-$AS13)-$AU13)),"") | BD13: =IF($BA13="CURRENT",($AX13*$AR13),"") | BF13: =CONCATENATE(TEXT(Dashboard!$Q19,"dd-mmm-yyyy")," ",Dashboard!$P19,"USD"," ",1) -> 00-Jan-1900 ETHUSD 1 | BG13: =IF($BF13="00-Jan-1900 USD 1","",$BF13) -> 00-Jan-1900 ETHUSD 1 | BH13: 1 | BR13: https://coinmarketcap.com/currencies/matic-network/ | BS13: =IF(Stock_Connector!B13="","",Stock_Connector!B13) -> MATIC | BT13: =IF(Stock_Connector!C13="","",Stock_Connector!C13) -> 0.05287282 | BU13: =IF(Stock_Connector!C13="","",Stock_Connector!C13) -> 0.05287282 | BV13: =IF(Stock_Connector!E13="","",Stock_Connector!E13) | BW13: =IF(Stock_Connector!D13="","",Stock_Connector!D13) -> 0.048009641 | BY13: =Y13 | BZ13: =AB13 | CA13: =IFERROR(VLOOKUP($BY13,Account_Value!$C$2:$F$2500,4,0),"") | CB13: =IF(BZ13="","",BZ13*CA13) | CC13: =IF($BZ13="","",SUM($BZ$2:$BZ13)) | CD13: =IF($BZ13="","",$CA13*(SUM($BZ$2:$BZ13)))
A14: =IF($B14="","",$A13+1) | B14: =IF(Investments_Import!A14="","",Investments_Import!A14) | C14: =IF(B14="","",B14*1) | D14: =$C14 | E14: =IF(Investments_Import!B14="","",Investments_Import!B14) | F14: =CONCATENATE(TEXT($D14,"dd-mmm-yyyy")," ",$E14) | G14: =IF($B14="","",COUNTIF($F$2:$F14,$F14)) | H14: =CONCATENATE(TEXT($D14,"dd-mmm-yyyy")," ",$E14," ",$G14) | I14: =IF(Investments_Import!C14="","",Investments_Import!C14) | J14: =IF(Investments_Import!D14="","",Investments_Import!D14) | K14: =IF($B14="","",$J14*1) | L14: =IF(Investments_Import!E14="","",Investments_Import!E14) | M14: =IF($L14="","",$L14*1) | N14: =IF(Investments_Import!F14="","",Investments_Import!F14) | O14: =IF($N14="","",$N14*1) | P14: =IF(Investments_Import!G14="","",Investments_Import!G14) | Q14: =IF(Investments_Import!H14="","",Investments_Import!H14) | R14: =IF($Q14="","",IF($Q14="USD",$P14,$P14*$J14)) | S14: =IF($R14="","",$R14*1) | U14: =IF(Mining_Import!A14="","",Mining_Import!A14) | V14: =IF(U14="","",U14*1) | W14: =V14 | X14: =IFERROR(INT($W14),"") | Y14: =$X14 | Z14: =IF(Mining_Import!B14="","",Mining_Import!B14) | AA14: =IF(Mining_Import!$C14="","",Mining_Import!$C14) | AB14: =IFERROR($AA14*1,"") | AC14: =IF($Y14>Dashboard!$Q$19,$AB14,"") | AD14: =IFERROR($AB14*$BU$19,"") | AE14: =IF(Mining_Import!D14="","",Mining_Import!D14) | AF14: =IF(Mining_Import!E14="","",Mining_Import!E14) | AG14: =IF(Mining_Import!F14="","",Mining_Import!F14) | AH14: =IF(Mining_Import!G14="","",Mining_Import!G14) | AI14: =IF(Mining_Import!H14="","",Mining_Import!H14) | AJ14: =IF(Mining_Import!I14="","",Mining_Import!I14) | AL14: =IFERROR(INDEX($E$2:$E$2500, MATCH(0, INDEX(COUNTIF($AL$1:AL13, $E$2:$E$2500), 0, 0), 0)), "") | AM14: =IF(Calculator!$AL14="","",LEFT(Calculator!$AL14, LEN(Calculator!$AL14)-3)) | AN14: {=IF($AL14="","",MAX(IF($E$2:$E$2500=$AL14,$C$2:$C$2500)))} | AO14: =IF($AN14="","",(TEXT($AN14,"dd-mmm-yyyy")&" "&$AL14&" "&"1")) | AP14: =$AO14 | AQ14: =IF($AL14="","",VLOOKUP($AO14, $H:$K, 3, 0)) | AR14: =IF($AQ14="","",$AQ14*1) | AS14: =IF($AL14="","",SUMIFS($O:$O,$E:$E,$AL14,$I:$I,"BUY")) | AT14: =IF($AL14="","",SUMIFS($O:$O,$E:$E,$AL14,$I:$I,"SELL")) | AU14: =IF($AL14="","",SUMIF($E:$E,$AL14,$S:$S)) | AV14: =IF($AL14="","",SUMIFS($M:$M,$E:$E,$AL14,$I:$I,"BUY")) | AW14: =IF($AL14="","",SUMIFS($M:$M,$E:$E,$AL14,$I:$I,"SELL")) | AX14: =IF($AZ14=1,$AV14-$AW14,"") | AY14: =$AM14 | AZ14: =IF($AY14="","",IFERROR(VLOOKUP($AP14,$BG$2:$BH$13,2, FALSE),"")) | BA14: =IF($AZ14=1, "CURRENT","") | BB14: =IF($AW14=0,"",IFERROR($AS14-$BD14,"")) | BC14: =IFERROR(IF($BA14="CURRENT",(($AT14-$BB14)-$AU14),IF($AW14=0,"",($AT14-$AS14)-$AU14)),"") | BD14: =IF($BA14="CURRENT",($AX14*$AR14),"") | BR14: https://coinmarketcap.com/currencies/ravencoin/ | BS14: =IF(Stock_Connector!B14="","",Stock_Connector!B14) -> RVN | BT14: =IF(Stock_Connector!C14="","",Stock_Connector!C14) -> 0.03009006 | BU14: =IF(Stock_Connector!C14="","",Stock_Connector!C14) -> 0.03009006 | BV14: =IF(Stock_Connector!E14="","",Stock_Connector!E14) | BW14: =IF(Stock_Connector!D14="","",Stock_Connector!D14) -> 0.062256809 | BY14: =Y14 | BZ14: =AB14 | CA14: =IFERROR(VLOOKUP($BY14,Account_Value!$C$2:$F$2500,4,0),"") | CB14: =IF(BZ14="","",BZ14*CA14) | CC14: =IF($BZ14="","",SUM($BZ$2:$BZ14)) | CD14: =IF($BZ14="","",$CA14*(SUM($BZ$2:$BZ14)))
A15: =IF($B15="","",$A14+1) | B15: =IF(Investments_Import!A15="","",Investments_Import!A15) | C15: =IF(B15="","",B15*1) | D15: =$C15 | E15: =IF(Investments_Import!B15="","",Investments_Import!B15) | F15: =CONCATENATE(TEXT($D15,"dd-mmm-yyyy")," ",$E15) | G15: =IF($B15="","",COUNTIF($F$2:$F15,$F15)) | H15: =CONCATENATE(TEXT($D15,"dd-mmm-yyyy")," ",$E15," ",$G15) | I15: =IF(Investments_Import!C15="","",Investments_Import!C15) | J15: =IF(Investments_Import!D15="","",Investments_Import!D15) | K15: =IF($B15="","",$J15*1) | L15: =IF(Investments_Import!E15="","",Investments_Import!E15) | M15: =IF($L15="","",$L15*1) | N15: =IF(Investments_Import!F15="","",Investments_Import!F15) | O15: =IF($N15="","",$N15*1) | P15: =IF(Investments_Import!G15="","",Investments_Import!G15) | Q15: =IF(Investments_Import!H15="","",Investments_Import!H15) | R15: =IF($Q15="","",IF($Q15="USD",$P15,$P15*$J15)) | S15: =IF($R15="","",$R15*1) | U15: =IF(Mining_Import!A15="","",Mining_Import!A15) | V15: =IF(U15="","",U15*1) | W15: =V15 | X15: =IFERROR(INT($W15),"") | Y15: =$X15 | Z15: =IF(Mining_Import!B15="","",Mining_Import!B15) | AA15: =IF(Mining_Import!$C15="","",Mining_Import!$C15) | AB15: =IFERROR($AA15*1,"") | AC15: =IF($Y15>Dashboard!$Q$19,$AB15,"") | AD15: =IFERROR($AB15*$BU$19,"") | AE15: =IF(Mining_Import!D15="","",Mining_Import!D15) | AF15: =IF(Mining_Import!E15="","",Mining_Import!E15) | AG15: =IF(Mining_Import!F15="","",Mining_Import!F15) | AH15: =IF(Mining_Import!G15="","",Mining_Import!G15) | AI15: =IF(Mining_Import!H15="","",Mining_Import!H15) | AJ15: =IF(Mining_Import!I15="","",Mining_Import!I15) | AL15: =IFERROR(INDEX($E$2:$E$2500, MATCH(0, INDEX(COUNTIF($AL$1:AL14, $E$2:$E$2500), 0, 0), 0)), "") | AM15: =IF(Calculator!$AL15="","",LEFT(Calculator!$AL15, LEN(Calculator!$AL15)-3)) | AN15: {=IF($AL15="","",MAX(IF($E$2:$E$2500=$AL15,$C$2:$C$2500)))} | AO15: =IF($AN15="","",(TEXT($AN15,"dd-mmm-yyyy")&" "&$AL15&" "&"1")) | AP15: =$AO15 | AQ15: =IF($AL15="","",VLOOKUP($AO15, $H:$K, 3, 0)) | AR15: =IF($AQ15="","",$AQ15*1) | AS15: =IF($AL15="","",SUMIFS($O:$O,$E:$E,$AL15,$I:$I,"BUY")) | AT15: =IF($AL15="","",SUMIFS($O:$O,$E:$E,$AL15,$I:$I,"SELL")) | AU15: =IF($AL15="","",SUMIF($E:$E,$AL15,$S:$S)) | AV15: =IF($AL15="","",SUMIFS($M:$M,$E:$E,$AL15,$I:$I,"BUY")) | AW15: =IF($AL15="","",SUMIFS($M:$M,$E:$E,$AL15,$I:$I,"SELL")) | AX15: =IF($AZ15=1,$AV15-$AW15,"") | AY15: =$AM15 | AZ15: =IF($AY15="","",IFERROR(VLOOKUP($AP15,$BG$2:$BH$13,2, FALSE),"")) | BA15: =IF($AZ15=1, "CURRENT","") | BB15: =IF($AW15=0,"",IFERROR($AS15-$BD15,"")) | BC15: =IFERROR(IF($BA15="CURRENT",(($AT15-$BB15)-$AU15),IF($AW15=0,"",($AT15-$AS15)-$AU15)),"") | BD15: =IF($BA15="CURRENT",($AX15*$AR15),"") | BR15: https://coinmarketcap.com/currencies/zilliqa/ | BS15: =IF(Stock_Connector!B15="","",Stock_Connector!B15) -> ZIL | BT15: =IF(Stock_Connector!C15="","",Stock_Connector!C15) -> 0.07882875 | BU15: =IF(Stock_Connector!C15="","",Stock_Connector!C15) -> 0.07882875 | BV15: =IF(Stock_Connector!E15="","",Stock_Connector!E15) | BW15: =IF(Stock_Connector!D15="","",Stock_Connector!D15) -> 0.011070649 | BY15: =Y15 | BZ15: =AB15 | CA15: =IFERROR(VLOOKUP($BY15,Account_Value!$C$2:$F$2500,4,0),"") | CB15: =IF(BZ15="","",BZ15*CA15) | CC15: =IF($BZ15="","",SUM($BZ$2:$BZ15)) | CD15: =IF($BZ15="","",$CA15*(SUM($BZ$2:$BZ15)))
A16: =IF($B16="","",$A15+1) | B16: =IF(Investments_Import!A16="","",Investments_Import!A16) | C16: =IF(B16="","",B16*1) | D16: =$C16 | E16: =IF(Investments_Import!B16="","",Investments_Import!B16) | F16: =CONCATENATE(TEXT($D16,"dd-mmm-yyyy")," ",$E16) | G16: =IF($B16="","",COUNTIF($F$2:$F16,$F16)) | H16: =CONCATENATE(TEXT($D16,"dd-mmm-yyyy")," ",$E16," ",$G16) | I16: =IF(Investments_Import!C16="","",Investments_Import!C16) | J16: =IF(Investments_Import!D16="","",Investments_Import!D16) | K16: =IF($B16="","",$J16*1) | L16: =IF(Investments_Import!E16="","",Investments_Import!E16) | M16: =IF($L16="","",$L16*1) | N16: =IF(Investments_Import!F16="","",Investments_Import!F16) | O16: =IF($N16="","",$N16*1) | P16: =IF(Investments_Import!G16="","",Investments_Import!G16) | Q16: =IF(Investments_Import!H16="","",Investments_Import!H16) | R16: =IF($Q16="","",IF($Q16="USD",$P16,$P16*$J16)) | S16: =IF($R16="","",$R16*1) | U16: =IF(Mining_Import!A16="","",Mining_Import!A16) | V16: =IF(U16="","",U16*1) | W16: =V16 | X16: =IFERROR(INT($W16),"") | Y16: =$X16 | Z16: =IF(Mining_Import!B16="","",Mining_Import!B16) | AA16: =IF(Mining_Import!$C16="","",Mining_Import!$C16) | AB16: =IFERROR($AA16*1,"") | AC16: =IF($Y16>Dashboard!$Q$19,$AB16,"") | AD16: =IFERROR($AB16*$BU$19,"") | AE16: =IF(Mining_Import!D16="","",Mining_Import!D16) | AF16: =IF(Mining_Import!E16="","",Mining_Import!E16) | AG16: =IF(Mining_Import!F16="","",Mining_Import!F16) | AH16: =IF(Mining_Import!G16="","",Mining_Import!G16) | AI16: =IF(Mining_Import!H16="","",Mining_Import!H16) | AJ16: =IF(Mining_Import!I16="","",Mining_Import!I16) | AL16: =IFERROR(INDEX($E$2:$E$2500, MATCH(0, INDEX(COUNTIF($AL$1:AL15, $E$2:$E$2500), 0, 0), 0)), "") | AM16: =IF(Calculator!$AL16="","",LEFT(Calculator!$AL16, LEN(Calculator!$AL16)-3)) | AN16: {=IF($AL16="","",MAX(IF($E$2:$E$2500=$AL16,$C$2:$C$2500)))} | AO16: =IF($AN16="","",(TEXT($AN16,"dd-mmm-yyyy")&" "&$AL16&" "&"1")) | AP16: =$AO16 | AQ16: =IF($AL16="","",VLOOKUP($AO16, $H:$K, 3, 0)) | AR16: =IF($AQ16="","",$AQ16*1) | AS16: =IF($AL16="","",SUMIFS($O:$O,$E:$E,$AL16,$I:$I,"BUY")) | AT16: =IF($AL16="","",SUMIFS($O:$O,$E:$E,$AL16,$I:$I,"SELL")) | AU16: =IF($AL16="","",SUMIF($E:$E,$AL16,$S:$S)) | AV16: =IF($AL16="","",SUMIFS($M:$M,$E:$E,$AL16,$I:$I,"BUY")) | AW16: =IF($AL16="","",SUMIFS($M:$M,$E:$E,$AL16,$I:$I,"SELL")) | AX16: =IF($AZ16=1,$AV16-$AW16,"") | AY16: =$AM16 | AZ16: =IF($AY16="","",IFERROR(VLOOKUP($AP16,$BG$2:$BH$13,2, FALSE),"")) | BA16: =IF($AZ16=1, "CURRENT","") | BB16: =IF($AW16=0,"",IFERROR($AS16-$BD16,"")) | BC16: =IFERROR(IF($BA16="CURRENT",(($AT16-$BB16)-$AU16),IF($AW16=0,"",($AT16-$AS16)-$AU16)),"") | BD16: =IF($BA16="CURRENT",($AX16*$AR16),"") | BR16: https://coinmarketcap.com/currencies/vechain/ | BS16: =IF(Stock_Connector!B16="","",Stock_Connector!B16) -> VET | BT16: =IF(Stock_Connector!C16="","",Stock_Connector!C16) -> 0.02886884 | BU16: =IF(Stock_Connector!C16="","",Stock_Connector!C16) -> 0.02886884 | BV16: =IF(Stock_Connector!E16="","",Stock_Connector!E16) | BW16: =IF(Stock_Connector!D16="","",Stock_Connector!D16) -> -0.007878183 | BY16: =Y16 | BZ16: =AB16 | CA16: =IFERROR(VLOOKUP($BY16,Account_Value!$C$2:$F$2500,4,0),"") | CB16: =IF(BZ16="","",BZ16*CA16) | CC16: =IF($BZ16="","",SUM($BZ$2:$BZ16)) | CD16: =IF($BZ16="","",$CA16*(SUM($BZ$2:$BZ16)))
A17: =IF($B17="","",$A16+1) | B17: =IF(Investments_Import!A17="","",Investments_Import!A17) | C17: =IF(B17="","",B17*1) | D17: =$C17 | E17: =IF(Investments_Import!B17="","",Investments_Import!B17) | F17: =CONCATENATE(TEXT($D17,"dd-mmm-yyyy")," ",$E17) | G17: =IF($B17="","",COUNTIF($F$2:$F17,$F17)) | H17: =CONCATENATE(TEXT($D17,"dd-mmm-yyyy")," ",$E17," ",$G17) | I17: =IF(Investments_Import!C17="","",Investments_Import!C17) | J17: =IF(Investments_Import!D17="","",Investments_Import!D17) | K17: =IF($B17="","",$J17*1) | L17: =IF(Investments_Import!E17="","",Investments_Import!E17) | M17: =IF($L17="","",$L17*1) | N17: =IF(Investments_Import!F17="","",Investments_Import!F17) | O17: =IF($N17="","",$N17*1) | P17: =IF(Investments_Import!G17="","",Investments_Import!G17) | Q17: =IF(Investments_Import!H17="","",Investments_Import!H17) | R17: =IF($Q17="","",IF($Q17="USD",$P17,$P17*$J17)) | S17: =IF($R17="","",$R17*1) | U17: =IF(Mining_Import!A17="","",Mining_Import!A17) | V17: =IF(U17="","",U17*1) | W17: =V17 | X17: =IFERROR(INT($W17),"") | Y17: =$X17 | Z17: =IF(Mining_Import!B17="","",Mining_Import!B17) | AA17: =IF(Mining_Import!$C17="","",Mining_Import!$C17) | AB17: =IFERROR($AA17*1,"") | AC17: =IF($Y17>Dashboard!$Q$19,$AB17,"") | AD17: =IFERROR($AB17*$BU$19,"") | AE17: =IF(Mining_Import!D17="","",Mining_Import!D17) | AF17: =IF(Mining_Import!E17="","",Mining_Import!E17) | AG17: =IF(Mining_Import!F17="","",Mining_Import!F17) | AH17: =IF(Mining_Import!G17="","",Mining_Import!G17) | AI17: =IF(Mining_Import!H17="","",Mining_Import!H17) | AJ17: =IF(Mining_Import!I17="","",Mining_Import!I17) | AL17: =IFERROR(INDEX($E$2:$E$2500, MATCH(0, INDEX(COUNTIF($AL$1:AL16, $E$2:$E$2500), 0, 0), 0)), "") | AM17: =IF(Calculator!$AL17="","",LEFT(Calculator!$AL17, LEN(Calculator!$AL17)-3)) | AN17: {=IF($AL17="","",MAX(IF($E$2:$E$2500=$AL17,$C$2:$C$2500)))} | AO17: =IF($AN17="","",(TEXT($AN17,"dd-mmm-yyyy")&" "&$AL17&" "&"1")) | AP17: =$AO17 | AQ17: =IF($AL17="","",VLOOKUP($AO17, $H:$K, 3, 0)) | AR17: =IF($AQ17="","",$AQ17*1) | AS17: =IF($AL17="","",SUMIFS($O:$O,$E:$E,$AL17,$I:$I,"BUY")) | AT17: =IF($AL17="","",SUMIFS($O:$O,$E:$E,$AL17,$I:$I,"SELL")) | AU17: =IF($AL17="","",SUMIF($E:$E,$AL17,$S:$S)) | AV17: =IF($AL17="","",SUMIFS($M:$M,$E:$E,$AL17,$I:$I,"BUY")) | AW17: =IF($AL17="","",SUMIFS($M:$M,$E:$E,$AL17,$I:$I,"SELL")) | AX17: =IF($AZ17=1,$AV17-$AW17,"") | AY17: =$AM17 | AZ17: =IF($AY17="","",IFERROR(VLOOKUP($AP17,$BG$2:$BH$13,2, FALSE),"")) | BA17: =IF($AZ17=1, "CURRENT","") | BB17: =IF($AW17=0,"",IFERROR($AS17-$BD17,"")) | BC17: =IFERROR(IF($BA17="CURRENT",(($AT17-$BB17)-$AU17),IF($AW17=0,"",($AT17-$AS17)-$AU17)),"") | BD17: =IF($BA17="CURRENT",($AX17*$AR17),"") | BR17: https://coinmarketcap.com/currencies/algorand/ | BS17: =IF(Stock_Connector!B17="","",Stock_Connector!B17) -> ALGO | BT17: =IF(Stock_Connector!C17="","",Stock_Connector!C17) -> 0.8435 | BU17: =IF(Stock_Connector!C17="","",Stock_Connector!C17) -> 0.8435 | BV17: =IF(Stock_Connector!E17="","",Stock_Connector!E17) | BW17: =IF(Stock_Connector!D17="","",Stock_Connector!D17) -> 0.11574074 | BY17: =Y17 | BZ17: =AB17 | CA17: =IFERROR(VLOOKUP($BY17,Account_Value!$C$2:$F$2500,4,0),"") | CB17: =IF(BZ17="","",BZ17*CA17) | CC17: =IF($BZ17="","",SUM($BZ$2:$BZ17)) | CD17: =IF($BZ17="","",$CA17*(SUM($BZ$2:$BZ17)))
A18: =IF($B18="","",$A17+1) | B18: =IF(Investments_Import!A18="","",Investments_Import!A18) | C18: =IF(B18="","",B18*1) | D18: =$C18 | E18: =IF(Investments_Import!B18="","",Investments_Import!B18) | F18: =CONCATENATE(TEXT($D18,"dd-mmm-yyyy")," ",$E18) | G18: =IF($B18="","",COUNTIF($F$2:$F18,$F18)) | H18: =CONCATENATE(TEXT($D18,"dd-mmm-yyyy")," ",$E18," ",$G18) | I18: =IF(Investments_Import!C18="","",Investments_Import!C18) | J18: =IF(Investments_Import!D18="","",Investments_Import!D18) | K18: =IF($B18="","",$J18*1) | L18: =IF(Investments_Import!E18="","",Investments_Import!E18) | M18: =IF($L18="","",$L18*1) | N18: =IF(Investments_Import!F18="","",Investments_Import!F18) | O18: =IF($N18="","",$N18*1) | P18: =IF(Investments_Import!G18="","",Investments_Import!G18) | Q18: =IF(Investments_Import!H18="","",Investments_Import!H18) | R18: =IF($Q18="","",IF($Q18="USD",$P18,$P18*$J18)) | S18: =IF($R18="","",$R18*1) | U18: =IF(Mining_Import!A18="","",Mining_Import!A18) | V18: =IF(U18="","",U18*1) | W18: =V18 | X18: =IFERROR(INT($W18),"") | Y18: =$X18 | Z18: =IF(Mining_Import!B18="","",Mining_Import!B18) | AA18: =IF(Mining_Import!$C18="","",Mining_Import!$C18) | AB18: =IFERROR($AA18*1,"") | AC18: =IF($Y18>Dashboard!$Q$19,$AB18,"") | AD18: =IFERROR($AB18*$BU$19,"") | AE18: =IF(Mining_Import!D18="","",Mining_Import!D18) | AF18: =IF(Mining_Import!E18="","",Mining_Import!E18) | AG18: =IF(Mining_Import!F18="","",Mining_Import!F18) | AH18: =IF(Mining_Import!G18="","",Mining_Import!G18) | AI18: =IF(Mining_Import!H18="","",Mining_Import!H18) | AJ18: =IF(Mining_Import!I18="","",Mining_Import!I18) | AL18: =IFERROR(INDEX($E$2:$E$2500, MATCH(0, INDEX(COUNTIF($AL$1:AL17, $E$2:$E$2500), 0, 0), 0)), "") | AM18: =IF(Calculator!$AL18="","",LEFT(Calculator!$AL18, LEN(Calculator!$AL18)-3)) | AN18: {=IF($AL18="","",MAX(IF($E$2:$E$2500=$AL18,$C$2:$C$2500)))} | AO18: =IF($AN18="","",(TEXT($AN18,"dd-mmm-yyyy")&" "&$AL18&" "&"1")) | AP18: =$AO18 | AQ18: =IF($AL18="","",VLOOKUP($AO18, $H:$K, 3, 0)) | AR18: =IF($AQ18="","",$AQ18*1) | AS18: =IF($AL18="","",SUMIFS($O:$O,$E:$E,$AL18,$I:$I,"BUY")) | AT18: =IF($AL18="","",SUMIFS($O:$O,$E:$E,$AL18,$I:$I,"SELL")) | AU18: =IF($AL18="","",SUMIF($E:$E,$AL18,$S:$S)) | AV18: =IF($AL18="","",SUMIFS($M:$M,$E:$E,$AL18,$I:$I,"BUY")) | AW18: =IF($AL18="","",SUMIFS($M:$M,$E:$E,$AL18,$I:$I,"SELL")) | AX18: =IF($AZ18=1,$AV18-$AW18,"") | AY18: =$AM18 | AZ18: =IF($AY18="","",IFERROR(VLOOKUP($AP18,$BG$2:$BH$13,2, FALSE),"")) | BA18: =IF($AZ18=1, "CURRENT","") | BB18: =IF($AW18=0,"",IFERROR($AS18-$BD18,"")) | BC18: =IFERROR(IF($BA18="CURRENT",(($AT18-$BB18)-$AU18),IF($AW18=0,"",($AT18-$AS18)-$AU18)),"") | BD18: =IF($BA18="CURRENT",($AX18*$AR18),"") | BR18: https://coinmarketcap.com/currencies/helium/ | BS18: =IF(Stock_Connector!B18="","",Stock_Connector!B18) -> HNT | BT18: =IF(Stock_Connector!C18="","",Stock_Connector!C18) -> 3.590587 | BU18: =IF(Stock_Connector!C18="","",Stock_Connector!C18) -> 3.590587 | BV18: =IF(Stock_Connector!E18="","",Stock_Connector!E18) | BW18: =IF(Stock_Connector!D18="","",Stock_Connector!D18) -> 0.12262536 | BY18: =Y18 | BZ18: =AB18 | CA18: =IFERROR(VLOOKUP($BY18,Account_Value!$C$2:$F$2500,4,0),"") | CB18: =IF(BZ18="","",BZ18*CA18) | CC18: =IF($BZ18="","",SUM($BZ$2:$BZ18)) | CD18: =IF($BZ18="","",$CA18*(SUM($BZ$2:$BZ18)))
A19: =IF($B19="","",$A18+1) | B19: =IF(Investments_Import!A19="","",Investments_Import!A19) | C19: =IF(B19="","",B19*1) | D19: =$C19 | E19: =IF(Investments_Import!B19="","",Investments_Import!B19) | F19: =CONCATENATE(TEXT($D19,"dd-mmm-yyyy")," ",$E19) | G19: =IF($B19="","",COUNTIF($F$2:$F19,$F19)) | H19: =CONCATENATE(TEXT($D19,"dd-mmm-yyyy")," ",$E19," ",$G19) | I19: =IF(Investments_Import!C19="","",Investments_Import!C19) | J19: =IF(Investments_Import!D19="","",Investments_Import!D19) | K19: =IF($B19="","",$J19*1) | L19: =IF(Investments_Import!E19="","",Investments_Import!E19) | M19: =IF($L19="","",$L19*1) | N19: =IF(Investments_Import!F19="","",Investments_Import!F19) | O19: =IF($N19="","",$N19*1) | P19: =IF(Investments_Import!G19="","",Investments_Import!G19) | Q19: =IF(Investments_Import!H19="","",Investments_Import!H19) | R19: =IF($Q19="","",IF($Q19="USD",$P19,$P19*$J19)) | S19: =IF($R19="","",$R19*1) | U19: =IF(Mining_Import!A19="","",Mining_Import!A19) | V19: =IF(U19="","",U19*1) | W19: =V19 | X19: =IFERROR(INT($W19),"") | Y19: =$X19 | Z19: =IF(Mining_Import!B19="","",Mining_Import!B19) | AA19: =IF(Mining_Import!$C19="","",Mining_Import!$C19) | AB19: =IFERROR($AA19*1,"") | AC19: =IF($Y19>Dashboard!$Q$19,$AB19,"") | AD19: =IFERROR($AB19*$BU$19,"") | AE19: =IF(Mining_Import!D19="","",Mining_Import!D19) | AF19: =IF(Mining_Import!E19="","",Mining_Import!E19) | AG19: =IF(Mining_Import!F19="","",Mining_Import!F19) | AH19: =IF(Mining_Import!G19="","",Mining_Import!G19) | AI19: =IF(Mining_Import!H19="","",Mining_Import!H19) | AJ19: =IF(Mining_Import!I19="","",Mining_Import!I19) | AL19: =IFERROR(INDEX($E$2:$E$2500, MATCH(0, INDEX(COUNTIF($AL$1:AL18, $E$2:$E$2500), 0, 0), 0)), "") | AM19: =IF(Calculator!$AL19="","",LEFT(Calculator!$AL19, LEN(Calculator!$AL19)-3)) | AN19: {=IF($AL19="","",MAX(IF($E$2:$E$2500=$AL19,$C$2:$C$2500)))} | AO19: =IF($AN19="","",(TEXT($AN19,"dd-mmm-yyyy")&" "&$AL19&" "&"1")) | AP19: =$AO19 | AQ19: =IF($AL19="","",VLOOKUP($AO19, $H:$K, 3, 0)) | AR19: =IF($AQ19="","",$AQ19*1) | AS19: =IF($AL19="","",SUMIFS($O:$O,$E:$E,$AL19,$I:$I,"BUY")) | AT19: =IF($AL19="","",SUMIFS($O:$O,$E:$E,$AL19,$I:$I,"SELL")) | AU19: =IF($AL19="","",SUMIF($E:$E,$AL19,$S:$S)) | AV19: =IF($AL19="","",SUMIFS($M:$M,$E:$E,$AL19,$I:$I,"BUY")) | AW19: =IF($AL19="","",SUMIFS($M:$M,$E:$E,$AL19,$I:$I,"SELL")) | AX19: =IF($AZ19=1,$AV19-$AW19,"") | AY19: =$AM19 | AZ19: =IF($AY19="","",IFERROR(VLOOKUP($AP19,$BG$2:$BH$13,2, FALSE),"")) | BA19: =IF($AZ19=1, "CURRENT","") | BB19: =IF($AW19=0,"",IFERROR($AS19-$BD19,"")) | BC19: =IFERROR(IF($BA19="CURRENT",(($AT19-$BB19)-$AU19),IF($AW19=0,"",($AT19-$AS19)-$AU19)),"") | BD19: =IF($BA19="CURRENT",($AX19*$AR19),"") | BR19: https://coinmarketcap.com/currencies/ethereum/ | BS19: =IF(Stock_Connector!B19="","",Stock_Connector!B19) -> ETH | BT19: =IF(Stock_Connector!C19="","",Stock_Connector!C19) -> 1624.07 | BU19: =IF(Stock_Connector!C19="","",Stock_Connector!C19) -> 1624.07 | BV19: =IF(Stock_Connector!E19="","",Stock_Connector!E19) | BW19: =IF(Stock_Connector!D19="","",Stock_Connector!D19) -> -0.033941456 | BY19: =Y19 | BZ19: =AB19 | CA19: =IFERROR(VLOOKUP($BY19,Account_Value!$C$2:$F$2500,4,0),"") | CB19: =IF(BZ19="","",BZ19*CA19) | CC19: =IF($BZ19="","",SUM($BZ$2:$BZ19)) | CD19: =IF($BZ19="","",$CA19*(SUM($BZ$2:$BZ19)))
A20: =IF($B20="","",$A19+1) | B20: =IF(Investments_Import!A20="","",Investments_Import!A20) | C20: =IF(B20="","",B20*1) | D20: =$C20 | E20: =IF(Investments_Import!B20="","",Investments_Import!B20) | F20: =CONCATENATE(TEXT($D20,"dd-mmm-yyyy")," ",$E20) | G20: =IF($B20="","",COUNTIF($F$2:$F20,$F20)) | H20: =CONCATENATE(TEXT($D20,"dd-mmm-yyyy")," ",$E20," ",$G20) | I20: =IF(Investments_Import!C20="","",Investments_Import!C20) | J20: =IF(Investments_Import!D20="","",Investments_Import!D20) | K20: =IF($B20="","",$J20*1) | L20: =IF(Investments_Import!E20="","",Investments_Import!E20) | M20: =IF($L20="","",$L20*1) | N20: =IF(Investments_Import!F20="","",Investments_Import!F20) | O20: =IF($N20="","",$N20*1) | P20: =IF(Investments_Import!G20="","",Investments_Import!G20) | Q20: =IF(Investments_Import!H20="","",Investments_Import!H20) | R20: =IF($Q20="","",IF($Q20="USD",$P20,$P20*$J20)) | S20: =IF($R20="","",$R20*1) | U20: =IF(Mining_Import!A20="","",Mining_Import!A20) | V20: =IF(U20="","",U20*1) | W20: =V20 | X20: =IFERROR(INT($W20),"") | Y20: =$X20 | Z20: =IF(Mining_Import!B20="","",Mining_Import!B20) | AA20: =IF(Mining_Import!$C20="","",Mining_Import!$C20) | AB20: =IFERROR($AA20*1,"") | AC20: =IF($Y20>Dashboard!$Q$19,$AB20,"") | AD20: =IFERROR($AB20*$BU$19,"") | AE20: =IF(Mining_Import!D20="","",Mining_Import!D20) | AF20: =IF(Mining_Import!E20="","",Mining_Import!E20) | AG20: =IF(Mining_Import!F20="","",Mining_Import!F20) | AH20: =IF(Mining_Import!G20="","",Mining_Import!G20) | AI20: =IF(Mining_Import!H20="","",Mining_Import!H20) | AJ20: =IF(Mining_Import!I20="","",Mining_Import!I20) | AL20: =IFERROR(INDEX($E$2:$E$2500, MATCH(0, INDEX(COUNTIF($AL$1:AL19, $E$2:$E$2500), 0, 0), 0)), "") | AM20: =IF(Calculator!$AL20="","",LEFT(Calculator!$AL20, LEN(Calculator!$AL20)-3)) | AN20: {=IF($AL20="","",MAX(IF($E$2:$E$2500=$AL20,$C$2:$C$2500)))} | AO20: =IF($AN20="","",(TEXT($AN20,"dd-mmm-yyyy")&" "&$AL20&" "&"1")) | AP20: =$AO20 | AQ20: =IF($AL20="","",VLOOKUP($AO20, $H:$K, 3, 0)) | AR20: =IF($AQ20="","",$AQ20*1) | AS20: =IF($AL20="","",SUMIFS($O:$O,$E:$E,$AL20,$I:$I,"BUY")) | AT20: =IF($AL20="","",SUMIFS($O:$O,$E:$E,$AL20,$I:$I,"SELL")) | AU20: =IF($AL20="","",SUMIF($E:$E,$AL20,$S:$S)) | AV20: =IF($AL20="","",SUMIFS($M:$M,$E:$E,$AL20,$I:$I,"BUY")) | AW20: =IF($AL20="","",SUMIFS($M:$M,$E:$E,$AL20,$I:$I,"SELL")) | AX20: =IF($AZ20=1,$AV20-$AW20,"") | AY20: =$AM20 | AZ20: =IF($AY20="","",IFERROR(VLOOKUP($AP20,$BG$2:$BH$13,2, FALSE),"")) | BA20: =IF($AZ20=1, "CURRENT","") | BB20: =IF($AW20=0,"",IFERROR($AS20-$BD20,"")) | BC20: =IFERROR(IF($BA20="CURRENT",(($AT20-$BB20)-$AU20),IF($AW20=0,"",($AT20-$AS20)-$AU20)),"") | BD20: =IF($BA20="CURRENT",($AX20*$AR20),"") | BR20: https://coinmarketcap.com/currencies/solana/ | BS20: =IF(Stock_Connector!B20="","",Stock_Connector!B20) -> SOL | BT20: =IF(Stock_Connector!C20="","",Stock_Connector!C20) -> 6.455 | BU20: =IF(Stock_Connector!C20="","",Stock_Connector!C20) -> 6.455 | BV20: =IF(Stock_Connector!E20="","",Stock_Connector!E20) | BW20: =IF(Stock_Connector!D20="","",Stock_Connector!D20) -> 0.070658484 | BY20: =Y20 | BZ20: =AB20 | CA20: =IFERROR(VLOOKUP($BY20,Account_Value!$C$2:$F$2500,4,0),"") | CB20: =IF(BZ20="","",BZ20*CA20) | CC20: =IF($BZ20="","",SUM($BZ$2:$BZ20)) | CD20: =IF($BZ20="","",$CA20*(SUM($BZ$2:$BZ20)))
A21: =IF($B21="","",$A20+1) | B21: =IF(Investments_Import!A21="","",Investments_Import!A21) | C21: =IF(B21="","",B21*1) | D21: =$C21 | E21: =IF(Investments_Import!B21="","",Investments_Import!B21) | F21: =CONCATENATE(TEXT($D21,"dd-mmm-yyyy")," ",$E21) | G21: =IF($B21="","",COUNTIF($F$2:$F21,$F21)) | H21: =CONCATENATE(TEXT($D21,"dd-mmm-yyyy")," ",$E21," ",$G21) | I21: =IF(Investments_Import!C21="","",Investments_Import!C21) | J21: =IF(Investments_Import!D21="","",Investments_Import!D21) | K21: =IF($B21="","",$J21*1) | L21: =IF(Investments_Import!E21="","",Investments_Import!E21) | M21: =IF($L21="","",$L21*1) | N21: =IF(Investments_Import!F21="","",Investments_Import!F21) | O21: =IF($N21="","",$N21*1) | P21: =IF(Investments_Import!G21="","",Investments_Import!G21) | Q21: =IF(Investments_Import!H21="","",Investments_Import!H21) | R21: =IF($Q21="","",IF($Q21="USD",$P21,$P21*$J21)) | S21: =IF($R21="","",$R21*1) | U21: =IF(Mining_Import!A21="","",Mining_Import!A21) | V21: =IF(U21="","",U21*1) | W21: =V21 | X21: =IFERROR(INT($W21),"") | Y21: =$X21 | Z21: =IF(Mining_Import!B21="","",Mining_Import!B21) | AA21: =IF(Mining_Import!$C21="","",Mining_Import!$C21) | AB21: =IFERROR($AA21*1,"") | AC21: =IF($Y21>Dashboard!$Q$19,$AB21,"") | AD21: =IFERROR($AB21*$BU$19,"") | AE21: =IF(Mining_Import!D21="","",Mining_Import!D21) | AF21: =IF(Mining_Import!E21="","",Mining_Import!E21) | AG21: =IF(Mining_Import!F21="","",Mining_Import!F21) | AH21: =IF(Mining_Import!G21="","",Mining_Import!G21) | AI21: =IF(Mining_Import!H21="","",Mining_Import!H21) | AJ21: =IF(Mining_Import!I21="","",Mining_Import!I21) | AL21: =IFERROR(INDEX($E$2:$E$2500, MATCH(0, INDEX(COUNTIF($AL$1:AL20, $E$2:$E$2500), 0, 0), 0)), "") | AM21: =IF(Calculator!$AL21="","",LEFT(Calculator!$AL21, LEN(Calculator!$AL21)-3)) | AN21: {=IF($AL21="","",MAX(IF($E$2:$E$2500=$AL21,$C$2:$C$2500)))} | AO21: =IF($AN21="","",(TEXT($AN21,"dd-mmm-yyyy")&" "&$AL21&" "&"1")) | AP21: =$AO21 | AQ21: =IF($AL21="","",VLOOKUP($AO21, $H:$K, 3, 0)) | AR21: =IF($AQ21="","",$AQ21*1) | AS21: =IF($AL21="","",SUMIFS($O:$O,$E:$E,$AL21,$I:$I,"BUY")) | AT21: =IF($AL21="","",SUMIFS($O:$O,$E:$E,$AL21,$I:$I,"SELL")) | AU21: =IF($AL21="","",SUMIF($E:$E,$AL21,$S:$S)) | AV21: =IF($AL21="","",SUMIFS($M:$M,$E:$E,$AL21,$I:$I,"BUY")) | AW21: =IF($AL21="","",SUMIFS($M:$M,$E:$E,$AL21,$I:$I,"SELL")) | AX21: =IF($AZ21=1,$AV21-$AW21,"") | AY21: =$AM21 | AZ21: =IF($AY21="","",IFERROR(VLOOKUP($AP21,$BG$2:$BH$13,2, FALSE),"")) | BA21: =IF($AZ21=1, "CURRENT","") | BB21: =IF($AW21=0,"",IFERROR($AS21-$BD21,"")) | BC21: =IFERROR(IF($BA21="CURRENT",(($AT21-$BB21)-$AU21),IF($AW21=0,"",($AT21-$AS21)-$AU21)),"") | BD21: =IF($BA21="CURRENT",($AX21*$AR21),"") | BR21: https://coinmarketcap.com/currencies/elrond-egld/ | BS21: =IF(Stock_Connector!B21="","",Stock_Connector!B21) -> EGLD | BT21: =IF(Stock_Connector!C21="","",Stock_Connector!C21) -> 115.60549 | BU21: =IF(Stock_Connector!C21="","",Stock_Connector!C21) -> 115.60549 | BV21: =IF(Stock_Connector!E21="","",Stock_Connector!E21) | BW21: =IF(Stock_Connector!D21="","",Stock_Connector!D21) -> 0.21447095 | BY21: =Y21 | BZ21: =AB21 | CA21: =IFERROR(VLOOKUP($BY21,Account_Value!$C$2:$F$2500,4,0),"") | CB21: =IF(BZ21="","",BZ21*CA21) | CC21: =IF($BZ21="","",SUM($BZ$2:$BZ21)) | CD21: =IF($BZ21="","",$CA21*(SUM($BZ$2:$BZ21)))
A22: =IF($B22="","",$A21+1) | B22: =IF(Investments_Import!A22="","",Investments_Import!A22) | C22: =IF(B22="","",B22*1) | D22: =$C22 | E22: =IF(Investments_Import!B22="","",Investments_Import!B22) | F22: =CONCATENATE(TEXT($D22,"dd-mmm-yyyy")," ",$E22) | G22: =IF($B22="","",COUNTIF($F$2:$F22,$F22)) | H22: =CONCATENATE(TEXT($D22,"dd-mmm-yyyy")," ",$E22," ",$G22) | I22: =IF(Investments_Import!C22="","",Investments_Import!C22) | J22: =IF(Investments_Import!D22="","",Investments_Import!D22) | K22: =IF($B22="","",$J22*1) | L22: =IF(Investments_Import!E22="","",Investments_Import!E22) | M22: =IF($L22="","",$L22*1) | N22: =IF(Investments_Import!F22="","",Investments_Import!F22) | O22: =IF($N22="","",$N22*1) | P22: =IF(Investments_Import!G22="","",Investments_Import!G22) | Q22: =IF(Investments_Import!H22="","",Investments_Import!H22) | R22: =IF($Q22="","",IF($Q22="USD",$P22,$P22*$J22)) | S22: =IF($R22="","",$R22*1) | U22: =IF(Mining_Import!A22="","",Mining_Import!A22) | V22: =IF(U22="","",U22*1) | W22: =V22 | X22: =IFERROR(INT($W22),"") | Y22: =$X22 | Z22: =IF(Mining_Import!B22="","",Mining_Import!B22) | AA22: =IF(Mining_Import!$C22="","",Mining_Import!$C22) | AB22: =IFERROR($AA22*1,"") | AC22: =IF($Y22>Dashboard!$Q$19,$AB22,"") | AD22: =IFERROR($AB22*$BU$19,"") | AE22: =IF(Mining_Import!D22="","",Mining_Import!D22) | AF22: =IF(Mining_Import!E22="","",Mining_Import!E22) | AG22: =IF(Mining_Import!F22="","",Mining_Import!F22) | AH22: =IF(Mining_Import!G22="","",Mining_Import!G22) | AI22: =IF(Mining_Import!H22="","",Mining_Import!H22) | AJ22: =IF(Mining_Import!I22="","",Mining_Import!I22) | AL22: =IFERROR(INDEX($E$2:$E$2500, MATCH(0, INDEX(COUNTIF($AL$1:AL21, $E$2:$E$2500), 0, 0), 0)), "") | AM22: =IF(Calculator!$AL22="","",LEFT(Calculator!$AL22, LEN(Calculator!$AL22)-3)) | AN22: {=IF($AL22="","",MAX(IF($E$2:$E$2500=$AL22,$C$2:$C$2500)))} | AO22: =IF($AN22="","",(TEXT($AN22,"dd-mmm-yyyy")&" "&$AL22&" "&"1")) | AP22: =$AO22 | AQ22: =IF($AL22="","",VLOOKUP($AO22, $H:$K, 3, 0)) | AR22: =IF($AQ22="","",$AQ22*1) | AS22: =IF($AL22="","",SUMIFS($O:$O,$E:$E,$AL22,$I:$I,"BUY")) | AT22: =IF($AL22="","",SUMIFS($O:$O,$E:$E,$AL22,$I:$I,"SELL")) | AU22: =IF($AL22="","",SUMIF($E:$E,$AL22,$S:$S)) | AV22: =IF($AL22="","",SUMIFS($M:$M,$E:$E,$AL22,$I:$I,"BUY")) | AW22: =IF($AL22="","",SUMIFS($M:$M,$E:$E,$AL22,$I:$I,"SELL")) | AX22: =IF($AZ22=1,$AV22-$AW22,"") | AY22: =$AM22 | AZ22: =IF($AY22="","",IFERROR(VLOOKUP($AP22,$BG$2:$BH$13,2, FALSE),"")) | BA22: =IF($AZ22=1, "CURRENT","") | BB22: =IF($AW22=0,"",IFERROR($AS22-$BD22,"")) | BC22: =IFERROR(IF($BA22="CURRENT",(($AT22-$BB22)-$AU22),IF($AW22=0,"",($AT22-$AS22)-$AU22)),"") | BD22: =IF($BA22="CURRENT",($AX22*$AR22),"") | BR22: https://coinmarketcap.com/currencies/binance-coin/ | BS22: =IF(Stock_Connector!B22="","",Stock_Connector!B22) -> BNB | BT22: =IF(Stock_Connector!C22="","",Stock_Connector!C22) -> 69.72 | BU22: =IF(Stock_Connector!C22="","",Stock_Connector!C22) -> 69.72 | BV22: =IF(Stock_Connector!E22="","",Stock_Connector!E22) | BW22: =IF(Stock_Connector!D22="","",Stock_Connector!D22) -> -0.056562923 | BY22: =Y22 | BZ22: =AB22 | CA22: =IFERROR(VLOOKUP($BY22,Account_Value!$C$2:$F$2500,4,0),"") | CB22: =IF(BZ22="","",BZ22*CA22) | CC22: =IF($BZ22="","",SUM($BZ$2:$BZ22)) | CD22: =IF($BZ22="","",$CA22*(SUM($BZ$2:$BZ22)))
A23: =IF($B23="","",$A22+1) | B23: =IF(Investments_Import!A23="","",Investments_Import!A23) | C23: =IF(B23="","",B23*1) | D23: =$C23 | E23: =IF(Investments_Import!B23="","",Investments_Import!B23) | F23: =CONCATENATE(TEXT($D23,"dd-mmm-yyyy")," ",$E23) | G23: =IF($B23="","",COUNTIF($F$2:$F23,$F23)) | H23: =CONCATENATE(TEXT($D23,"dd-mmm-yyyy")," ",$E23," ",$G23) | I23: =IF(Investments_Import!C23="","",Investments_Import!C23) | J23: =IF(Investments_Import!D23="","",Investments_Import!D23) | K23: =IF($B23="","",$J23*1) | L23: =IF(Investments_Import!E23="","",Investments_Import!E23) | M23: =IF($L23="","",$L23*1) | N23: =IF(Investments_Import!F23="","",Investments_Import!F23) | O23: =IF($N23="","",$N23*1) | P23: =IF(Investments_Import!G23="","",Investments_Import!G23) | Q23: =IF(Investments_Import!H23="","",Investments_Import!H23) | R23: =IF($Q23="","",IF($Q23="USD",$P23,$P23*$J23)) | S23: =IF($R23="","",$R23*1) | U23: =IF(Mining_Import!A23="","",Mining_Import!A23) | V23: =IF(U23="","",U23*1) | W23: =V23 | X23: =IFERROR(INT($W23),"") | Y23: =$X23 | Z23: =IF(Mining_Import!B23="","",Mining_Import!B23) | AA23: =IF(Mining_Import!$C23="","",Mining_Import!$C23) | AB23: =IFERROR($AA23*1,"") | AC23: =IF($Y23>Dashboard!$Q$19,$AB23,"") | AD23: =IFERROR($AB23*$BU$19,"") | AE23: =IF(Mining_Import!D23="","",Mining_Import!D23) | AF23: =IF(Mining_Import!E23="","",Mining_Import!E23) | AG23: =IF(Mining_Import!F23="","",Mining_Import!F23) | AH23: =IF(Mining_Import!G23="","",Mining_Import!G23) | AI23: =IF(Mining_Import!H23="","",Mining_Import!H23) | AJ23: =IF(Mining_Import!I23="","",Mining_Import!I23) | AL23: =IFERROR(INDEX($E$2:$E$2500, MATCH(0, INDEX(COUNTIF($AL$1:AL22, $E$2:$E$2500), 0, 0), 0)), "") | AM23: =IF(Calculator!$AL23="","",LEFT(Calculator!$AL23, LEN(Calculator!$AL23)-3)) | AN23: {=IF($AL23="","",MAX(IF($E$2:$E$2500=$AL23,$C$2:$C$2500)))} | AO23: =IF($AN23="","",(TEXT($AN23,"dd-mmm-yyyy")&" "&$AL23&" "&"1")) | AP23: =$AO23 | AQ23: =IF($AL23="","",VLOOKUP($AO23, $H:$K, 3, 0)) | AR23: =IF($AQ23="","",$AQ23*1) | AS23: =IF($AL23="","",SUMIFS($O:$O,$E:$E,$AL23,$I:$I,"BUY")) | AT23: =IF($AL23="","",SUMIFS($O:$O,$E:$E,$AL23,$I:$I,"SELL")) | AU23: =IF($AL23="","",SUMIF($E:$E,$AL23,$S:$S)) | AV23: =IF($AL23="","",SUMIFS($M:$M,$E:$E,$AL23,$I:$I,"BUY")) | AW23: =IF($AL23="","",SUMIFS($M:$M,$E:$E,$AL23,$I:$I,"SELL")) | AX23: =IF($AZ23=1,$AV23-$AW23,"") | AY23: =$AM23 | AZ23: =IF($AY23="","",IFERROR(VLOOKUP($AP23,$BG$2:$BH$13,2, FALSE),"")) | BA23: =IF($AZ23=1, "CURRENT","") | BB23: =IF($AW23=0,"",IFERROR($AS23-$BD23,"")) | BC23: =IFERROR(IF($BA23="CURRENT",(($AT23-$BB23)-$AU23),IF($AW23=0,"",($AT23-$AS23)-$AU23)),"") | BD23: =IF($BA23="CURRENT",($AX23*$AR23),"") | BS23: =IF(Stock_Connector!B23="","",Stock_Connector!B23) -> PAXG | BT23: =IF(Stock_Connector!C23="","",Stock_Connector!C23) -> 1832.74 | BU23: =IF(Stock_Connector!C23="","",Stock_Connector!C23) -> 1832.74 | BV23: =IF(Stock_Connector!E23="","",Stock_Connector!E23) | BW23: =IF(Stock_Connector!D23="","",Stock_Connector!D23) -> -0.00028364771 | BY23: =Y23 | BZ23: =AB23 | CA23: =IFERROR(VLOOKUP($BY23,Account_Value!$C$2:$F$2500,4,0),"") | CB23: =IF(BZ23="","",BZ23*CA23) | CC23: =IF($BZ23="","",SUM($BZ$2:$BZ23)) | CD23: =IF($BZ23="","",$CA23*(SUM($BZ$2:$BZ23)))
A24: =IF($B24="","",$A23+1) | B24: =IF(Investments_Import!A24="","",Investments_Import!A24) | C24: =IF(B24="","",B24*1) | D24: =$C24 | E24: =IF(Investments_Import!B24="","",Investments_Import!B24) | F24: =CONCATENATE(TEXT($D24,"dd-mmm-yyyy")," ",$E24) | G24: =IF($B24="","",COUNTIF($F$2:$F24,$F24)) | H24: =CONCATENATE(TEXT($D24,"dd-mmm-yyyy")," ",$E24," ",$G24) | I24: =IF(Investments_Import!C24="","",Investments_Import!C24) | J24: =IF(Investments_Import!D24="","",Investments_Import!D24) | K24: =IF($B24="","",$J24*1) | L24: =IF(Investments_Import!E24="","",Investments_Import!E24) | M24: =IF($L24="","",$L24*1) | N24: =IF(Investments_Import!F24="","",Investments_Import!F24) | O24: =IF($N24="","",$N24*1) | P24: =IF(Investments_Import!G24="","",Investments_Import!G24) | Q24: =IF(Investments_Import!H24="","",Investments_Import!H24) | R24: =IF($Q24="","",IF($Q24="USD",$P24,$P24*$J24)) | S24: =IF($R24="","",$R24*1) | U24: =IF(Mining_Import!A24="","",Mining_Import!A24) | V24: =IF(U24="","",U24*1) | W24: =V24 | X24: =IFERROR(INT($W24),"") | Y24: =$X24 | Z24: =IF(Mining_Import!B24="","",Mining_Import!B24) | AA24: =IF(Mining_Import!$C24="","",Mining_Import!$C24) | AB24: =IFERROR($AA24*1,"") | AC24: =IF($Y24>Dashboard!$Q$19,$AB24,"") | AD24: =IFERROR($AB24*$BU$19,"") | AE24: =IF(Mining_Import!D24="","",Mining_Import!D24) | AF24: =IF(Mining_Import!E24="","",Mining_Import!E24) | AG24: =IF(Mining_Import!F24="","",Mining_Import!F24) | AH24: =IF(Mining_Import!G24="","",Mining_Import!G24) | AI24: =IF(Mining_Import!H24="","",Mining_Import!H24) | AJ24: =IF(Mining_Import!I24="","",Mining_Import!I24) | AL24: =IFERROR(INDEX($E$2:$E$2500, MATCH(0, INDEX(COUNTIF($AL$1:AL23, $E$2:$E$2500), 0, 0), 0)), "") | AM24: =IF(Calculator!$AL24="","",LEFT(Calculator!$AL24, LEN(Calculator!$AL24)-3)) | AN24: {=IF($AL24="","",MAX(IF($E$2:$E$2500=$AL24,$C$2:$C$2500)))} | AO24: =IF($AN24="","",(TEXT($AN24,"dd-mmm-yyyy")&" "&$AL24&" "&"1")) | AP24: =$AO24 | AQ24: =IF($AL24="","",VLOOKUP($AO24, $H:$K, 3, 0)) | AR24: =IF($AQ24="","",$AQ24*1) | AS24: =IF($AL24="","",SUMIFS($O:$O,$E:$E,$AL24,$I:$I,"BUY")) | AT24: =IF($AL24="","",SUMIFS($O:$O,$E:$E,$AL24,$I:$I,"SELL")) | AU24: =IF($AL24="","",SUMIF($E:$E,$AL24,$S:$S)) | AV24: =IF($AL24="","",SUMIFS($M:$M,$E:$E,$AL24,$I:$I,"BUY")) | AW24: =IF($AL24="","",SUMIFS($M:$M,$E:$E,$AL24,$I:$I,"SELL")) | AX24: =IF($AZ24=1,$AV24-$AW24,"") | AY24: =$AM24 | AZ24: =IF($AY24="","",IFERROR(VLOOKUP($AP24,$BG$2:$BH$13,2, FALSE),"")) | BA24: =IF($AZ24=1, "CURRENT","") | BB24: =IF($AW24=0,"",IFERROR($AS24-$BD24,"")) | BC24: =IFERROR(IF($BA24="CURRENT",(($AT24-$BB24)-$AU24),IF($AW24=0,"",($AT24-$AS24)-$AU24)),"") | BD24: =IF($BA24="CURRENT",($AX24*$AR24),"") | BS24: =IF(Stock_Connector!B24="","",Stock_Connector!B24) -> DASH | BT24: =IF(Stock_Connector!C24="","",Stock_Connector!C24) -> 117.90779 | BU24: =IF(Stock_Connector!C24="","",Stock_Connector!C24) -> 117.90779 | BV24: =IF(Stock_Connector!E24="","",Stock_Connector!E24) | BW24: =IF(Stock_Connector!D24="","",Stock_Connector!D24) -> 0.0088515527 | BY24: =Y24 | BZ24: =AB24 | CA24: =IFERROR(VLOOKUP($BY24,Account_Value!$C$2:$F$2500,4,0),"") | CB24: =IF(BZ24="","",BZ24*CA24) | CC24: =IF($BZ24="","",SUM($BZ$2:$BZ24)) | CD24: =IF($BZ24="","",$CA24*(SUM($BZ$2:$BZ24)))
A25: =IF($B25="","",$A24+1) | B25: =IF(Investments_Import!A25="","",Investments_Import!A25) | C25: =IF(B25="","",B25*1) | D25: =$C25 | E25: =IF(Investments_Import!B25="","",Investments_Import!B25) | F25: =CONCATENATE(TEXT($D25,"dd-mmm-yyyy")," ",$E25) | G25: =IF($B25="","",COUNTIF($F$2:$F25,$F25)) | H25: =CONCATENATE(TEXT($D25,"dd-mmm-yyyy")," ",$E25," ",$G25) | I25: =IF(Investments_Import!C25="","",Investments_Import!C25) | J25: =IF(Investments_Import!D25="","",Investments_Import!D25) | K25: =IF($B25="","",$J25*1) | L25: =IF(Investments_Import!E25="","",Investments_Import!E25) | M25: =IF($L25="","",$L25*1) | N25: =IF(Investments_Import!F25="","",Investments_Import!F25) | O25: =IF($N25="","",$N25*1) | P25: =IF(Investments_Import!G25="","",Investments_Import!G25) | Q25: =IF(Investments_Import!H25="","",Investments_Import!H25) | R25: =IF($Q25="","",IF($Q25="USD",$P25,$P25*$J25)) | S25: =IF($R25="","",$R25*1) | U25: =IF(Mining_Import!A25="","",Mining_Import!A25) | V25: =IF(U25="","",U25*1) | W25: =V25 | X25: =IFERROR(INT($W25),"") | Y25: =$X25 | Z25: =IF(Mining_Import!B25="","",Mining_Import!B25) | AA25: =IF(Mining_Import!$C25="","",Mining_Import!$C25) | AB25: =IFERROR($AA25*1,"") | AC25: =IF($Y25>Dashboard!$Q$19,$AB25,"") | AD25: =IFERROR($AB25*$BU$19,"") | AE25: =IF(Mining_Import!D25="","",Mining_Import!D25) | AF25: =IF(Mining_Import!E25="","",Mining_Import!E25) | AG25: =IF(Mining_Import!F25="","",Mining_Import!F25) | AH25: =IF(Mining_Import!G25="","",Mining_Import!G25) | AI25: =IF(Mining_Import!H25="","",Mining_Import!H25) | AJ25: =IF(Mining_Import!I25="","",Mining_Import!I25) | AL25: =IFERROR(INDEX($E$2:$E$2500, MATCH(0, INDEX(COUNTIF($AL$1:AL24, $E$2:$E$2500), 0, 0), 0)), "") | AM25: =IF(Calculator!$AL25="","",LEFT(Calculator!$AL25, LEN(Calculator!$AL25)-3)) | AN25: {=IF($AL25="","",MAX(IF($E$2:$E$2500=$AL25,$C$2:$C$2500)))} | AO25: =IF($AN25="","",(TEXT($AN25,"dd-mmm-yyyy")&" "&$AL25&" "&"1")) | AP25: =$AO25 | AQ25: =IF($AL25="","",VLOOKUP($AO25, $H:$K, 3, 0)) | AR25: =IF($AQ25="","",$AQ25*1) | AS25: =IF($AL25="","",SUMIFS($O:$O,$E:$E,$AL25,$I:$I,"BUY")) | AT25: =IF($AL25="","",SUMIFS($O:$O,$E:$E,$AL25,$I:$I,"SELL")) | AU25: =IF($AL25="","",SUMIF($E:$E,$AL25,$S:$S)) | AV25: =IF($AL25="","",SUMIFS($M:$M,$E:$E,$AL25,$I:$I,"BUY")) | AW25: =IF($AL25="","",SUMIFS($M:$M,$E:$E,$AL25,$I:$I,"SELL")) | AX25: =IF($AZ25=1,$AV25-$AW25,"") | AY25: =$AM25 | AZ25: =IF($AY25="","",IFERROR(VLOOKUP($AP25,$BG$2:$BH$13,2, FALSE),"")) | BA25: =IF($AZ25=1, "CURRENT","") | BB25: =IF($AW25=0,"",IFERROR($AS25-$BD25,"")) | BC25: =IFERROR(IF($BA25="CURRENT",(($AT25-$BB25)-$AU25),IF($AW25=0,"",($AT25-$AS25)-$AU25)),"") | BD25: =IF($BA25="CURRENT",($AX25*$AR25),"") | BS25: =IF(Stock_Connector!B25="","",Stock_Connector!B25) -> MANA | BT25: =IF(Stock_Connector!C25="","",Stock_Connector!C25) -> 0.2481479 | BU25: =IF(Stock_Connector!C25="","",Stock_Connector!C25) -> 0.2481479 | BV25: =IF(Stock_Connector!E25="","",Stock_Connector!E25) | BW25: =IF(Stock_Connector!D25="","",Stock_Connector!D25) -> 0.26031855 | BY25: =Y25 | BZ25: =AB25 | CA25: =IFERROR(VLOOKUP($BY25,Account_Value!$C$2:$F$2500,4,0),"") | CB25: =IF(BZ25="","",BZ25*CA25) | CC25: =IF($BZ25="","",SUM($BZ$2:$BZ25)) | CD25: =IF($BZ25="","",$CA25*(SUM($BZ$2:$BZ25)))
A26: =IF($B26="","",$A25+1) | B26: =IF(Investments_Import!A26="","",Investments_Import!A26) | C26: =IF(B26="","",B26*1) | D26: =$C26 | E26: =IF(Investments_Import!B26="","",Investments_Import!B26) | F26: =CONCATENATE(TEXT($D26,"dd-mmm-yyyy")," ",$E26) | G26: =IF($B26="","",COUNTIF($F$2:$F26,$F26)) | H26: =CONCATENATE(TEXT($D26,"dd-mmm-yyyy")," ",$E26," ",$G26) | I26: =IF(Investments_Import!C26="","",Investments_Import!C26) | J26: =IF(Investments_Import!D26="","",Investments_Import!D26) | K26: =IF($B26="","",$J26*1) | L26: =IF(Investments_Import!E26="","",Investments_Import!E26) | M26: =IF($L26="","",$L26*1) | N26: =IF(Investments_Import!F26="","",Investments_Import!F26) | O26: =IF($N26="","",$N26*1) | P26: =IF(Investments_Import!G26="","",Investments_Import!G26) | Q26: =IF(Investments_Import!H26="","",Investments_Import!H26) | R26: =IF($Q26="","",IF($Q26="USD",$P26,$P26*$J26)) | S26: =IF($R26="","",$R26*1) | U26: =IF(Mining_Import!A26="","",Mining_Import!A26) | V26: =IF(U26="","",U26*1) | W26: =V26 | X26: =IFERROR(INT($W26),"") | Y26: =$X26 | Z26: =IF(Mining_Import!B26="","",Mining_Import!B26) | AA26: =IF(Mining_Import!$C26="","",Mining_Import!$C26) | AB26: =IFERROR($AA26*1,"") | AC26: =IF($Y26>Dashboard!$Q$19,$AB26,"") | AD26: =IFERROR($AB26*$BU$19,"") | AE26: =IF(Mining_Import!D26="","",Mining_Import!D26) | AF26: =IF(Mining_Import!E26="","",Mining_Import!E26) | AG26: =IF(Mining_Import!F26="","",Mining_Import!F26) | AH26: =IF(Mining_Import!G26="","",Mining_Import!G26) | AI26: =IF(Mining_Import!H26="","",Mining_Import!H26) | AJ26: =IF(Mining_Import!I26="","",Mining_Import!I26) | AL26: =IFERROR(INDEX($E$2:$E$2500, MATCH(0, INDEX(COUNTIF($AL$1:AL25, $E$2:$E$2500), 0, 0), 0)), "") | AM26: =IF(Calculator!$AL26="","",LEFT(Calculator!$AL26, LEN(Calculator!$AL26)-3)) | AN26: {=IF($AL26="","",MAX(IF($E$2:$E$2500=$AL26,$C$2:$C$2500)))} | AO26: =IF($AN26="","",(TEXT($AN26,"dd-mmm-yyyy")&" "&$AL26&" "&"1")) | AP26: =$AO26 | AQ26: =IF($AL26="","",VLOOKUP($AO26, $H:$K, 3, 0)) | AR26: =IF($AQ26="","",$AQ26*1) | AS26: =IF($AL26="","",SUMIFS($O:$O,$E:$E,$AL26,$I:$I,"BUY")) | AT26: =IF($AL26="","",SUMIFS($O:$O,$E:$E,$AL26,$I:$I,"SELL")) | AU26: =IF($AL26="","",SUMIF($E:$E,$AL26,$S:$S)) | AV26: =IF($AL26="","",SUMIFS($M:$M,$E:$E,$AL26,$I:$I,"BUY")) | AW26: =IF($AL26="","",SUMIFS($M:$M,$E:$E,$AL26,$I:$I,"SELL")) | AX26: =IF($AZ26=1,$AV26-$AW26,"") | AY26: =$AM26 | AZ26: =IF($AY26="","",IFERROR(VLOOKUP($AP26,$BG$2:$BH$13,2, FALSE),"")) | BA26: =IF($AZ26=1, "CURRENT","") | BB26: =IF($AW26=0,"",IFERROR($AS26-$BD26,"")) | BC26: =IFERROR(IF($BA26="CURRENT",(($AT26-$BB26)-$AU26),IF($AW26=0,"",($AT26-$AS26)-$AU26)),"") | BD26: =IF($BA26="CURRENT",($AX26*$AR26),"") | BS26: =IF(Stock_Connector!B26="","",Stock_Connector!B26) -> BTC | BT26: =IF(Stock_Connector!C26="","",Stock_Connector!C26) -> 38927.94 | BU26: =IF(Stock_Connector!C26="","",Stock_Connector!C26) -> 38927.94 | BV26: =IF(Stock_Connector!E26="","",Stock_Connector!E26) | BW26: =IF(Stock_Connector!D26="","",Stock_Connector!D26) -> -0.032839243 | BY26: =Y26 | BZ26: =AB26 | CA26: =IFERROR(VLOOKUP($BY26,Account_Value!$C$2:$F$2500,4,0),"") | CB26: =IF(BZ26="","",BZ26*CA26) | CC26: =IF($BZ26="","",SUM($BZ$2:$BZ26)) | CD26: =IF($BZ26="","",$CA26*(SUM($BZ$2:$BZ26)))
A27: =IF($B27="","",$A26+1) | B27: =IF(Investments_Import!A27="","",Investments_Import!A27) | C27: =IF(B27="","",B27*1) | D27: =$C27 | E27: =IF(Investments_Import!B27="","",Investments_Import!B27) | F27: =CONCATENATE(TEXT($D27,"dd-mmm-yyyy")," ",$E27) | G27: =IF($B27="","",COUNTIF($F$2:$F27,$F27)) | H27: =CONCATENATE(TEXT($D27,"dd-mmm-yyyy")," ",$E27," ",$G27) | I27: =IF(Investments_Import!C27="","",Investments_Import!C27) | J27: =IF(Investments_Import!D27="","",Investments_Import!D27) | K27: =IF($B27="","",$J27*1) | L27: =IF(Investments_Import!E27="","",Investments_Import!E27) | M27: =IF($L27="","",$L27*1) | N27: =IF(Investments_Import!F27="","",Investments_Import!F27) | O27: =IF($N27="","",$N27*1) | P27: =IF(Investments_Import!G27="","",Investments_Import!G27) | Q27: =IF(Investments_Import!H27="","",Investments_Import!H27) | R27: =IF($Q27="","",IF($Q27="USD",$P27,$P27*$J27)) | S27: =IF($R27="","",$R27*1) | U27: =IF(Mining_Import!A27="","",Mining_Import!A27) | V27: =IF(U27="","",U27*1) | W27: =V27 | X27: =IFERROR(INT($W27),"") | Y27: =$X27 | Z27: =IF(Mining_Import!B27="","",Mining_Import!B27) | AA27: =IF(Mining_Import!$C27="","",Mining_Import!$C27) | AB27: =IFERROR($AA27*1,"") | AC27: =IF($Y27>Dashboard!$Q$19,$AB27,"") | AD27: =IFERROR($AB27*$BU$19,"") | AE27: =IF(Mining_Import!D27="","",Mining_Import!D27) | AF27: =IF(Mining_Import!E27="","",Mining_Import!E27) | AG27: =IF(Mining_Import!F27="","",Mining_Import!F27) | AH27: =IF(Mining_Import!G27="","",Mining_Import!G27) | AI27: =IF(Mining_Import!H27="","",Mining_Import!H27) | AJ27: =IF(Mining_Import!I27="","",Mining_Import!I27) | AL27: =IFERROR(INDEX($E$2:$E$2500, MATCH(0, INDEX(COUNTIF($AL$1:AL26, $E$2:$E$2500), 0, 0), 0)), "") | AM27: =IF(Calculator!$AL27="","",LEFT(Calculator!$AL27, LEN(Calculator!$AL27)-3)) | AN27: {=IF($AL27="","",MAX(IF($E$2:$E$2500=$AL27,$C$2:$C$2500)))} | AO27: =IF($AN27="","",(TEXT($AN27,"dd-mmm-yyyy")&" "&$AL27&" "&"1")) | AP27: =$AO27 | AQ27: =IF($AL27="","",VLOOKUP($AO27, $H:$K, 3, 0)) | AR27: =IF($AQ27="","",$AQ27*1) | AS27: =IF($AL27="","",SUMIFS($O:$O,$E:$E,$AL27,$I:$I,"BUY")) | AT27: =IF($AL27="","",SUMIFS($O:$O,$E:$E,$AL27,$I:$I,"SELL")) | AU27: =IF($AL27="","",SUMIF($E:$E,$AL27,$S:$S)) | AV27: =IF($AL27="","",SUMIFS($M:$M,$E:$E,$AL27,$I:$I,"BUY")) | AW27: =IF($AL27="","",SUMIFS($M:$M,$E:$E,$AL27,$I:$I,"SELL")) | AX27: =IF($AZ27=1,$AV27-$AW27,"") | AY27: =$AM27 | AZ27: =IF($AY27="","",IFERROR(VLOOKUP($AP27,$BG$2:$BH$13,2, FALSE),"")) | BA27: =IF($AZ27=1, "CURRENT","") | BB27: =IF($AW27=0,"",IFERROR($AS27-$BD27,"")) | BC27: =IFERROR(IF($BA27="CURRENT",(($AT27-$BB27)-$AU27),IF($AW27=0,"",($AT27-$AS27)-$AU27)),"") | BD27: =IF($BA27="CURRENT",($AX27*$AR27),"") | BS27: =IF(Stock_Connector!B27="","",Stock_Connector!B27) -> COMP | BT27: =IF(Stock_Connector!C27="","",Stock_Connector!C27) -> 437.47 | BU27: =IF(Stock_Connector!C27="","",Stock_Connector!C27) -> 437.47 | BV27: =IF(Stock_Connector!E27="","",Stock_Connector!E27) | BW27: =IF(Stock_Connector!D27="","",Stock_Connector!D27) -> -0.034090658 | BY27: =Y27 | BZ27: =AB27 | CA27: =IFERROR(VLOOKUP($BY27,Account_Value!$C$2:$F$2500,4,0),"") | CB27: =IF(BZ27="","",BZ27*CA27) | CC27: =IF($BZ27="","",SUM($BZ$2:$BZ27)) | CD27: =IF($BZ27="","",$CA27*(SUM($BZ$2:$BZ27)))
A28: =IF($B28="","",$A27+1) | B28: =IF(Investments_Import!A28="","",Investments_Import!A28) | C28: =IF(B28="","",B28*1) | D28: =$C28 | E28: =IF(Investments_Import!B28="","",Investments_Import!B28) | F28: =CONCATENATE(TEXT($D28,"dd-mmm-yyyy")," ",$E28) | G28: =IF($B28="","",COUNTIF($F$2:$F28,$F28)) | H28: =CONCATENATE(TEXT($D28,"dd-mmm-yyyy")," ",$E28," ",$G28) | I28: =IF(Investments_Import!C28="","",Investments_Import!C28) | J28: =IF(Investments_Import!D28="","",Investments_Import!D28) | K28: =IF($B28="","",$J28*1) | L28: =IF(Investments_Import!E28="","",Investments_Import!E28) | M28: =IF($L28="","",$L28*1) | N28: =IF(Investments_Import!F28="","",Investments_Import!F28) | O28: =IF($N28="","",$N28*1) | P28: =IF(Investments_Import!G28="","",Investments_Import!G28) | Q28: =IF(Investments_Import!H28="","",Investments_Import!H28) | R28: =IF($Q28="","",IF($Q28="USD",$P28,$P28*$J28)) | S28: =IF($R28="","",$R28*1) | U28: =IF(Mining_Import!A28="","",Mining_Import!A28) | V28: =IF(U28="","",U28*1) | W28: =V28 | X28: =IFERROR(INT($W28),"") | Y28: =$X28 | Z28: =IF(Mining_Import!B28="","",Mining_Import!B28) | AA28: =IF(Mining_Import!$C28="","",Mining_Import!$C28) | AB28: =IFERROR($AA28*1,"") | AC28: =IF($Y28>Dashboard!$Q$19,$AB28,"") | AD28: =IFERROR($AB28*$BU$19,"") | AE28: =IF(Mining_Import!D28="","",Mining_Import!D28) | AF28: =IF(Mining_Import!E28="","",Mining_Import!E28) | AG28: =IF(Mining_Import!F28="","",Mining_Import!F28) | AH28: =IF(Mining_Import!G28="","",Mining_Import!G28) | AI28: =IF(Mining_Import!H28="","",Mining_Import!H28) | AJ28: =IF(Mining_Import!I28="","",Mining_Import!I28) | AL28: =IFERROR(INDEX($E$2:$E$2500, MATCH(0, INDEX(COUNTIF($AL$1:AL27, $E$2:$E$2500), 0, 0), 0)), "") | AM28: =IF(Calculator!$AL28="","",LEFT(Calculator!$AL28, LEN(Calculator!$AL28)-3)) | AN28: {=IF($AL28="","",MAX(IF($E$2:$E$2500=$AL28,$C$2:$C$2500)))} | AO28: =IF($AN28="","",(TEXT($AN28,"dd-mmm-yyyy")&" "&$AL28&" "&"1")) | AP28: =$AO28 | AQ28: =IF($AL28="","",VLOOKUP($AO28, $H:$K, 3, 0)) | AR28: =IF($AQ28="","",$AQ28*1) | AS28: =IF($AL28="","",SUMIFS($O:$O,$E:$E,$AL28,$I:$I,"BUY")) | AT28: =IF($AL28="","",SUMIFS($O:$O,$E:$E,$AL28,$I:$I,"SELL")) | AU28: =IF($AL28="","",SUMIF($E:$E,$AL28,$S:$S)) | AV28: =IF($AL28="","",SUMIFS($M:$M,$E:$E,$AL28,$I:$I,"BUY")) | AW28: =IF($AL28="","",SUMIFS($M:$M,$E:$E,$AL28,$I:$I,"SELL")) | AX28: =IF($AZ28=1,$AV28-$AW28,"") | AY28: =$AM28 | AZ28: =IF($AY28="","",IFERROR(VLOOKUP($AP28,$BG$2:$BH$13,2, FALSE),"")) | BA28: =IF($AZ28=1, "CURRENT","") | BB28: =IF($AW28=0,"",IFERROR($AS28-$BD28,"")) | BC28: =IFERROR(IF($BA28="CURRENT",(($AT28-$BB28)-$AU28),IF($AW28=0,"",($AT28-$AS28)-$AU28)),"") | BD28: =IF($BA28="CURRENT",($AX28*$AR28),"") | BS28: =IF(Stock_Connector!B28="","",Stock_Connector!B28) -> ZEN | BT28: =IF(Stock_Connector!C28="","",Stock_Connector!C28) -> 35.28525 | BU28: =IF(Stock_Connector!C28="","",Stock_Connector!C28) -> 35.28525 | BV28: =IF(Stock_Connector!E28="","",Stock_Connector!E28) | BW28: =IF(Stock_Connector!D28="","",Stock_Connector!D28) -> -0.025869423 | BY28: =Y28 | BZ28: =AB28 | CA28: =IFERROR(VLOOKUP($BY28,Account_Value!$C$2:$F$2500,4,0),"") | CB28: =IF(BZ28="","",BZ28*CA28) | CC28: =IF($BZ28="","",SUM($BZ$2:$BZ28)) | CD28: =IF($BZ28="","",$BU$19*(SUM($BZ$2:$BZ28)))
A29: =IF($B29="","",$A28+1) | B29: =IF(Investments_Import!A29="","",Investments_Import!A29) | C29: =IF(B29="","",B29*1) | D29: =$C29 | E29: =IF(Investments_Import!B29="","",Investments_Import!B29) | F29: =CONCATENATE(TEXT($D29,"dd-mmm-yyyy")," ",$E29) | G29: =IF($B29="","",COUNTIF($F$2:$F29,$F29)) | H29: =CONCATENATE(TEXT($D29,"dd-mmm-yyyy")," ",$E29," ",$G29) | I29: =IF(Investments_Import!C29="","",Investments_Import!C29) | J29: =IF(Investments_Import!D29="","",Investments_Import!D29) | K29: =IF($B29="","",$J29*1) | L29: =IF(Investments_Import!E29="","",Investments_Import!E29) | M29: =IF($L29="","",$L29*1) | N29: =IF(Investments_Import!F29="","",Investments_Import!F29) | O29: =IF($N29="","",$N29*1) | P29: =IF(Investments_Import!G29="","",Investments_Import!G29) | Q29: =IF(Investments_Import!H29="","",Investments_Import!H29) | R29: =IF($Q29="","",IF($Q29="USD",$P29,$P29*$J29)) | S29: =IF($R29="","",$R29*1) | U29: =IF(Mining_Import!A29="","",Mining_Import!A29) | V29: =IF(U29="","",U29*1) | W29: =V29 | X29: =IFERROR(INT($W29),"") | Y29: =$X29 | Z29: =IF(Mining_Import!B29="","",Mining_Import!B29) | AA29: =IF(Mining_Import!$C29="","",Mining_Import!$C29) | AB29: =IFERROR($AA29*1,"") | AC29: =IF($Y29>Dashboard!$Q$19,$AB29,"") | AD29: =IFERROR($AB29*$BU$19,"") | AE29: =IF(Mining_Import!D29="","",Mining_Import!D29) | AF29: =IF(Mining_Import!E29="","",Mining_Import!E29) | AG29: =IF(Mining_Import!F29="","",Mining_Import!F29) | AH29: =IF(Mining_Import!G29="","",Mining_Import!G29) | AI29: =IF(Mining_Import!H29="","",Mining_Import!H29) | AJ29: =IF(Mining_Import!I29="","",Mining_Import!I29) | AL29: =IFERROR(INDEX($E$2:$E$2500, MATCH(0, INDEX(COUNTIF($AL$1:AL28, $E$2:$E$2500), 0, 0), 0)), "") | AM29: =IF(Calculator!$AL29="","",LEFT(Calculator!$AL29, LEN(Calculator!$AL29)-3)) | AN29: {=IF($AL29="","",MAX(IF($E$2:$E$2500=$AL29,$C$2:$C$2500)))} | AO29: =IF($AN29="","",(TEXT($AN29,"dd-mmm-yyyy")&" "&$AL29&" "&"1")) | AP29: =$AO29 | AQ29: =IF($AL29="","",VLOOKUP($AO29, $H:$K, 3, 0)) | AR29: =IF($AQ29="","",$AQ29*1) | AS29: =IF($AL29="","",SUMIFS($O:$O,$E:$E,$AL29,$I:$I,"BUY")) | AT29: =IF($AL29="","",SUMIFS($O:$O,$E:$E,$AL29,$I:$I,"SELL")) | AU29: =IF($AL29="","",SUMIF($E:$E,$AL29,$S:$S)) | AV29: =IF($AL29="","",SUMIFS($M:$M,$E:$E,$AL29,$I:$I,"BUY")) | AW29: =IF($AL29="","",SUMIFS($M:$M,$E:$E,$AL29,$I:$I,"SELL")) | AX29: =IF($AZ29=1,$AV29-$AW29,"") | AY29: =$AM29 | AZ29: =IF($AY29="","",IFERROR(VLOOKUP($AP29,$BG$2:$BH$13,2, FALSE),"")) | BA29: =IF($AZ29=1, "CURRENT","") | BB29: =IF($AW29=0,"",IFERROR($AS29-$BD29,"")) | BC29: =IFERROR(IF($BA29="CURRENT",(($AT29-$BB29)-$AU29),IF($AW29=0,"",($AT29-$AS29)-$AU29)),"") | BD29: =IF($BA29="CURRENT",($AX29*$AR29),"") | BS29: =IF(Stock_Connector!B29="","",Stock_Connector!B29) -> UNI | BT29: =IF(Stock_Connector!C29="","",Stock_Connector!C29) -> 18.46 | BU29: =IF(Stock_Connector!C29="","",Stock_Connector!C29) -> 18.46 | BV29: =IF(Stock_Connector!E29="","",Stock_Connector!E29) | BW29: =IF(Stock_Connector!D29="","",Stock_Connector!D29) -> -0.049433574 | BY29: =Y29 | BZ29: =AB29 | CA29: =IFERROR(VLOOKUP($BY29,Account_Value!$C$2:$F$2500,4,0),"") | CB29: =IF(BZ29="","",BZ29*CA29) | CC29: =IF($BZ29="","",SUM($BZ$2:$BZ29)) | CD29: =IF($BZ29="","",$BU$19*(SUM($BZ$2:$BZ29)))
A30: =IF($B30="","",$A29+1) | B30: =IF(Investments_Import!A30="","",Investments_Import!A30) | C30: =IF(B30="","",B30*1) | D30: =$C30 | E30: =IF(Investments_Import!B30="","",Investments_Import!B30) | F30: =CONCATENATE(TEXT($D30,"dd-mmm-yyyy")," ",$E30) | G30: =IF($B30="","",COUNTIF($F$2:$F30,$F30)) | H30: =CONCATENATE(TEXT($D30,"dd-mmm-yyyy")," ",$E30," ",$G30) | I30: =IF(Investments_Import!C30="","",Investments_Import!C30) | J30: =IF(Investments_Import!D30="","",Investments_Import!D30) | K30: =IF($B30="","",$J30*1) | L30: =IF(Investments_Import!E30="","",Investments_Import!E30) | M30: =IF($L30="","",$L30*1) | N30: =IF(Investments_Import!F30="","",Investments_Import!F30) | O30: =IF($N30="","",$N30*1) | P30: =IF(Investments_Import!G30="","",Investments_Import!G30) | Q30: =IF(Investments_Import!H30="","",Investments_Import!H30) | R30: =IF($Q30="","",IF($Q30="USD",$P30,$P30*$J30)) | S30: =IF($R30="","",$R30*1) | U30: =IF(Mining_Import!A30="","",Mining_Import!A30) | V30: =IF(U30="","",U30*1) | W30: =V30 | X30: =IFERROR(INT($W30),"") | Y30: =$X30 | Z30: =IF(Mining_Import!B30="","",Mining_Import!B30) | AA30: =IF(Mining_Import!$C30="","",Mining_Import!$C30) | AB30: =IFERROR($AA30*1,"") | AC30: =IF($Y30>Dashboard!$Q$19,$AB30,"") | AD30: =IFERROR($AB30*$BU$19,"") | AE30: =IF(Mining_Import!D30="","",Mining_Import!D30) | AF30: =IF(Mining_Import!E30="","",Mining_Import!E30) | AG30: =IF(Mining_Import!F30="","",Mining_Import!F30) | AH30: =IF(Mining_Import!G30="","",Mining_Import!G30) | AI30: =IF(Mining_Import!H30="","",Mining_Import!H30) | AJ30: =IF(Mining_Import!I30="","",Mining_Import!I30) | AL30: =IFERROR(INDEX($E$2:$E$2500, MATCH(0, INDEX(COUNTIF($AL$1:AL29, $E$2:$E$2500), 0, 0), 0)), "") | AM30: =IF(Calculator!$AL30="","",LEFT(Calculator!$AL30, LEN(Calculator!$AL30)-3)) | AN30: {=IF($AL30="","",MAX(IF($E$2:$E$2500=$AL30,$C$2:$C$2500)))} | AO30: =IF($AN30="","",(TEXT($AN30,"dd-mmm-yyyy")&" "&$AL30&" "&"1")) | AP30: =$AO30 | AQ30: =IF($AL30="","",VLOOKUP($AO30, $H:$K, 3, 0)) | AR30: =IF($AQ30="","",$AQ30*1) | AS30: =IF($AL30="","",SUMIFS($O:$O,$E:$E,$AL30,$I:$I,"BUY")) | AT30: =IF($AL30="","",SUMIFS($O:$O,$E:$E,$AL30,$I:$I,"SELL")) | AU30: =IF($AL30="","",SUMIF($E:$E,$AL30,$S:$S)) | AV30: =IF($AL30="","",SUMIFS($M:$M,$E:$E,$AL30,$I:$I,"BUY")) | AW30: =IF($AL30="","",SUMIFS($M:$M,$E:$E,$AL30,$I:$I,"SELL")) | AX30: =IF($AZ30=1,$AV30-$AW30,"") | AY30: =$AM30 | AZ30: =IF($AY30="","",IFERROR(VLOOKUP($AP30,$BG$2:$BH$13,2, FALSE),"")) | BA30: =IF($AZ30=1, "CURRENT","") | BB30: =IF($AW30=0,"",IFERROR($AS30-$BD30,"")) | BC30: =IFERROR(IF($BA30="CURRENT",(($AT30-$BB30)-$AU30),IF($AW30=0,"",($AT30-$AS30)-$AU30)),"") | BD30: =IF($BA30="CURRENT",($AX30*$AR30),"") | BS30: =IF(Stock_Connector!B30="","",Stock_Connector!B30) -> BAND | BT30: =IF(Stock_Connector!C30="","",Stock_Connector!C30) -> 11.28 | BU30: =IF(Stock_Connector!C30="","",Stock_Connector!C30) -> 11.28 | BV30: =IF(Stock_Connector!E30="","",Stock_Connector!E30) | BW30: =IF(Stock_Connector!D30="","",Stock_Connector!D30) -> -0.0079155673 | BY30: =Y30 | BZ30: =AB30 | CA30: =IFERROR(VLOOKUP($BY30,Account_Value!$C$2:$F$2500,4,0),"") | CB30: =IF(BZ30="","",BZ30*CA30) | CC30: =IF($BZ30="","",SUM($BZ$2:$BZ30)) | CD30: =IF($BZ30="","",$BU$19*(SUM($BZ$2:$BZ30)))
A31: =IF($B31="","",$A30+1) | B31: =IF(Investments_Import!A31="","",Investments_Import!A31) | C31: =IF(B31="","",B31*1) | D31: =$C31 | E31: =IF(Investments_Import!B31="","",Investments_Import!B31) | F31: =CONCATENATE(TEXT($D31,"dd-mmm-yyyy")," ",$E31) | G31: =IF($B31="","",COUNTIF($F$2:$F31,$F31)) | H31: =CONCATENATE(TEXT($D31,"dd-mmm-yyyy")," ",$E31," ",$G31) | I31: =IF(Investments_Import!C31="","",Investments_Import!C31) | J31: =IF(Investments_Import!D31="","",Investments_Import!D31) | K31: =IF($B31="","",$J31*1) | L31: =IF(Investments_Import!E31="","",Investments_Import!E31) | M31: =IF($L31="","",$L31*1) | N31: =IF(Investments_Import!F31="","",Investments_Import!F31) | O31: =IF($N31="","",$N31*1) | P31: =IF(Investments_Import!G31="","",Investments_Import!G31) | Q31: =IF(Investments_Import!H31="","",Investments_Import!H31) | R31: =IF($Q31="","",IF($Q31="USD",$P31,$P31*$J31)) | S31: =IF($R31="","",$R31*1) | U31: =IF(Mining_Import!A31="","",Mining_Import!A31) | V31: =IF(U31="","",U31*1) | W31: =V31 | X31: =IFERROR(INT($W31),"") | Y31: =$X31 | Z31: =IF(Mining_Import!B31="","",Mining_Import!B31) | AA31: =IF(Mining_Import!$C31="","",Mining_Import!$C31) | AB31: =IFERROR($AA31*1,"") | AC31: =IF($Y31>Dashboard!$Q$19,$AB31,"") | AD31: =IFERROR($AB31*$BU$19,"") | AE31: =IF(Mining_Import!D31="","",Mining_Import!D31) | AF31: =IF(Mining_Import!E31="","",Mining_Import!E31) | AG31: =IF(Mining_Import!F31="","",Mining_Import!F31) | AH31: =IF(Mining_Import!G31="","",Mining_Import!G31) | AI31: =IF(Mining_Import!H31="","",Mining_Import!H31) | AJ31: =IF(Mining_Import!I31="","",Mining_Import!I31) | AL31: =IFERROR(INDEX($E$2:$E$2500, MATCH(0, INDEX(COUNTIF($AL$1:AL30, $E$2:$E$2500), 0, 0), 0)), "") | AM31: =IF(Calculator!$AL31="","",LEFT(Calculator!$AL31, LEN(Calculator!$AL31)-3)) | AN31: {=IF($AL31="","",MAX(IF($E$2:$E$2500=$AL31,$C$2:$C$2500)))} | AO31: =IF($AN31="","",(TEXT($AN31,"dd-mmm-yyyy")&" "&$AL31&" "&"1")) | AP31: =$AO31 | AQ31: =IF($AL31="","",VLOOKUP($AO31, $H:$K, 3, 0)) | AR31: =IF($AQ31="","",$AQ31*1) | AS31: =IF($AL31="","",SUMIFS($O:$O,$E:$E,$AL31,$I:$I,"BUY")) | AT31: =IF($AL31="","",SUMIFS($O:$O,$E:$E,$AL31,$I:$I,"SELL")) | AU31: =IF($AL31="","",SUMIF($E:$E,$AL31,$S:$S)) | AV31: =IF($AL31="","",SUMIFS($M:$M,$E:$E,$AL31,$I:$I,"BUY")) | AW31: =IF($AL31="","",SUMIFS($M:$M,$E:$E,$AL31,$I:$I,"SELL")) | AX31: =IF($AZ31=1,$AV31-$AW31,"") | AY31: =$AM31 | AZ31: =IF($AY31="","",IFERROR(VLOOKUP($AP31,$BG$2:$BH$13,2, FALSE),"")) | BA31: =IF($AZ31=1, "CURRENT","") | BB31: =IF($AW31=0,"",IFERROR($AS31-$BD31,"")) | BC31: =IFERROR(IF($BA31="CURRENT",(($AT31-$BB31)-$AU31),IF($AW31=0,"",($AT31-$AS31)-$AU31)),"") | BD31: =IF($BA31="CURRENT",($AX31*$AR31),"") | BS31: =IF(Stock_Connector!B31="","",Stock_Connector!B31) -> WAVES | BT31: =IF(Stock_Connector!C31="","",Stock_Connector!C31) -> 8.141133 | BU31: =IF(Stock_Connector!C31="","",Stock_Connector!C31) -> 8.141133 | BV31: =IF(Stock_Connector!E31="","",Stock_Connector!E31) | BW31: =IF(Stock_Connector!D31="","",Stock_Connector!D31) -> 0.021997891 | BY31: =Y31 | BZ31: =AB31 | CA31: =IFERROR(VLOOKUP($BY31,Account_Value!$C$2:$F$2500,4,0),"") | CB31: =IF(BZ31="","",BZ31*CA31) | CC31: =IF($BZ31="","",SUM($BZ$2:$BZ31)) | CD31: =IF($BZ31="","",$BU$19*(SUM($BZ$2:$BZ31)))
A32: =IF($B32="","",$A31+1) | B32: =IF(Investments_Import!A32="","",Investments_Import!A32) | C32: =IF(B32="","",B32*1) | D32: =$C32 | E32: =IF(Investments_Import!B32="","",Investments_Import!B32) | F32: =CONCATENATE(TEXT($D32,"dd-mmm-yyyy")," ",$E32) | G32: =IF($B32="","",COUNTIF($F$2:$F32,$F32)) | H32: =CONCATENATE(TEXT($D32,"dd-mmm-yyyy")," ",$E32," ",$G32) | I32: =IF(Investments_Import!C32="","",Investments_Import!C32) | J32: =IF(Investments_Import!D32="","",Investments_Import!D32) | K32: =IF($B32="","",$J32*1) | L32: =IF(Investments_Import!E32="","",Investments_Import!E32) | M32: =IF($L32="","",$L32*1) | N32: =IF(Investments_Import!F32="","",Investments_Import!F32) | O32: =IF($N32="","",$N32*1) | P32: =IF(Investments_Import!G32="","",Investments_Import!G32) | Q32: =IF(Investments_Import!H32="","",Investments_Import!H32) | R32: =IF($Q32="","",IF($Q32="USD",$P32,$P32*$J32)) | S32: =IF($R32="","",$R32*1) | U32: =IF(Mining_Import!A32="","",Mining_Import!A32) | V32: =IF(U32="","",U32*1) | W32: =V32 | X32: =IFERROR(INT($W32),"") | Y32: =$X32 | Z32: =IF(Mining_Import!B32="","",Mining_Import!B32) | AA32: =IF(Mining_Import!$C32="","",Mining_Import!$C32) | AB32: =IFERROR($AA32*1,"") | AC32: =IF($Y32>Dashboard!$Q$19,$AB32,"") | AD32: =IFERROR($AB32*$BU$19,"") | AE32: =IF(Mining_Import!D32="","",Mining_Import!D32) | AF32: =IF(Mining_Import!E32="","",Mining_Import!E32) | AG32: =IF(Mining_Import!F32="","",Mining_Import!F32) | AH32: =IF(Mining_Import!G32="","",Mining_Import!G32) | AI32: =IF(Mining_Import!H32="","",Mining_Import!H32) | AJ32: =IF(Mining_Import!I32="","",Mining_Import!I32) | AL32: =IFERROR(INDEX($E$2:$E$2500, MATCH(0, INDEX(COUNTIF($AL$1:AL31, $E$2:$E$2500), 0, 0), 0)), "") | AM32: =IF(Calculator!$AL32="","",LEFT(Calculator!$AL32, LEN(Calculator!$AL32)-3)) | AN32: {=IF($AL32="","",MAX(IF($E$2:$E$2500=$AL32,$C$2:$C$2500)))} | AO32: =IF($AN32="","",(TEXT($AN32,"dd-mmm-yyyy")&" "&$AL32&" "&"1")) | AP32: =$AO32 | AQ32: =IF($AL32="","",VLOOKUP($AO32, $H:$K, 3, 0)) | AR32: =IF($AQ32="","",$AQ32*1) | AS32: =IF($AL32="","",SUMIFS($O:$O,$E:$E,$AL32,$I:$I,"BUY")) | AT32: =IF($AL32="","",SUMIFS($O:$O,$E:$E,$AL32,$I:$I,"SELL")) | AU32: =IF($AL32="","",SUMIF($E:$E,$AL32,$S:$S)) | AV32: =IF($AL32="","",SUMIFS($M:$M,$E:$E,$AL32,$I:$I,"BUY")) | AW32: =IF($AL32="","",SUMIFS($M:$M,$E:$E,$AL32,$I:$I,"SELL")) | AX32: =IF($AZ32=1,$AV32-$AW32,"") | AY32: =$AM32 | AZ32: =IF($AY32="","",IFERROR(VLOOKUP($AP32,$BG$2:$BH$13,2, FALSE),"")) | BA32: =IF($AZ32=1, "CURRENT","") | BB32: =IF($AW32=0,"",IFERROR($AS32-$BD32,"")) | BC32: =IFERROR(IF($BA32="CURRENT",(($AT32-$BB32)-$AU32),IF($AW32=0,"",($AT32-$AS32)-$AU32)),"") | BD32: =IF($BA32="CURRENT",($AX32*$AR32),"") | BS32: =IF(Stock_Connector!B32="","",Stock_Connector!B32) -> NANO | BT32: =IF(Stock_Connector!C32="","",Stock_Connector!C32) -> 3.828 | BU32: =IF(Stock_Connector!C32="","",Stock_Connector!C32) -> 3.828 | BV32: =IF(Stock_Connector!E32="","",Stock_Connector!E32) | BW32: =IF(Stock_Connector!D32="","",Stock_Connector!D32) -> 0.069572506 | BY32: =Y32 | BZ32: =AB32 | CA32: =IFERROR(VLOOKUP($BY32,Account_Value!$C$2:$F$2500,4,0),"") | CB32: =IF(BZ32="","",BZ32*CA32) | CC32: =IF($BZ32="","",SUM($BZ$2:$BZ32)) | CD32: =IF($BZ32="","",$BU$19*(SUM($BZ$2:$BZ32)))
A33: =IF($B33="","",$A32+1) | B33: =IF(Investments_Import!A33="","",Investments_Import!A33) | C33: =IF(B33="","",B33*1) | D33: =$C33 | E33: =IF(Investments_Import!B33="","",Investments_Import!B33) | F33: =CONCATENATE(TEXT($D33,"dd-mmm-yyyy")," ",$E33) | G33: =IF($B33="","",COUNTIF($F$2:$F33,$F33)) | H33: =CONCATENATE(TEXT($D33,"dd-mmm-yyyy")," ",$E33," ",$G33) | I33: =IF(Investments_Import!C33="","",Investments_Import!C33) | J33: =IF(Investments_Import!D33="","",Investments_Import!D33) | K33: =IF($B33="","",$J33*1) | L33: =IF(Investments_Import!E33="","",Investments_Import!E33) | M33: =IF($L33="","",$L33*1) | N33: =IF(Investments_Import!F33="","",Investments_Import!F33) | O33: =IF($N33="","",$N33*1) | P33: =IF(Investments_Import!G33="","",Investments_Import!G33) | Q33: =IF(Investments_Import!H33="","",Investments_Import!H33) | R33: =IF($Q33="","",IF($Q33="USD",$P33,$P33*$J33)) | S33: =IF($R33="","",$R33*1) | U33: =IF(Mining_Import!A33="","",Mining_Import!A33) | V33: =IF(U33="","",U33*1) | W33: =V33 | X33: =IFERROR(INT($W33),"") | Y33: =$X33 | Z33: =IF(Mining_Import!B33="","",Mining_Import!B33) | AA33: =IF(Mining_Import!$C33="","",Mining_Import!$C33) | AB33: =IFERROR($AA33*1,"") | AC33: =IF($Y33>Dashboard!$Q$19,$AB33,"") | AD33: =IFERROR($AB33*$BU$19,"") | AE33: =IF(Mining_Import!D33="","",Mining_Import!D33) | AF33: =IF(Mining_Import!E33="","",Mining_Import!E33) | AG33: =IF(Mining_Import!F33="","",Mining_Import!F33) | AH33: =IF(Mining_Import!G33="","",Mining_Import!G33) | AI33: =IF(Mining_Import!H33="","",Mining_Import!H33) | AJ33: =IF(Mining_Import!I33="","",Mining_Import!I33) | AL33: =IFERROR(INDEX($E$2:$E$2500, MATCH(0, INDEX(COUNTIF($AL$1:AL32, $E$2:$E$2500), 0, 0), 0)), "") | AM33: =IF(Calculator!$AL33="","",LEFT(Calculator!$AL33, LEN(Calculator!$AL33)-3)) | AN33: {=IF($AL33="","",MAX(IF($E$2:$E$2500=$AL33,$C$2:$C$2500)))} | AO33: =IF($AN33="","",(TEXT($AN33,"dd-mmm-yyyy")&" "&$AL33&" "&"1")) | AP33: =$AO33 | AQ33: =IF($AL33="","",VLOOKUP($AO33, $H:$K, 3, 0)) | AR33: =IF($AQ33="","",$AQ33*1) | AS33: =IF($AL33="","",SUMIFS($O:$O,$E:$E,$AL33,$I:$I,"BUY")) | AT33: =IF($AL33="","",SUMIFS($O:$O,$E:$E,$AL33,$I:$I,"SELL")) | AU33: =IF($AL33="","",SUMIF($E:$E,$AL33,$S:$S)) | AV33: =IF($AL33="","",SUMIFS($M:$M,$E:$E,$AL33,$I:$I,"BUY")) | AW33: =IF($AL33="","",SUMIFS($M:$M,$E:$E,$AL33,$I:$I,"SELL")) | AX33: =IF($AZ33=1,$AV33-$AW33,"") | AY33: =$AM33 | AZ33: =IF($AY33="","",IFERROR(VLOOKUP($AP33,$BG$2:$BH$13,2, FALSE),"")) | BA33: =IF($AZ33=1, "CURRENT","") | BB33: =IF($AW33=0,"",IFERROR($AS33-$BD33,"")) | BC33: =IFERROR(IF($BA33="CURRENT",(($AT33-$BB33)-$AU33),IF($AW33=0,"",($AT33-$AS33)-$AU33)),"") | BD33: =IF($BA33="CURRENT",($AX33*$AR33),"") | BS33: =IF(Stock_Connector!B33="","",Stock_Connector!B33) -> ADA | BT33: =IF(Stock_Connector!C33="","",Stock_Connector!C33) -> 0.6827 | BU33: =IF(Stock_Connector!C33="","",Stock_Connector!C33) -> 0.6827 | BV33: =IF(Stock_Connector!E33="","",Stock_Connector!E33) | BW33: =IF(Stock_Connector!D33="","",Stock_Connector!D33) -> 0.27155895 | BY33: =Y33 | BZ33: =AB33 | CA33: =IFERROR(VLOOKUP($BY33,Account_Value!$C$2:$F$2500,4,0),"") | CB33: =IF(BZ33="","",BZ33*CA33) | CC33: =IF($BZ33="","",SUM($BZ$2:$BZ33)) | CD33: =IF($BZ33="","",$BU$19*(SUM($BZ$2:$BZ33)))
A34: =IF($B34="","",$A33+1) | B34: =IF(Investments_Import!A34="","",Investments_Import!A34) | C34: =IF(B34="","",B34*1) | D34: =$C34 | E34: =IF(Investments_Import!B34="","",Investments_Import!B34) | F34: =CONCATENATE(TEXT($D34,"dd-mmm-yyyy")," ",$E34) | G34: =IF($B34="","",COUNTIF($F$2:$F34,$F34)) | H34: =CONCATENATE(TEXT($D34,"dd-mmm-yyyy")," ",$E34," ",$G34) | I34: =IF(Investments_Import!C34="","",Investments_Import!C34) | J34: =IF(Investments_Import!D34="","",Investments_Import!D34) | K34: =IF($B34="","",$J34*1) | L34: =IF(Investments_Import!E34="","",Investments_Import!E34) | M34: =IF($L34="","",$L34*1) | N34: =IF(Investments_Import!F34="","",Investments_Import!F34) | O34: =IF($N34="","",$N34*1) | P34: =IF(Investments_Import!G34="","",Investments_Import!G34) | Q34: =IF(Investments_Import!H34="","",Investments_Import!H34) | R34: =IF($Q34="","",IF($Q34="USD",$P34,$P34*$J34)) | S34: =IF($R34="","",$R34*1) | U34: =IF(Mining_Import!A34="","",Mining_Import!A34) | V34: =IF(U34="","",U34*1) | W34: =V34 | X34: =IFERROR(INT($W34),"") | Y34: =$X34 | Z34: =IF(Mining_Import!B34="","",Mining_Import!B34) | AA34: =IF(Mining_Import!$C34="","",Mining_Import!$C34) | AB34: =IFERROR($AA34*1,"") | AC34: =IF($Y34>Dashboard!$Q$19,$AB34,"") | AD34: =IFERROR($AB34*$BU$19,"") | AE34: =IF(Mining_Import!D34="","",Mining_Import!D34) | AF34: =IF(Mining_Import!E34="","",Mining_Import!E34) | AG34: =IF(Mining_Import!F34="","",Mining_Import!F34) | AH34: =IF(Mining_Import!G34="","",Mining_Import!G34) | AI34: =IF(Mining_Import!H34="","",Mining_Import!H34) | AJ34: =IF(Mining_Import!I34="","",Mining_Import!I34) | AL34: =IFERROR(INDEX($E$2:$E$2500, MATCH(0, INDEX(COUNTIF($AL$1:AL33, $E$2:$E$2500), 0, 0), 0)), "") | AM34: =IF(Calculator!$AL34="","",LEFT(Calculator!$AL34, LEN(Calculator!$AL34)-3)) | AN34: {=IF($AL34="","",MAX(IF($E$2:$E$2500=$AL34,$C$2:$C$2500)))} | AO34: =IF($AN34="","",(TEXT($AN34,"dd-mmm-yyyy")&" "&$AL34&" "&"1")) | AP34: =$AO34 | AQ34: =IF($AL34="","",VLOOKUP($AO34, $H:$K, 3, 0)) | AR34: =IF($AQ34="","",$AQ34*1) | AS34: =IF($AL34="","",SUMIFS($O:$O,$E:$E,$AL34,$I:$I,"BUY")) | AT34: =IF($AL34="","",SUMIFS($O:$O,$E:$E,$AL34,$I:$I,"SELL")) | AU34: =IF($AL34="","",SUMIF($E:$E,$AL34,$S:$S)) | AV34: =IF($AL34="","",SUMIFS($M:$M,$E:$E,$AL34,$I:$I,"BUY")) | AW34: =IF($AL34="","",SUMIFS($M:$M,$E:$E,$AL34,$I:$I,"SELL")) | AX34: =IF($AZ34=1,$AV34-$AW34,"") | AY34: =$AM34 | AZ34: =IF($AY34="","",IFERROR(VLOOKUP($AP34,$BG$2:$BH$13,2, FALSE),"")) | BA34: =IF($AZ34=1, "CURRENT","") | BB34: =IF($AW34=0,"",IFERROR($AS34-$BD34,"")) | BC34: =IFERROR(IF($BA34="CURRENT",(($AT34-$BB34)-$AU34),IF($AW34=0,"",($AT34-$AS34)-$AU34)),"") | BD34: =IF($BA34="CURRENT",($AX34*$AR34),"") | BS34: =IF(Stock_Connector!B34="","",Stock_Connector!B34) -> BAT | BT34: =IF(Stock_Connector!C34="","",Stock_Connector!C34) -> 0.4022018 | BU34: =IF(Stock_Connector!C34="","",Stock_Connector!C34) -> 0.4022018 | BV34: =IF(Stock_Connector!E34="","",Stock_Connector!E34) | BW34: =IF(Stock_Connector!D34="","",Stock_Connector!D34) -> 0.17025948 | BY34: =Y34 | BZ34: =AB34 | CA34: =IFERROR(VLOOKUP($BY34,Account_Value!$C$2:$F$2500,4,0),"") | CB34: =IF(BZ34="","",BZ34*CA34) | CC34: =IF($BZ34="","",SUM($BZ$2:$BZ34)) | CD34: =IF($BZ34="","",$BU$19*(SUM($BZ$2:$BZ34)))
A35: =IF($B35="","",$A34+1) | B35: =IF(Investments_Import!A35="","",Investments_Import!A35) | C35: =IF(B35="","",B35*1) | D35: =$C35 | E35: =IF(Investments_Import!B35="","",Investments_Import!B35) | F35: =CONCATENATE(TEXT($D35,"dd-mmm-yyyy")," ",$E35) | G35: =IF($B35="","",COUNTIF($F$2:$F35,$F35)) | H35: =CONCATENATE(TEXT($D35,"dd-mmm-yyyy")," ",$E35," ",$G35) | I35: =IF(Investments_Import!C35="","",Investments_Import!C35) | J35: =IF(Investments_Import!D35="","",Investments_Import!D35) | K35: =IF($B35="","",$J35*1) | L35: =IF(Investments_Import!E35="","",Investments_Import!E35) | M35: =IF($L35="","",$L35*1) | N35: =IF(Investments_Import!F35="","",Investments_Import!F35) | O35: =IF($N35="","",$N35*1) | P35: =IF(Investments_Import!G35="","",Investments_Import!G35) | Q35: =IF(Investments_Import!H35="","",Investments_Import!H35) | R35: =IF($Q35="","",IF($Q35="USD",$P35,$P35*$J35)) | S35: =IF($R35="","",$R35*1) | U35: =IF(Mining_Import!A35="","",Mining_Import!A35) | V35: =IF(U35="","",U35*1) | W35: =V35 | X35: =IFERROR(INT($W35),"") | Y35: =$X35 | Z35: =IF(Mining_Import!B35="","",Mining_Import!B35) | AA35: =IF(Mining_Import!$C35="","",Mining_Import!$C35) | AB35: =IFERROR($AA35*1,"") | AC35: =IF($Y35>Dashboard!$Q$19,$AB35,"") | AD35: =IFERROR($AB35*$BU$19,"") | AE35: =IF(Mining_Import!D35="","",Mining_Import!D35) | AF35: =IF(Mining_Import!E35="","",Mining_Import!E35) | AG35: =IF(Mining_Import!F35="","",Mining_Import!F35) | AH35: =IF(Mining_Import!G35="","",Mining_Import!G35) | AI35: =IF(Mining_Import!H35="","",Mining_Import!H35) | AJ35: =IF(Mining_Import!I35="","",Mining_Import!I35) | AL35: =IFERROR(INDEX($E$2:$E$2500, MATCH(0, INDEX(COUNTIF($AL$1:AL34, $E$2:$E$2500), 0, 0), 0)), "") | AM35: =IF(Calculator!$AL35="","",LEFT(Calculator!$AL35, LEN(Calculator!$AL35)-3)) | AN35: {=IF($AL35="","",MAX(IF($E$2:$E$2500=$AL35,$C$2:$C$2500)))} | AO35: =IF($AN35="","",(TEXT($AN35,"dd-mmm-yyyy")&" "&$AL35&" "&"1")) | AP35: =$AO35 | AQ35: =IF($AL35="","",VLOOKUP($AO35, $H:$K, 3, 0)) | AR35: =IF($AQ35="","",$AQ35*1) | AS35: =IF($AL35="","",SUMIFS($O:$O,$E:$E,$AL35,$I:$I,"BUY")) | AT35: =IF($AL35="","",SUMIFS($O:$O,$E:$E,$AL35,$I:$I,"SELL")) | AU35: =IF($AL35="","",SUMIF($E:$E,$AL35,$S:$S)) | AV35: =IF($AL35="","",SUMIFS($M:$M,$E:$E,$AL35,$I:$I,"BUY")) | AW35: =IF($AL35="","",SUMIFS($M:$M,$E:$E,$AL35,$I:$I,"SELL")) | AX35: =IF($AZ35=1,$AV35-$AW35,"") | AY35: =$AM35 | AZ35: =IF($AY35="","",IFERROR(VLOOKUP($AP35,$BG$2:$BH$13,2, FALSE),"")) | BA35: =IF($AZ35=1, "CURRENT","") | BB35: =IF($AW35=0,"",IFERROR($AS35-$BD35,"")) | BC35: =IFERROR(IF($BA35="CURRENT",(($AT35-$BB35)-$AU35),IF($AW35=0,"",($AT35-$AS35)-$AU35)),"") | BD35: =IF($BA35="CURRENT",($AX35*$AR35),"") | BS35: =IF(Stock_Connector!B35="","",Stock_Connector!B35) -> DAI | BT35: =IF(Stock_Connector!C35="","",Stock_Connector!C35) -> 1.001 | BU35: =IF(Stock_Connector!C35="","",Stock_Connector!C35) -> 1.001 | BV35: =IF(Stock_Connector!E35="","",Stock_Connector!E35) | BW35: =IF(Stock_Connector!D35="","",Stock_Connector!D35) -> -0.00099800399 | BY35: =Y35 | BZ35: =AB35 | CA35: =IFERROR(VLOOKUP($BY35,Account_Value!$C$2:$F$2500,4,0),"") | CB35: =IF(BZ35="","",BZ35*CA35) | CC35: =IF($BZ35="","",SUM($BZ$2:$BZ35)) | CD35: =IF($BZ35="","",$BU$19*(SUM($BZ$2:$BZ35)))
A36: =IF($B36="","",$A35+1) | B36: =IF(Investments_Import!A36="","",Investments_Import!A36) | C36: =IF(B36="","",B36*1) | D36: =$C36 | E36: =IF(Investments_Import!B36="","",Investments_Import!B36) | F36: =CONCATENATE(TEXT($D36,"dd-mmm-yyyy")," ",$E36) | G36: =IF($B36="","",COUNTIF($F$2:$F36,$F36)) | H36: =CONCATENATE(TEXT($D36,"dd-mmm-yyyy")," ",$E36," ",$G36) | I36: =IF(Investments_Import!C36="","",Investments_Import!C36) | J36: =IF(Investments_Import!D36="","",Investments_Import!D36) | K36: =IF($B36="","",$J36*1) | L36: =IF(Investments_Import!E36="","",Investments_Import!E36) | M36: =IF($L36="","",$L36*1) | N36: =IF(Investments_Import!F36="","",Investments_Import!F36) | O36: =IF($N36="","",$N36*1) | P36: =IF(Investments_Import!G36="","",Investments_Import!G36) | Q36: =IF(Investments_Import!H36="","",Investments_Import!H36) | R36: =IF($Q36="","",IF($Q36="USD",$P36,$P36*$J36)) | S36: =IF($R36="","",$R36*1) | U36: =IF(Mining_Import!A36="","",Mining_Import!A36) | V36: =IF(U36="","",U36*1) | W36: =V36 | X36: =IFERROR(INT($W36),"") | Y36: =$X36 | Z36: =IF(Mining_Import!B36="","",Mining_Import!B36) | AA36: =IF(Mining_Import!$C36="","",Mining_Import!$C36) | AB36: =IFERROR($AA36*1,"") | AC36: =IF($Y36>Dashboard!$Q$19,$AB36,"") | AD36: =IFERROR($AB36*$BU$19,"") | AE36: =IF(Mining_Import!D36="","",Mining_Import!D36) | AF36: =IF(Mining_Import!E36="","",Mining_Import!E36) | AG36: =IF(Mining_Import!F36="","",Mining_Import!F36) | AH36: =IF(Mining_Import!G36="","",Mining_Import!G36) | AI36: =IF(Mining_Import!H36="","",Mining_Import!H36) | AJ36: =IF(Mining_Import!I36="","",Mining_Import!I36) | AL36: =IFERROR(INDEX($E$2:$E$2500, MATCH(0, INDEX(COUNTIF($AL$1:AL35, $E$2:$E$2500), 0, 0), 0)), "") | AM36: =IF(Calculator!$AL36="","",LEFT(Calculator!$AL36, LEN(Calculator!$AL36)-3)) | AN36: {=IF($AL36="","",MAX(IF($E$2:$E$2500=$AL36,$C$2:$C$2500)))} | AO36: =IF($AN36="","",(TEXT($AN36,"dd-mmm-yyyy")&" "&$AL36&" "&"1")) | AP36: =$AO36 | AQ36: =IF($AL36="","",VLOOKUP($AO36, $H:$K, 3, 0)) | AR36: =IF($AQ36="","",$AQ36*1) | AS36: =IF($AL36="","",SUMIFS($O:$O,$E:$E,$AL36,$I:$I,"BUY")) | AT36: =IF($AL36="","",SUMIFS($O:$O,$E:$E,$AL36,$I:$I,"SELL")) | AU36: =IF($AL36="","",SUMIF($E:$E,$AL36,$S:$S)) | AV36: =IF($AL36="","",SUMIFS($M:$M,$E:$E,$AL36,$I:$I,"BUY")) | AW36: =IF($AL36="","",SUMIFS($M:$M,$E:$E,$AL36,$I:$I,"SELL")) | AX36: =IF($AZ36=1,$AV36-$AW36,"") | AY36: =$AM36 | AZ36: =IF($AY36="","",IFERROR(VLOOKUP($AP36,$BG$2:$BH$13,2, FALSE),"")) | BA36: =IF($AZ36=1, "CURRENT","") | BB36: =IF($AW36=0,"",IFERROR($AS36-$BD36,"")) | BC36: =IFERROR(IF($BA36="CURRENT",(($AT36-$BB36)-$AU36),IF($AW36=0,"",($AT36-$AS36)-$AU36)),"") | BD36: =IF($BA36="CURRENT",($AX36*$AR36),"") | BS36: =IF(Stock_Connector!B36="","",Stock_Connector!B36) -> DOGE | BT36: =IF(Stock_Connector!C36="","",Stock_Connector!C36) -> 0.06 | BU36: =IF(Stock_Connector!C36="","",Stock_Connector!C36) -> 0.06 | BV36: =IF(Stock_Connector!E36="","",Stock_Connector!E36) | BW36: =IF(Stock_Connector!D36="","",Stock_Connector!D36) -> 0.226743 | BY36: =Y36 | BZ36: =AB36 | CA36: =IFERROR(VLOOKUP($BY36,Account_Value!$C$2:$F$2500,4,0),"") | CB36: =IF(BZ36="","",BZ36*CA36) | CC36: =IF($BZ36="","",SUM($BZ$2:$BZ36)) | CD36: =IF($BZ36="","",$BU$19*(SUM($BZ$2:$BZ36)))
A37: =IF($B37="","",$A36+1) | B37: =IF(Investments_Import!A37="","",Investments_Import!A37) | C37: =IF(B37="","",B37*1) | D37: =$C37 | E37: =IF(Investments_Import!B37="","",Investments_Import!B37) | F37: =CONCATENATE(TEXT($D37,"dd-mmm-yyyy")," ",$E37) | G37: =IF($B37="","",COUNTIF($F$2:$F37,$F37)) | H37: =CONCATENATE(TEXT($D37,"dd-mmm-yyyy")," ",$E37," ",$G37) | I37: =IF(Investments_Import!C37="","",Investments_Import!C37) | J37: =IF(Investments_Import!D37="","",Investments_Import!D37) | K37: =IF($B37="","",$J37*1) | L37: =IF(Investments_Import!E37="","",Investments_Import!E37) | M37: =IF($L37="","",$L37*1) | N37: =IF(Investments_Import!F37="","",Investments_Import!F37) | O37: =IF($N37="","",$N37*1) | P37: =IF(Investments_Import!G37="","",Investments_Import!G37) | Q37: =IF(Investments_Import!H37="","",Investments_Import!H37) | R37: =IF($Q37="","",IF($Q37="USD",$P37,$P37*$J37)) | S37: =IF($R37="","",$R37*1) | U37: =IF(Mining_Import!A37="","",Mining_Import!A37) | V37: =IF(U37="","",U37*1) | W37: =V37 | X37: =IFERROR(INT($W37),"") | Y37: =$X37 | Z37: =IF(Mining_Import!B37="","",Mining_Import!B37) | AA37: =IF(Mining_Import!$C37="","",Mining_Import!$C37) | AB37: =IFERROR($AA37*1,"") | AC37: =IF($Y37>Dashboard!$Q$19,$AB37,"") | AD37: =IFERROR($AB37*$BU$19,"") | AE37: =IF(Mining_Import!D37="","",Mining_Import!D37) | AF37: =IF(Mining_Import!E37="","",Mining_Import!E37) | AG37: =IF(Mining_Import!F37="","",Mining_Import!F37) | AH37: =IF(Mining_Import!G37="","",Mining_Import!G37) | AI37: =IF(Mining_Import!H37="","",Mining_Import!H37) | AJ37: =IF(Mining_Import!I37="","",Mining_Import!I37) | AL37: =IFERROR(INDEX($E$2:$E$2500, MATCH(0, INDEX(COUNTIF($AL$1:AL36, $E$2:$E$2500), 0, 0), 0)), "") | AM37: =IF(Calculator!$AL37="","",LEFT(Calculator!$AL37, LEN(Calculator!$AL37)-3)) | AN37: {=IF($AL37="","",MAX(IF($E$2:$E$2500=$AL37,$C$2:$C$2500)))} | AO37: =IF($AN37="","",(TEXT($AN37,"dd-mmm-yyyy")&" "&$AL37&" "&"1")) | AP37: =$AO37 | AQ37: =IF($AL37="","",VLOOKUP($AO37, $H:$K, 3, 0)) | AR37: =IF($AQ37="","",$AQ37*1) | AS37: =IF($AL37="","",SUMIFS($O:$O,$E:$E,$AL37,$I:$I,"BUY")) | AT37: =IF($AL37="","",SUMIFS($O:$O,$E:$E,$AL37,$I:$I,"SELL")) | AU37: =IF($AL37="","",SUMIF($E:$E,$AL37,$S:$S)) | AV37: =IF($AL37="","",SUMIFS($M:$M,$E:$E,$AL37,$I:$I,"BUY")) | AW37: =IF($AL37="","",SUMIFS($M:$M,$E:$E,$AL37,$I:$I,"SELL")) | AX37: =IF($AZ37=1,$AV37-$AW37,"") | AY37: =$AM37 | AZ37: =IF($AY37="","",IFERROR(VLOOKUP($AP37,$BG$2:$BH$13,2, FALSE),"")) | BA37: =IF($AZ37=1, "CURRENT","") | BB37: =IF($AW37=0,"",IFERROR($AS37-$BD37,"")) | BC37: =IFERROR(IF($BA37="CURRENT",(($AT37-$BB37)-$AU37),IF($AW37=0,"",($AT37-$AS37)-$AU37)),"") | BD37: =IF($BA37="CURRENT",($AX37*$AR37),"") | BS37: =IF(Stock_Connector!B37="","",Stock_Connector!B37) -> ENJ | BT37: =IF(Stock_Connector!C37="","",Stock_Connector!C37) -> 0.395395 | BU37: =IF(Stock_Connector!C37="","",Stock_Connector!C37) -> 0.395395 | BV37: =IF(Stock_Connector!E37="","",Stock_Connector!E37) | BW37: =IF(Stock_Connector!D37="","",Stock_Connector!D37) -> 0.056225344 | BY37: =Y37 | BZ37: =AB37 | CA37: =IFERROR(VLOOKUP($BY37,Account_Value!$C$2:$F$2500,4,0),"") | CB37: =IF(BZ37="","",BZ37*CA37) | CC37: =IF($BZ37="","",SUM($BZ$2:$BZ37)) | CD37: =IF($BZ37="","",$BU$19*(SUM($BZ$2:$BZ37)))
A38: =IF($B38="","",$A37+1) | B38: =IF(Investments_Import!A38="","",Investments_Import!A38) | C38: =IF(B38="","",B38*1) | D38: =$C38 | E38: =IF(Investments_Import!B38="","",Investments_Import!B38) | F38: =CONCATENATE(TEXT($D38,"dd-mmm-yyyy")," ",$E38) | G38: =IF($B38="","",COUNTIF($F$2:$F38,$F38)) | H38: =CONCATENATE(TEXT($D38,"dd-mmm-yyyy")," ",$E38," ",$G38) | I38: =IF(Investments_Import!C38="","",Investments_Import!C38) | J38: =IF(Investments_Import!D38="","",Investments_Import!D38) | K38: =IF($B38="","",$J38*1) | L38: =IF(Investments_Import!E38="","",Investments_Import!E38) | M38: =IF($L38="","",$L38*1) | N38: =IF(Investments_Import!F38="","",Investments_Import!F38) | O38: =IF($N38="","",$N38*1) | P38: =IF(Investments_Import!G38="","",Investments_Import!G38) | Q38: =IF(Investments_Import!H38="","",Investments_Import!H38) | R38: =IF($Q38="","",IF($Q38="USD",$P38,$P38*$J38)) | S38: =IF($R38="","",$R38*1) | U38: =IF(Mining_Import!A38="","",Mining_Import!A38) | V38: =IF(U38="","",U38*1) | W38: =V38 | X38: =IFERROR(INT($W38),"") | Y38: =$X38 | Z38: =IF(Mining_Import!B38="","",Mining_Import!B38) | AA38: =IF(Mining_Import!$C38="","",Mining_Import!$C38) | AB38: =IFERROR($AA38*1,"") | AC38: =IF($Y38>Dashboard!$Q$19,$AB38,"") | AD38: =IFERROR($AB38*$BU$19,"") | AE38: =IF(Mining_Import!D38="","",Mining_Import!D38) | AF38: =IF(Mining_Import!E38="","",Mining_Import!E38) | AG38: =IF(Mining_Import!F38="","",Mining_Import!F38) | AH38: =IF(Mining_Import!G38="","",Mining_Import!G38) | AI38: =IF(Mining_Import!H38="","",Mining_Import!H38) | AJ38: =IF(Mining_Import!I38="","",Mining_Import!I38) | AL38: =IFERROR(INDEX($E$2:$E$2500, MATCH(0, INDEX(COUNTIF($AL$1:AL37, $E$2:$E$2500), 0, 0), 0)), "") | AM38: =IF(Calculator!$AL38="","",LEFT(Calculator!$AL38, LEN(Calculator!$AL38)-3)) | AN38: {=IF($AL38="","",MAX(IF($E$2:$E$2500=$AL38,$C$2:$C$2500)))} | AO38: =IF($AN38="","",(TEXT($AN38,"dd-mmm-yyyy")&" "&$AL38&" "&"1")) | AP38: =$AO38 | AQ38: =IF($AL38="","",VLOOKUP($AO38, $H:$K, 3, 0)) | AR38: =IF($AQ38="","",$AQ38*1) | AS38: =IF($AL38="","",SUMIFS($O:$O,$E:$E,$AL38,$I:$I,"BUY")) | AT38: =IF($AL38="","",SUMIFS($O:$O,$E:$E,$AL38,$I:$I,"SELL")) | AU38: =IF($AL38="","",SUMIF($E:$E,$AL38,$S:$S)) | AV38: =IF($AL38="","",SUMIFS($M:$M,$E:$E,$AL38,$I:$I,"BUY")) | AW38: =IF($AL38="","",SUMIFS($M:$M,$E:$E,$AL38,$I:$I,"SELL")) | AX38: =IF($AZ38=1,$AV38-$AW38,"") | AY38: =$AM38 | AZ38: =IF($AY38="","",IFERROR(VLOOKUP($AP38,$BG$2:$BH$13,2, FALSE),"")) | BA38: =IF($AZ38=1, "CURRENT","") | BB38: =IF($AW38=0,"",IFERROR($AS38-$BD38,"")) | BC38: =IFERROR(IF($BA38="CURRENT",(($AT38-$BB38)-$AU38),IF($AW38=0,"",($AT38-$AS38)-$AU38)),"") | BD38: =IF($BA38="CURRENT",($AX38*$AR38),"") | BS38: =IF(Stock_Connector!B38="","",Stock_Connector!B38) -> EOS | BT38: =IF(Stock_Connector!C38="","",Stock_Connector!C38) -> 3.289 | BU38: =IF(Stock_Connector!C38="","",Stock_Connector!C38) -> 3.289 | BV38: =IF(Stock_Connector!E38="","",Stock_Connector!E38) | BW38: =IF(Stock_Connector!D38="","",Stock_Connector!D38) -> 0.0278125 | BY38: =Y38 | BZ38: =AB38 | CA38: =IFERROR(VLOOKUP($BY38,Account_Value!$C$2:$F$2500,4,0),"") | CB38: =IF(BZ38="","",BZ38*CA38) | CC38: =IF($BZ38="","",SUM($BZ$2:$BZ38)) | CD38: =IF($BZ38="","",$BU$19*(SUM($BZ$2:$BZ38)))
A39: =IF($B39="","",$A38+1) | B39: =IF(Investments_Import!A39="","",Investments_Import!A39) | C39: =IF(B39="","",B39*1) | D39: =$C39 | E39: =IF(Investments_Import!B39="","",Investments_Import!B39) | F39: =CONCATENATE(TEXT($D39,"dd-mmm-yyyy")," ",$E39) | G39: =IF($B39="","",COUNTIF($F$2:$F39,$F39)) | H39: =CONCATENATE(TEXT($D39,"dd-mmm-yyyy")," ",$E39," ",$G39) | I39: =IF(Investments_Import!C39="","",Investments_Import!C39) | J39: =IF(Investments_Import!D39="","",Investments_Import!D39) | K39: =IF($B39="","",$J39*1) | L39: =IF(Investments_Import!E39="","",Investments_Import!E39) | M39: =IF($L39="","",$L39*1) | N39: =IF(Investments_Import!F39="","",Investments_Import!F39) | O39: =IF($N39="","",$N39*1) | P39: =IF(Investments_Import!G39="","",Investments_Import!G39) | Q39: =IF(Investments_Import!H39="","",Investments_Import!H39) | R39: =IF($Q39="","",IF($Q39="USD",$P39,$P39*$J39)) | S39: =IF($R39="","",$R39*1) | U39: =IF(Mining_Import!A39="","",Mining_Import!A39) | V39: =IF(U39="","",U39*1) | W39: =V39 | X39: =IFERROR(INT($W39),"") | Y39: =$X39 | Z39: =IF(Mining_Import!B39="","",Mining_Import!B39) | AA39: =IF(Mining_Import!$C39="","",Mining_Import!$C39) | AB39: =IFERROR($AA39*1,"") | AC39: =IF($Y39>Dashboard!$Q$19,$AB39,"") | AD39: =IFERROR($AB39*$BU$19,"") | AE39: =IF(Mining_Import!D39="","",Mining_Import!D39) | AF39: =IF(Mining_Import!E39="","",Mining_Import!E39) | AG39: =IF(Mining_Import!F39="","",Mining_Import!F39) | AH39: =IF(Mining_Import!G39="","",Mining_Import!G39) | AI39: =IF(Mining_Import!H39="","",Mining_Import!H39) | AJ39: =IF(Mining_Import!I39="","",Mining_Import!I39) | AL39: =IFERROR(INDEX($E$2:$E$2500, MATCH(0, INDEX(COUNTIF($AL$1:AL38, $E$2:$E$2500), 0, 0), 0)), "") | AM39: =IF(Calculator!$AL39="","",LEFT(Calculator!$AL39, LEN(Calculator!$AL39)-3)) | AN39: {=IF($AL39="","",MAX(IF($E$2:$E$2500=$AL39,$C$2:$C$2500)))} | AO39: =IF($AN39="","",(TEXT($AN39,"dd-mmm-yyyy")&" "&$AL39&" "&"1")) | AP39: =$AO39 | AQ39: =IF($AL39="","",VLOOKUP($AO39, $H:$K, 3, 0)) | AR39: =IF($AQ39="","",$AQ39*1) | AS39: =IF($AL39="","",SUMIFS($O:$O,$E:$E,$AL39,$I:$I,"BUY")) | AT39: =IF($AL39="","",SUMIFS($O:$O,$E:$E,$AL39,$I:$I,"SELL")) | AU39: =IF($AL39="","",SUMIF($E:$E,$AL39,$S:$S)) | AV39: =IF($AL39="","",SUMIFS($M:$M,$E:$E,$AL39,$I:$I,"BUY")) | AW39: =IF($AL39="","",SUMIFS($M:$M,$E:$E,$AL39,$I:$I,"SELL")) | AX39: =IF($AZ39=1,$AV39-$AW39,"") | AY39: =$AM39 | AZ39: =IF($AY39="","",IFERROR(VLOOKUP($AP39,$BG$2:$BH$13,2, FALSE),"")) | BA39: =IF($AZ39=1, "CURRENT","") | BB39: =IF($AW39=0,"",IFERROR($AS39-$BD39,"")) | BC39: =IFERROR(IF($BA39="CURRENT",(($AT39-$BB39)-$AU39),IF($AW39=0,"",($AT39-$AS39)-$AU39)),"") | BD39: =IF($BA39="CURRENT",($AX39*$AR39),"") | BS39: =IF(Stock_Connector!B39="","",Stock_Connector!B39) -> HBAR | BT39: =IF(Stock_Connector!C39="","",Stock_Connector!C39) -> 0.09907898 | BU39: =IF(Stock_Connector!C39="","",Stock_Connector!C39) -> 0.09907898 | BV39: =IF(Stock_Connector!E39="","",Stock_Connector!E39) | BW39: =IF(Stock_Connector!D39="","",Stock_Connector!D39) -> -0.021946414 | BY39: =Y39 | BZ39: =AB39 | CA39: =IFERROR(VLOOKUP($BY39,Account_Value!$C$2:$F$2500,4,0),"") | CB39: =IF(BZ39="","",BZ39*CA39) | CC39: =IF($BZ39="","",SUM($BZ$2:$BZ39)) | CD39: =IF($BZ39="","",$BU$19*(SUM($BZ$2:$BZ39)))
... A50: =IF($B50="","",$A49+1) | B50: =IF(Investments_Import!A50="","",Investments_Import!A50) | C50: =IF(B50="","",B50*1) | D50: =$C50 | E50: =IF(Investments_Import!B50="","",Investments_Import!B50) | F50: =CONCATENATE(TEXT($D50,"dd-mmm-yyyy")," ",$E50) | G50: =IF($B50="","",COUNTIF($F$2:$F50,$F50)) | H50: =CONCATENATE(TEXT($D50,"dd-mmm-yyyy")," ",$E50," ",$G50) | I50: =IF(Investments_Import!C50="","",Investments_Import!C50) | J50: =IF(Investments_Import!D50="","",Investments_Import!D50) | K50: =IF($B50="","",$J50*1) | L50: =IF(Investments_Import!E50="","",Investments_Import!E50) | M50: =IF($L50="","",$L50*1) | N50: =IF(Investments_Import!F50="","",Investments_Import!F50) | O50: =IF($N50="","",$N50*1) | P50: =IF(Investments_Import!G50="","",Investments_Import!G50) | Q50: =IF(Investments_Import!H50="","",Investments_Import!H50) | R50: =IF($Q50="","",IF($Q50="USD",$P50,$P50*$J50)) | S50: =IF($R50="","",$R50*1) | U50: =IF(Mining_Import!A50="","",Mining_Import!A50) | V50: =IF(U50="","",U50*1) | W50: =V50 | X50: =IFERROR(INT($W50),"") | Y50: =$X50 | Z50: =IF(Mining_Import!B50="","",Mining_Import!B50) | AA50: =IF(Mining_Import!$C50="","",Mining_Import!$C50) | AB50: =IFERROR($AA50*1,"") | AC50: =IF($Y50>Dashboard!$Q$19,$AB50,"") | AD50: =IFERROR($AB50*$BU$19,"") | AE50: =IF(Mining_Import!D50="","",Mining_Import!D50) | AF50: =IF(Mining_Import!E50="","",Mining_Import!E50) | AG50: =IF(Mining_Import!F50="","",Mining_Import!F50) | AH50: =IF(Mining_Import!G50="","",Mining_Import!G50) | AI50: =IF(Mining_Import!H50="","",Mining_Import!H50) | AJ50: =IF(Mining_Import!I50="","",Mining_Import!I50) | AL50: =IFERROR(INDEX($E$2:$E$2500, MATCH(0, INDEX(COUNTIF($AL$1:AL49, $E$2:$E$2500), 0, 0), 0)), "") | AM50: =IF(Calculator!$AL50="","",LEFT(Calculator!$AL50, LEN(Calculator!$AL50)-3)) | AN50: {=IF($AL50="","",MAX(IF($E$2:$E$2500=$AL50,$C$2:$C$2500)))} | AO50: =IF($AN50="","",(TEXT($AN50,"dd-mmm-yyyy")&" "&$AL50&" "&"1")) | AP50: =$AO50 | AQ50: =IF($AL50="","",VLOOKUP($AO50, $H:$K, 3, 0)) | AR50: =IF($AQ50="","",$AQ50*1) | AS50: =IF($AL50="","",SUMIFS($O:$O,$E:$E,$AL50,$I:$I,"BUY")) | AT50: =IF($AL50="","",SUMIFS($O:$O,$E:$E,$AL50,$I:$I,"SELL")) | AU50: =IF($AL50="","",SUMIF($E:$E,$AL50,$S:$S)) | AV50: =IF($AL50="","",SUMIFS($M:$M,$E:$E,$AL50,$I:$I,"BUY")) | AW50: =IF($AL50="","",SUMIFS($M:$M,$E:$E,$AL50,$I:$I,"SELL")) | AX50: =IF($AZ50=1,$AV50-$AW50,"") | AY50: =$AM50 | AZ50: =IF($AY50="","",IFERROR(VLOOKUP($AP50,$BG$2:$BH$13,2, FALSE),"")) | BA50: =IF($AZ50=1, "CURRENT","") | BB50: =IF($AW50=0,"",IFERROR($AS50-$BD50,"")) | BC50: =IFERROR(IF($BA50="CURRENT",(($AT50-$BB50)-$AU50),IF($AW50=0,"",($AT50-$AS50)-$AU50)),"") | BD50: =IF($BA50="CURRENT",($AX50*$AR50),"") | BS50: =IF(Stock_Connector!B50="","",Stock_Connector!B50) | BT50: =IF(Stock_Connector!C50="","",Stock_Connector!C50) | BU50: =IF(Stock_Connector!C50="","",Stock_Connector!C50) | BV50: =IF(Stock_Connector!E50="","",Stock_Connector!E50) | BW50: =IF(Stock_Connector!D50="","",Stock_Connector!D50) | BY50: =Y50 | BZ50: =AB50 | CA50: =IFERROR(VLOOKUP($BY50,Account_Value!$C$2:$F$2500,4,0),"") | CB50: =IF(BZ50="","",BZ50*CA50) | CC50: =IF($BZ50="","",SUM($BZ$2:$BZ50)) | CD50: =IF($BZ50="","",$BU$19*(SUM($BZ$2:$BZ50)))
A51: =IF($B51="","",$A50+1) | B51: =IF(Investments_Import!A51="","",Investments_Import!A51) | C51: =IF(B51="","",B51*1) | D51: =$C51 | E51: =IF(Investments_Import!B51="","",Investments_Import!B51) | F51: =CONCATENATE(TEXT($D51,"dd-mmm-yyyy")," ",$E51) | G51: =IF($B51="","",COUNTIF($F$2:$F51,$F51)) | H51: =CONCATENATE(TEXT($D51,"dd-mmm-yyyy")," ",$E51," ",$G51) | I51: =IF(Investments_Import!C51="","",Investments_Import!C51) | J51: =IF(Investments_Import!D51="","",Investments_Import!D51) | K51: =IF($B51="","",$J51*1) | L51: =IF(Investments_Import!E51="","",Investments_Import!E51) | M51: =IF($L51="","",$L51*1) | N51: =IF(Investments_Import!F51="","",Investments_Import!F51) | O51: =IF($N51="","",$N51*1) | P51: =IF(Investments_Import!G51="","",Investments_Import!G51) | Q51: =IF(Investments_Import!H51="","",Investments_Import!H51) | R51: =IF($Q51="","",IF($Q51="USD",$P51,$P51*$J51)) | S51: =IF($R51="","",$R51*1) | U51: =IF(Mining_Import!A51="","",Mining_Import!A51) | V51: =IF(U51="","",U51*1) | W51: =V51 | X51: =IFERROR(INT($W51),"") | Y51: =$X51 | Z51: =IF(Mining_Import!B51="","",Mining_Import!B51) | AA51: =IF(Mining_Import!$C51="","",Mining_Import!$C51) | AB51: =IFERROR($AA51*1,"") | AC51: =IF($Y51>Dashboard!$Q$19,$AB51,"") | AD51: =IFERROR($AB51*$BU$19,"") | AE51: =IF(Mining_Import!D51="","",Mining_Import!D51) | AF51: =IF(Mining_Import!E51="","",Mining_Import!E51) | AG51: =IF(Mining_Import!F51="","",Mining_Import!F51) | AH51: =IF(Mining_Import!G51="","",Mining_Import!G51) | AI51: =IF(Mining_Import!H51="","",Mining_Import!H51) | AJ51: =IF(Mining_Import!I51="","",Mining_Import!I51) | BS51: =IF(Stock_Connector!B51="","",Stock_Connector!B51) | BT51: =IF(Stock_Connector!C51="","",Stock_Connector!C51) | BU51: =IF(Stock_Connector!C51="","",Stock_Connector!C51) | BV51: =IF(Stock_Connector!E51="","",Stock_Connector!E51) | BW51: =IF(Stock_Connector!D51="","",Stock_Connector!D51) | BY51: =Y51 | BZ51: =AB51 | CA51: =IFERROR(VLOOKUP($BY51,Account_Value!$C$2:$F$2500,4,0),"") | CB51: =IF(BZ51="","",BZ51*CA51) | CC51: =IF($BZ51="","",SUM($BZ$2:$BZ51)) | CD51: =IF($BZ51="","",$BU$19*(SUM($BZ$2:$BZ51)))
A52: =IF($B52="","",$A51+1) | B52: =IF(Investments_Import!A52="","",Investments_Import!A52) | C52: =IF(B52="","",B52*1) | D52: =$C52 | E52: =IF(Investments_Import!B52="","",Investments_Import!B52) | F52: =CONCATENATE(TEXT($D52,"dd-mmm-yyyy")," ",$E52) | G52: =IF($B52="","",COUNTIF($F$2:$F52,$F52)) | H52: =CONCATENATE(TEXT($D52,"dd-mmm-yyyy")," ",$E52," ",$G52) | I52: =IF(Investments_Import!C52="","",Investments_Import!C52) | J52: =IF(Investments_Import!D52="","",Investments_Import!D52) | K52: =IF($B52="","",$J52*1) | L52: =IF(Investments_Import!E52="","",Investments_Import!E52) | M52: =IF($L52="","",$L52*1) | N52: =IF(Investments_Import!F52="","",Investments_Import!F52) | O52: =IF($N52="","",$N52*1) | P52: =IF(Investments_Import!G52="","",Investments_Import!G52) | Q52: =IF(Investments_Import!H52="","",Investments_Import!H52) | R52: =IF($Q52="","",IF($Q52="USD",$P52,$P52*$J52)) | S52: =IF($R52="","",$R52*1) | U52: =IF(Mining_Import!A52="","",Mining_Import!A52) | V52: =IF(U52="","",U52*1) | W52: =V52 | X52: =IFERROR(INT($W52),"") | Y52: =$X52 | Z52: =IF(Mining_Import!B52="","",Mining_Import!B52) | AA52: =IF(Mining_Import!$C52="","",Mining_Import!$C52) | AB52: =IFERROR($AA52*1,"") | AC52: =IF($Y52>Dashboard!$Q$19,$AB52,"") | AD52: =IFERROR($AB52*$BU$19,"") | AE52: =IF(Mining_Import!D52="","",Mining_Import!D52) | AF52: =IF(Mining_Import!E52="","",Mining_Import!E52) | AG52: =IF(Mining_Import!F52="","",Mining_Import!F52) | AH52: =IF(Mining_Import!G52="","",Mining_Import!G52) | AI52: =IF(Mining_Import!H52="","",Mining_Import!H52) | AJ52: =IF(Mining_Import!I52="","",Mining_Import!I52) | BS52: =IF(Stock_Connector!B52="","",Stock_Connector!B52) | BT52: =IF(Stock_Connector!C52="","",Stock_Connector!C52) | BU52: =IF(Stock_Connector!C52="","",Stock_Connector!C52) | BV52: =IF(Stock_Connector!E52="","",Stock_Connector!E52) | BW52: =IF(Stock_Connector!D52="","",Stock_Connector!D52) | BY52: =Y52 | BZ52: =AB52 | CA52: =IFERROR(VLOOKUP($BY52,Account_Value!$C$2:$F$2500,4,0),"") | CB52: =IF(BZ52="","",BZ52*CA52) | CC52: =IF($BZ52="","",SUM($BZ$2:$BZ52)) | CD52: =IF($BZ52="","",$BU$19*(SUM($BZ$2:$BZ52)))
A53: =IF($B53="","",$A52+1) | B53: =IF(Investments_Import!A53="","",Investments_Import!A53) | C53: =IF(B53="","",B53*1) | D53: =$C53 | E53: =IF(Investments_Import!B53="","",Investments_Import!B53) | F53: =CONCATENATE(TEXT($D53,"dd-mmm-yyyy")," ",$E53) | G53: =IF($B53="","",COUNTIF($F$2:$F53,$F53)) | H53: =CONCATENATE(TEXT($D53,"dd-mmm-yyyy")," ",$E53," ",$G53) | I53: =IF(Investments_Import!C53="","",Investments_Import!C53) | J53: =IF(Investments_Import!D53="","",Investments_Import!D53) | K53: =IF($B53="","",$J53*1) | L53: =IF(Investments_Import!E53="","",Investments_Import!E53) | M53: =IF($L53="","",$L53*1) | N53: =IF(Investments_Import!F53="","",Investments_Import!F53) | O53: =IF($N53="","",$N53*1) | P53: =IF(Investments_Import!G53="","",Investments_Import!G53) | Q53: =IF(Investments_Import!H53="","",Investments_Import!H53) | R53: =IF($Q53="","",IF($Q53="USD",$P53,$P53*$J53)) | S53: =IF($R53="","",$R53*1) | U53: =IF(Mining_Import!A53="","",Mining_Import!A53) | V53: =IF(U53="","",U53*1) | W53: =V53 | X53: =IFERROR(INT($W53),"") | Y53: =$X53 | Z53: =IF(Mining_Import!B53="","",Mining_Import!B53) | AA53: =IF(Mining_Import!$C53="","",Mining_Import!$C53) | AB53: =IFERROR($AA53*1,"") | AC53: =IF($Y53>Dashboard!$Q$19,$AB53,"") | AD53: =IFERROR($AB53*$BU$19,"") | AE53: =IF(Mining_Import!D53="","",Mining_Import!D53) | AF53: =IF(Mining_Import!E53="","",Mining_Import!E53) | AG53: =IF(Mining_Import!F53="","",Mining_Import!F53) | AH53: =IF(Mining_Import!G53="","",Mining_Import!G53) | AI53: =IF(Mining_Import!H53="","",Mining_Import!H53) | AJ53: =IF(Mining_Import!I53="","",Mining_Import!I53) | BS53: =IF(Stock_Connector!B53="","",Stock_Connector!B53) | BT53: =IF(Stock_Connector!C53="","",Stock_Connector!C53) | BU53: =IF(Stock_Connector!C53="","",Stock_Connector!C53) | BV53: =IF(Stock_Connector!E53="","",Stock_Connector!E53) | BW53: =IF(Stock_Connector!D53="","",Stock_Connector!D53) | BY53: =Y53 | BZ53: =AB53 | CA53: =IFERROR(VLOOKUP($BY53,Account_Value!$C$2:$F$2500,4,0),"") | CB53: =IF(BZ53="","",BZ53*CA53) | CC53: =IF($BZ53="","",SUM($BZ$2:$BZ53)) | CD53: =IF($BZ53="","",$BU$19*(SUM($BZ$2:$BZ53)))
A54: =IF($B54="","",$A53+1) | B54: =IF(Investments_Import!A54="","",Investments_Import!A54) | C54: =IF(B54="","",B54*1) | D54: =$C54 | E54: =IF(Investments_Import!B54="","",Investments_Import!B54) | F54: =CONCATENATE(TEXT($D54,"dd-mmm-yyyy")," ",$E54) | G54: =IF($B54="","",COUNTIF($F$2:$F54,$F54)) | H54: =CONCATENATE(TEXT($D54,"dd-mmm-yyyy")," ",$E54," ",$G54) | I54: =IF(Investments_Import!C54="","",Investments_Import!C54) | J54: =IF(Investments_Import!D54="","",Investments_Import!D54) | K54: =IF($B54="","",$J54*1) | L54: =IF(Investments_Import!E54="","",Investments_Import!E54) | M54: =IF($L54="","",$L54*1) | N54: =IF(Investments_Import!F54="","",Investments_Import!F54) | O54: =IF($N54="","",$N54*1) | P54: =IF(Investments_Import!G54="","",Investments_Import!G54) | Q54: =IF(Investments_Import!H54="","",Investments_Import!H54) | R54: =IF($Q54="","",IF($Q54="USD",$P54,$P54*$J54)) | S54: =IF($R54="","",$R54*1) | U54: =IF(Mining_Import!A54="","",Mining_Import!A54) | V54: =IF(U54="","",U54*1) | W54: =V54 | X54: =IFERROR(INT($W54),"") | Y54: =$X54 | Z54: =IF(Mining_Import!B54="","",Mining_Import!B54) | AA54: =IF(Mining_Import!$C54="","",Mining_Import!$C54) | AB54: =IFERROR($AA54*1,"") | AC54: =IF($Y54>Dashboard!$Q$19,$AB54,"") | AD54: =IFERROR($AB54*$BU$19,"") | AE54: =IF(Mining_Import!D54="","",Mining_Import!D54) | AF54: =IF(Mining_Import!E54="","",Mining_Import!E54) | AG54: =IF(Mining_Import!F54="","",Mining_Import!F54) | AH54: =IF(Mining_Import!G54="","",Mining_Import!G54) | AI54: =IF(Mining_Import!H54="","",Mining_Import!H54) | AJ54: =IF(Mining_Import!I54="","",Mining_Import!I54) | BS54: =IF(Stock_Connector!B54="","",Stock_Connector!B54) | BT54: =IF(Stock_Connector!C54="","",Stock_Connector!C54) | BU54: =IF(Stock_Connector!C54="","",Stock_Connector!C54) | BV54: =IF(Stock_Connector!E54="","",Stock_Connector!E54) | BW54: =IF(Stock_Connector!D54="","",Stock_Connector!D54) | BY54: =Y54 | BZ54: =AB54 | CA54: =IFERROR(VLOOKUP($BY54,Account_Value!$C$2:$F$2500,4,0),"") | CB54: =IF(BZ54="","",BZ54*CA54) | CC54: =IF($BZ54="","",SUM($BZ$2:$BZ54)) | CD54: =IF($BZ54="","",$BU$19*(SUM($BZ$2:$BZ54)))
A55: =IF($B55="","",$A54+1) | B55: =IF(Investments_Import!A55="","",Investments_Import!A55) | C55: =IF(B55="","",B55*1) | D55: =$C55 | E55: =IF(Investments_Import!B55="","",Investments_Import!B55) | F55: =CONCATENATE(TEXT($D55,"dd-mmm-yyyy")," ",$E55) | G55: =IF($B55="","",COUNTIF($F$2:$F55,$F55)) | H55: =CONCATENATE(TEXT($D55,"dd-mmm-yyyy")," ",$E55," ",$G55) | I55: =IF(Investments_Import!C55="","",Investments_Import!C55) | J55: =IF(Investments_Import!D55="","",Investments_Import!D55) | K55: =IF($B55="","",$J55*1) | L55: =IF(Investments_Import!E55="","",Investments_Import!E55) | M55: =IF($L55="","",$L55*1) | N55: =IF(Investments_Import!F55="","",Investments_Import!F55) | O55: =IF($N55="","",$N55*1) | P55: =IF(Investments_Import!G55="","",Investments_Import!G55) | Q55: =IF(Investments_Import!H55="","",Investments_Import!H55) | R55: =IF($Q55="","",IF($Q55="USD",$P55,$P55*$J55)) | S55: =IF($R55="","",$R55*1) | U55: =IF(Mining_Import!A55="","",Mining_Import!A55) | V55: =IF(U55="","",U55*1) | W55: =V55 | X55: =IFERROR(INT($W55),"") | Y55: =$X55 | Z55: =IF(Mining_Import!B55="","",Mining_Import!B55) | AA55: =IF(Mining_Import!$C55="","",Mining_Import!$C55) | AB55: =IFERROR($AA55*1,"") | AC55: =IF($Y55>Dashboard!$Q$19,$AB55,"") | AD55: =IFERROR($AB55*$BU$19,"") | AE55: =IF(Mining_Import!D55="","",Mining_Import!D55) | AF55: =IF(Mining_Import!E55="","",Mining_Import!E55) | AG55: =IF(Mining_Import!F55="","",Mining_Import!F55) | AH55: =IF(Mining_Import!G55="","",Mining_Import!G55) | AI55: =IF(Mining_Import!H55="","",Mining_Import!H55) | AJ55: =IF(Mining_Import!I55="","",Mining_Import!I55) | BS55: =IF(Stock_Connector!B55="","",Stock_Connector!B55) | BT55: =IF(Stock_Connector!C55="","",Stock_Connector!C55) | BU55: =IF(Stock_Connector!C55="","",Stock_Connector!C55) | BV55: =IF(Stock_Connector!E55="","",Stock_Connector!E55) | BW55: =IF(Stock_Connector!D55="","",Stock_Connector!D55) | BY55: =Y55 | BZ55: =AB55 | CA55: =IFERROR(VLOOKUP($BY55,Account_Value!$C$2:$F$2500,4,0),"") | CB55: =IF(BZ55="","",BZ55*CA55) | CC55: =IF($BZ55="","",SUM($BZ$2:$BZ55)) | CD55: =IF($BZ55="","",$BU$19*(SUM($BZ$2:$BZ55)))
A56: =IF($B56="","",$A55+1) | B56: =IF(Investments_Import!A56="","",Investments_Import!A56) | C56: =IF(B56="","",B56*1) | D56: =$C56 | E56: =IF(Investments_Import!B56="","",Investments_Import!B56) | F56: =CONCATENATE(TEXT($D56,"dd-mmm-yyyy")," ",$E56) | G56: =IF($B56="","",COUNTIF($F$2:$F56,$F56)) | H56: =CONCATENATE(TEXT($D56,"dd-mmm-yyyy")," ",$E56," ",$G56) | I56: =IF(Investments_Import!C56="","",Investments_Import!C56) | J56: =IF(Investments_Import!D56="","",Investments_Import!D56) | K56: =IF($B56="","",$J56*1) | L56: =IF(Investments_Import!E56="","",Investments_Import!E56) | M56: =IF($L56="","",$L56*1) | N56: =IF(Investments_Import!F56="","",Investments_Import!F56) | O56: =IF($N56="","",$N56*1) | P56: =IF(Investments_Import!G56="","",Investments_Import!G56) | Q56: =IF(Investments_Import!H56="","",Investments_Import!H56) | R56: =IF($Q56="","",IF($Q56="USD",$P56,$P56*$J56)) | S56: =IF($R56="","",$R56*1) | U56: =IF(Mining_Import!A56="","",Mining_Import!A56) | V56: =IF(U56="","",U56*1) | W56: =V56 | X56: =IFERROR(INT($W56),"") | Y56: =$X56 | Z56: =IF(Mining_Import!B56="","",Mining_Import!B56) | AA56: =IF(Mining_Import!$C56="","",Mining_Import!$C56) | AB56: =IFERROR($AA56*1,"") | AC56: =IF($Y56>Dashboard!$Q$19,$AB56,"") | AD56: =IFERROR($AB56*$BU$19,"") | AE56: =IF(Mining_Import!D56="","",Mining_Import!D56) | AF56: =IF(Mining_Import!E56="","",Mining_Import!E56) | AG56: =IF(Mining_Import!F56="","",Mining_Import!F56) | AH56: =IF(Mining_Import!G56="","",Mining_Import!G56) | AI56: =IF(Mining_Import!H56="","",Mining_Import!H56) | AJ56: =IF(Mining_Import!I56="","",Mining_Import!I56) | BS56: =IF(Stock_Connector!B56="","",Stock_Connector!B56) | BT56: =IF(Stock_Connector!C56="","",Stock_Connector!C56) | BU56: =IF(Stock_Connector!C56="","",Stock_Connector!C56) | BV56: =IF(Stock_Connector!E56="","",Stock_Connector!E56) | BW56: =IF(Stock_Connector!D56="","",Stock_Connector!D56) | BY56: =Y56 | BZ56: =AB56 | CA56: =IFERROR(VLOOKUP($BY56,Account_Value!$C$2:$F$2500,4,0),"") | CB56: =IF(BZ56="","",BZ56*CA56) | CC56: =IF($BZ56="","",SUM($BZ$2:$BZ56)) | CD56: =IF($BZ56="","",$BU$19*(SUM($BZ$2:$BZ56)))
A57: =IF($B57="","",$A56+1) | B57: =IF(Investments_Import!A57="","",Investments_Import!A57) | C57: =IF(B57="","",B57*1) | D57: =$C57 | E57: =IF(Investments_Import!B57="","",Investments_Import!B57) | F57: =CONCATENATE(TEXT($D57,"dd-mmm-yyyy")," ",$E57) | G57: =IF($B57="","",COUNTIF($F$2:$F57,$F57)) | H57: =CONCATENATE(TEXT($D57,"dd-mmm-yyyy")," ",$E57," ",$G57) | I57: =IF(Investments_Import!C57="","",Investments_Import!C57) | J57: =IF(Investments_Import!D57="","",Investments_Import!D57) | K57: =IF($B57="","",$J57*1) | L57: =IF(Investments_Import!E57="","",Investments_Import!E57) | M57: =IF($L57="","",$L57*1) | N57: =IF(Investments_Import!F57="","",Investments_Import!F57) | O57: =IF($N57="","",$N57*1) | P57: =IF(Investments_Import!G57="","",Investments_Import!G57) | Q57: =IF(Investments_Import!H57="","",Investments_Import!H57) | R57: =IF($Q57="","",IF($Q57="USD",$P57,$P57*$J57)) | S57: =IF($R57="","",$R57*1) | U57: =IF(Mining_Import!A57="","",Mining_Import!A57) | V57: =IF(U57="","",U57*1) | W57: =V57 | X57: =IFERROR(INT($W57),"") | Y57: =$X57 | Z57: =IF(Mining_Import!B57="","",Mining_Import!B57) | AA57: =IF(Mining_Import!$C57="","",Mining_Import!$C57) | AB57: =IFERROR($AA57*1,"") | AC57: =IF($Y57>Dashboard!$Q$19,$AB57,"") | AD57: =IFERROR($AB57*$BU$19,"") | AE57: =IF(Mining_Import!D57="","",Mining_Import!D57) | AF57: =IF(Mining_Import!E57="","",Mining_Import!E57) | AG57: =IF(Mining_Import!F57="","",Mining_Import!F57) | AH57: =IF(Mining_Import!G57="","",Mining_Import!G57) | AI57: =IF(Mining_Import!H57="","",Mining_Import!H57) | AJ57: =IF(Mining_Import!I57="","",Mining_Import!I57) | BS57: =IF(Stock_Connector!B57="","",Stock_Connector!B57) | BT57: =IF(Stock_Connector!C57="","",Stock_Connector!C57) | BU57: =IF(Stock_Connector!C57="","",Stock_Connector!C57) | BV57: =IF(Stock_Connector!E57="","",Stock_Connector!E57) | BW57: =IF(Stock_Connector!D57="","",Stock_Connector!D57) | BY57: =Y57 | BZ57: =AB57 | CA57: =IFERROR(VLOOKUP($BY57,Account_Value!$C$2:$F$2500,4,0),"") | CB57: =IF(BZ57="","",BZ57*CA57) | CC57: =IF($BZ57="","",SUM($BZ$2:$BZ57)) | CD57: =IF($BZ57="","",$BU$19*(SUM($BZ$2:$BZ57)))
A58: =IF($B58="","",$A57+1) | B58: =IF(Investments_Import!A58="","",Investments_Import!A58) | C58: =IF(B58="","",B58*1) | D58: =$C58 | E58: =IF(Investments_Import!B58="","",Investments_Import!B58) | F58: =CONCATENATE(TEXT($D58,"dd-mmm-yyyy")," ",$E58) | G58: =IF($B58="","",COUNTIF($F$2:$F58,$F58)) | H58: =CONCATENATE(TEXT($D58,"dd-mmm-yyyy")," ",$E58," ",$G58) | I58: =IF(Investments_Import!C58="","",Investments_Import!C58) | J58: =IF(Investments_Import!D58="","",Investments_Import!D58) | K58: =IF($B58="","",$J58*1) | L58: =IF(Investments_Import!E58="","",Investments_Import!E58) | M58: =IF($L58="","",$L58*1) | N58: =IF(Investments_Import!F58="","",Investments_Import!F58) | O58: =IF($N58="","",$N58*1) | P58: =IF(Investments_Import!G58="","",Investments_Import!G58) | Q58: =IF(Investments_Import!H58="","",Investments_Import!H58) | R58: =IF($Q58="","",IF($Q58="USD",$P58,$P58*$J58)) | S58: =IF($R58="","",$R58*1) | U58: =IF(Mining_Import!A58="","",Mining_Import!A58) | V58: =IF(U58="","",U58*1) | W58: =V58 | X58: =IFERROR(INT($W58),"") | Y58: =$X58 | Z58: =IF(Mining_Import!B58="","",Mining_Import!B58) | AA58: =IF(Mining_Import!$C58="","",Mining_Import!$C58) | AB58: =IFERROR($AA58*1,"") | AC58: =IF($Y58>Dashboard!$Q$19,$AB58,"") | AD58: =IFERROR($AB58*$BU$19,"") | AE58: =IF(Mining_Import!D58="","",Mining_Import!D58) | AF58: =IF(Mining_Import!E58="","",Mining_Import!E58) | AG58: =IF(Mining_Import!F58="","",Mining_Import!F58) | AH58: =IF(Mining_Import!G58="","",Mining_Import!G58) | AI58: =IF(Mining_Import!H58="","",Mining_Import!H58) | AJ58: =IF(Mining_Import!I58="","",Mining_Import!I58) | BS58: =IF(Stock_Connector!B58="","",Stock_Connector!B58) | BT58: =IF(Stock_Connector!C58="","",Stock_Connector!C58) | BU58: =IF(Stock_Connector!C58="","",Stock_Connector!C58) | BV58: =IF(Stock_Connector!E58="","",Stock_Connector!E58) | BW58: =IF(Stock_Connector!D58="","",Stock_Connector!D58) | BY58: =Y58 | BZ58: =AB58 | CA58: =IFERROR(VLOOKUP($BY58,Account_Value!$C$2:$F$2500,4,0),"") | CB58: =IF(BZ58="","",BZ58*CA58) | CC58: =IF($BZ58="","",SUM($BZ$2:$BZ58)) | CD58: =IF($BZ58="","",$BU$19*(SUM($BZ$2:$BZ58)))
A59: =IF($B59="","",$A58+1) | B59: =IF(Investments_Import!A59="","",Investments_Import!A59) | C59: =IF(B59="","",B59*1) | D59: =$C59 | E59: =IF(Investments_Import!B59="","",Investments_Import!B59) | F59: =CONCATENATE(TEXT($D59,"dd-mmm-yyyy")," ",$E59) | G59: =IF($B59="","",COUNTIF($F$2:$F59,$F59)) | H59: =CONCATENATE(TEXT($D59,"dd-mmm-yyyy")," ",$E59," ",$G59) | I59: =IF(Investments_Import!C59="","",Investments_Import!C59) | J59: =IF(Investments_Import!D59="","",Investments_Import!D59) | K59: =IF($B59="","",$J59*1) | L59: =IF(Investments_Import!E59="","",Investments_Import!E59) | M59: =IF($L59="","",$L59*1) | N59: =IF(Investments_Import!F59="","",Investments_Import!F59) | O59: =IF($N59="","",$N59*1) | P59: =IF(Investments_Import!G59="","",Investments_Import!G59) | Q59: =IF(Investments_Import!H59="","",Investments_Import!H59) | R59: =IF($Q59="","",IF($Q59="USD",$P59,$P59*$J59)) | S59: =IF($R59="","",$R59*1) | U59: =IF(Mining_Import!A59="","",Mining_Import!A59) | V59: =IF(U59="","",U59*1) | W59: =V59 | X59: =IFERROR(INT($W59),"") | Y59: =$X59 | Z59: =IF(Mining_Import!B59="","",Mining_Import!B59) | AA59: =IF(Mining_Import!$C59="","",Mining_Import!$C59) | AB59: =IFERROR($AA59*1,"") | AC59: =IF($Y59>Dashboard!$Q$19,$AB59,"") | AD59: =IFERROR($AB59*$BU$19,"") | AE59: =IF(Mining_Import!D59="","",Mining_Import!D59) | AF59: =IF(Mining_Import!E59="","",Mining_Import!E59) | AG59: =IF(Mining_Import!F59="","",Mining_Import!F59) | AH59: =IF(Mining_Import!G59="","",Mining_Import!G59) | AI59: =IF(Mining_Import!H59="","",Mining_Import!H59) | AJ59: =IF(Mining_Import!I59="","",Mining_Import!I59) | BS59: =IF(Stock_Connector!B59="","",Stock_Connector!B59) | BT59: =IF(Stock_Connector!C59="","",Stock_Connector!C59) | BU59: =IF(Stock_Connector!C59="","",Stock_Connector!C59) | BV59: =IF(Stock_Connector!E59="","",Stock_Connector!E59) | BW59: =IF(Stock_Connector!D59="","",Stock_Connector!D59) | BY59: =Y59 | BZ59: =AB59 | CA59: =IFERROR(VLOOKUP($BY59,Account_Value!$C$2:$F$2500,4,0),"") | CB59: =IF(BZ59="","",BZ59*CA59) | CC59: =IF($BZ59="","",SUM($BZ$2:$BZ59)) | CD59: =IF($BZ59="","",$BU$19*(SUM($BZ$2:$BZ59)))
A60: =IF($B60="","",$A59+1) | B60: =IF(Investments_Import!A60="","",Investments_Import!A60) | C60: =IF(B60="","",B60*1) | D60: =$C60 | E60: =IF(Investments_Import!B60="","",Investments_Import!B60) | F60: =CONCATENATE(TEXT($D60,"dd-mmm-yyyy")," ",$E60) | G60: =IF($B60="","",COUNTIF($F$2:$F60,$F60)) | H60: =CONCATENATE(TEXT($D60,"dd-mmm-yyyy")," ",$E60," ",$G60) | I60: =IF(Investments_Import!C60="","",Investments_Import!C60) | J60: =IF(Investments_Import!D60="","",Investments_Import!D60) | K60: =IF($B60="","",$J60*1) | L60: =IF(Investments_Import!E60="","",Investments_Import!E60) | M60: =IF($L60="","",$L60*1) | N60: =IF(Investments_Import!F60="","",Investments_Import!F60) | O60: =IF($N60="","",$N60*1) | P60: =IF(Investments_Import!G60="","",Investments_Import!G60) | Q60: =IF(Investments_Import!H60="","",Investments_Import!H60) | R60: =IF($Q60="","",IF($Q60="USD",$P60,$P60*$J60)) | S60: =IF($R60="","",$R60*1) | U60: =IF(Mining_Import!A60="","",Mining_Import!A60) | V60: =IF(U60="","",U60*1) | W60: =V60 | X60: =IFERROR(INT($W60),"") | Y60: =$X60 | Z60: =IF(Mining_Import!B60="","",Mining_Import!B60) | AA60: =IF(Mining_Import!$C60="","",Mining_Import!$C60) | AB60: =IFERROR($AA60*1,"") | AC60: =IF($Y60>Dashboard!$Q$19,$AB60,"") | AD60: =IFERROR($AB60*$BU$19,"") | AE60: =IF(Mining_Import!D60="","",Mining_Import!D60) | AF60: =IF(Mining_Import!E60="","",Mining_Import!E60) | AG60: =IF(Mining_Import!F60="","",Mining_Import!F60) | AH60: =IF(Mining_Import!G60="","",Mining_Import!G60) | AI60: =IF(Mining_Import!H60="","",Mining_Import!H60) | AJ60: =IF(Mining_Import!I60="","",Mining_Import!I60) | BS60: =IF(Stock_Connector!B60="","",Stock_Connector!B60) | BT60: =IF(Stock_Connector!C60="","",Stock_Connector!C60) | BU60: =IF(Stock_Connector!C60="","",Stock_Connector!C60) | BV60: =IF(Stock_Connector!E60="","",Stock_Connector!E60) | BW60: =IF(Stock_Connector!D60="","",Stock_Connector!D60) | BY60: =Y60 | BZ60: =AB60 | CA60: =IFERROR(VLOOKUP($BY60,Account_Value!$C$2:$F$2500,4,0),"") | CB60: =IF(BZ60="","",BZ60*CA60) | CC60: =IF($BZ60="","",SUM($BZ$2:$BZ60)) | CD60: =IF($BZ60="","",$BU$19*(SUM($BZ$2:$BZ60)))
A61: =IF($B61="","",$A60+1) | B61: =IF(Investments_Import!A61="","",Investments_Import!A61) | C61: =IF(B61="","",B61*1) | D61: =$C61 | E61: =IF(Investments_Import!B61="","",Investments_Import!B61) | F61: =CONCATENATE(TEXT($D61,"dd-mmm-yyyy")," ",$E61) | G61: =IF($B61="","",COUNTIF($F$2:$F61,$F61)) | H61: =CONCATENATE(TEXT($D61,"dd-mmm-yyyy")," ",$E61," ",$G61) | I61: =IF(Investments_Import!C61="","",Investments_Import!C61) | J61: =IF(Investments_Import!D61="","",Investments_Import!D61) | K61: =IF($B61="","",$J61*1) | L61: =IF(Investments_Import!E61="","",Investments_Import!E61) | M61: =IF($L61="","",$L61*1) | N61: =IF(Investments_Import!F61="","",Investments_Import!F61) | O61: =IF($N61="","",$N61*1) | P61: =IF(Investments_Import!G61="","",Investments_Import!G61) | Q61: =IF(Investments_Import!H61="","",Investments_Import!H61) | R61: =IF($Q61="","",IF($Q61="USD",$P61,$P61*$J61)) | S61: =IF($R61="","",$R61*1) | U61: =IF(Mining_Import!A61="","",Mining_Import!A61) | V61: =IF(U61="","",U61*1) | W61: =V61 | X61: =IFERROR(INT($W61),"") | Y61: =$X61 | Z61: =IF(Mining_Import!B61="","",Mining_Import!B61) | AA61: =IF(Mining_Import!$C61="","",Mining_Import!$C61) | AB61: =IFERROR($AA61*1,"") | AC61: =IF($Y61>Dashboard!$Q$19,$AB61,"") | AD61: =IFERROR($AB61*$BU$19,"") | AE61: =IF(Mining_Import!D61="","",Mining_Import!D61) | AF61: =IF(Mining_Import!E61="","",Mining_Import!E61) | AG61: =IF(Mining_Import!F61="","",Mining_Import!F61) | AH61: =IF(Mining_Import!G61="","",Mining_Import!G61) | AI61: =IF(Mining_Import!H61="","",Mining_Import!H61) | AJ61: =IF(Mining_Import!I61="","",Mining_Import!I61) | BS61: =IF(Stock_Connector!B61="","",Stock_Connector!B61) | BT61: =IF(Stock_Connector!C61="","",Stock_Connector!C61) | BU61: =IF(Stock_Connector!C61="","",Stock_Connector!C61) | BV61: =IF(Stock_Connector!E61="","",Stock_Connector!E61) | BW61: =IF(Stock_Connector!D61="","",Stock_Connector!D61) | BY61: =Y61 | BZ61: =AB61 | CA61: =IFERROR(VLOOKUP($BY61,Account_Value!$C$2:$F$2500,4,0),"") | CB61: =IF(BZ61="","",BZ61*CA61) | CC61: =IF($BZ61="","",SUM($BZ$2:$BZ61)) | CD61: =IF($BZ61="","",$BU$19*(SUM($BZ$2:$BZ61)))
A62: =IF($B62="","",$A61+1) | B62: =IF(Investments_Import!A62="","",Investments_Import!A62) | C62: =IF(B62="","",B62*1) | D62: =$C62 | E62: =IF(Investments_Import!B62="","",Investments_Import!B62) | F62: =CONCATENATE(TEXT($D62,"dd-mmm-yyyy")," ",$E62) | G62: =IF($B62="","",COUNTIF($F$2:$F62,$F62)) | H62: =CONCATENATE(TEXT($D62,"dd-mmm-yyyy")," ",$E62," ",$G62) | I62: =IF(Investments_Import!C62="","",Investments_Import!C62) | J62: =IF(Investments_Import!D62="","",Investments_Import!D62) | K62: =IF($B62="","",$J62*1) | L62: =IF(Investments_Import!E62="","",Investments_Import!E62) | M62: =IF($L62="","",$L62*1) | N62: =IF(Investments_Import!F62="","",Investments_Import!F62) | O62: =IF($N62="","",$N62*1) | P62: =IF(Investments_Import!G62="","",Investments_Import!G62) | Q62: =IF(Investments_Import!H62="","",Investments_Import!H62) | R62: =IF($Q62="","",IF($Q62="USD",$P62,$P62*$J62)) | S62: =IF($R62="","",$R62*1) | U62: =IF(Mining_Import!A62="","",Mining_Import!A62) | V62: =IF(U62="","",U62*1) | W62: =V62 | X62: =IFERROR(INT($W62),"") | Y62: =$X62 | Z62: =IF(Mining_Import!B62="","",Mining_Import!B62) | AA62: =IF(Mining_Import!$C62="","",Mining_Import!$C62) | AB62: =IFERROR($AA62*1,"") | AC62: =IF($Y62>Dashboard!$Q$19,$AB62,"") | AD62: =IFERROR($AB62*$BU$19,"") | AE62: =IF(Mining_Import!D62="","",Mining_Import!D62) | AF62: =IF(Mining_Import!E62="","",Mining_Import!E62) | AG62: =IF(Mining_Import!F62="","",Mining_Import!F62) | AH62: =IF(Mining_Import!G62="","",Mining_Import!G62) | AI62: =IF(Mining_Import!H62="","",Mining_Import!H62) | AJ62: =IF(Mining_Import!I62="","",Mining_Import!I62) | BS62: =IF(Stock_Connector!B62="","",Stock_Connector!B62) | BT62: =IF(Stock_Connector!C62="","",Stock_Connector!C62) | BU62: =IF(Stock_Connector!C62="","",Stock_Connector!C62) | BV62: =IF(Stock_Connector!E62="","",Stock_Connector!E62) | BW62: =IF(Stock_Connector!D62="","",Stock_Connector!D62) | BY62: =Y62 | BZ62: =AB62 | CA62: =IFERROR(VLOOKUP($BY62,Account_Value!$C$2:$F$2500,4,0),"") | CB62: =IF(BZ62="","",BZ62*CA62) | CC62: =IF($BZ62="","",SUM($BZ$2:$BZ62)) | CD62: =IF($BZ62="","",$BU$19*(SUM($BZ$2:$BZ62)))
... A70: =IF($B70="","",$A69+1) | B70: =IF(Investments_Import!A70="","",Investments_Import!A70) | C70: =IF(B70="","",B70*1) | D70: =$C70 | E70: =IF(Investments_Import!B70="","",Investments_Import!B70) | F70: =CONCATENATE(TEXT($D70,"dd-mmm-yyyy")," ",$E70) | G70: =IF($B70="","",COUNTIF($F$2:$F70,$F70)) | H70: =CONCATENATE(TEXT($D70,"dd-mmm-yyyy")," ",$E70," ",$G70) | I70: =IF(Investments_Import!C70="","",Investments_Import!C70) | J70: =IF(Investments_Import!D70="","",Investments_Import!D70) | K70: =IF($B70="","",$J70*1) | L70: =IF(Investments_Import!E70="","",Investments_Import!E70) | M70: =IF($L70="","",$L70*1) | N70: =IF(Investments_Import!F70="","",Investments_Import!F70) | O70: =IF($N70="","",$N70*1) | P70: =IF(Investments_Import!G70="","",Investments_Import!G70) | Q70: =IF(Investments_Import!H70="","",Investments_Import!H70) | R70: =IF($Q70="","",IF($Q70="USD",$P70,$P70*$J70)) | S70: =IF($R70="","",$R70*1) | U70: =IF(Mining_Import!A70="","",Mining_Import!A70) | V70: =IF(U70="","",U70*1) | W70: =V70 | X70: =IFERROR(INT($W70),"") | Y70: =$X70 | Z70: =IF(Mining_Import!B70="","",Mining_Import!B70) | AA70: =IF(Mining_Import!$C70="","",Mining_Import!$C70) | AB70: =IFERROR($AA70*1,"") | AC70: =IF($Y70>Dashboard!$Q$19,$AB70,"") | AD70: =IFERROR($AB70*$BU$19,"") | AE70: =IF(Mining_Import!D70="","",Mining_Import!D70) | AF70: =IF(Mining_Import!E70="","",Mining_Import!E70) | AG70: =IF(Mining_Import!F70="","",Mining_Import!F70) | AH70: =IF(Mining_Import!G70="","",Mining_Import!G70) | AI70: =IF(Mining_Import!H70="","",Mining_Import!H70) | AJ70: =IF(Mining_Import!I70="","",Mining_Import!I70) | BS70: =IF(Stock_Connector!B70="","",Stock_Connector!B70) | BT70: =IF(Stock_Connector!C70="","",Stock_Connector!C70) | BU70: =IF(Stock_Connector!C70="","",Stock_Connector!C70) | BV70: =IF(Stock_Connector!E70="","",Stock_Connector!E70) | BW70: =IF(Stock_Connector!D70="","",Stock_Connector!D70) | BY70: =Y70 | BZ70: =AB70 | CA70: =IFERROR(VLOOKUP($BY70,Account_Value!$C$2:$F$2500,4,0),"") | CB70: =IF(BZ70="","",BZ70*CA70) | CC70: =IF($BZ70="","",SUM($BZ$2:$BZ70)) | CD70: =IF($BZ70="","",$BU$19*(SUM($BZ$2:$BZ70)))
A71: =IF($B71="","",$A70+1) | B71: =IF(Investments_Import!A71="","",Investments_Import!A71) | C71: =IF(B71="","",B71*1) | D71: =$C71 | E71: =IF(Investments_Import!B71="","",Investments_Import!B71) | F71: =CONCATENATE(TEXT($D71,"dd-mmm-yyyy")," ",$E71) | G71: =IF($B71="","",COUNTIF($F$2:$F71,$F71)) | H71: =CONCATENATE(TEXT($D71,"dd-mmm-yyyy")," ",$E71," ",$G71) | I71: =IF(Investments_Import!C71="","",Investments_Import!C71) | J71: =IF(Investments_Import!D71="","",Investments_Import!D71) | K71: =IF($B71="","",$J71*1) | L71: =IF(Investments_Import!E71="","",Investments_Import!E71) | M71: =IF($L71="","",$L71*1) | N71: =IF(Investments_Import!F71="","",Investments_Import!F71) | O71: =IF($N71="","",$N71*1) | P71: =IF(Investments_Import!G71="","",Investments_Import!G71) | Q71: =IF(Investments_Import!H71="","",Investments_Import!H71) | R71: =IF($Q71="","",IF($Q71="USD",$P71,$P71*$J71)) | S71: =IF($R71="","",$R71*1) | U71: =IF(Mining_Import!A71="","",Mining_Import!A71) | V71: =IF(U71="","",U71*1) | W71: =V71 | X71: =IFERROR(INT($W71),"") | Y71: =$X71 | Z71: =IF(Mining_Import!B71="","",Mining_Import!B71) | AA71: =IF(Mining_Import!$C71="","",Mining_Import!$C71) | AB71: =IFERROR($AA71*1,"") | AC71: =IF($Y71>Dashboard!$Q$19,$AB71,"") | AD71: =IFERROR($AB71*$BU$19,"") | AE71: =IF(Mining_Import!D71="","",Mining_Import!D71) | AF71: =IF(Mining_Import!E71="","",Mining_Import!E71) | AG71: =IF(Mining_Import!F71="","",Mining_Import!F71) | AH71: =IF(Mining_Import!G71="","",Mining_Import!G71) | AI71: =IF(Mining_Import!H71="","",Mining_Import!H71) | AJ71: =IF(Mining_Import!I71="","",Mining_Import!I71) | BY71: =Y71 | BZ71: =AB71 | CA71: =IFERROR(VLOOKUP($BY71,Account_Value!$C$2:$F$2500,4,0),"") | CB71: =IF(BZ71="","",BZ71*CA71) | CC71: =IF($BZ71="","",SUM($BZ$2:$BZ71)) | CD71: =IF($BZ71="","",$BU$19*(SUM($BZ$2:$BZ71)))
A72: =IF($B72="","",$A71+1) | B72: =IF(Investments_Import!A72="","",Investments_Import!A72) | C72: =IF(B72="","",B72*1) | D72: =$C72 | E72: =IF(Investments_Import!B72="","",Investments_Import!B72) | F72: =CONCATENATE(TEXT($D72,"dd-mmm-yyyy")," ",$E72) | G72: =IF($B72="","",COUNTIF($F$2:$F72,$F72)) | H72: =CONCATENATE(TEXT($D72,"dd-mmm-yyyy")," ",$E72," ",$G72) | I72: =IF(Investments_Import!C72="","",Investments_Import!C72) | J72: =IF(Investments_Import!D72="","",Investments_Import!D72) | K72: =IF($B72="","",$J72*1) | L72: =IF(Investments_Import!E72="","",Investments_Import!E72) | M72: =IF($L72="","",$L72*1) | N72: =IF(Investments_Import!F72="","",Investments_Import!F72) | O72: =IF($N72="","",$N72*1) | P72: =IF(Investments_Import!G72="","",Investments_Import!G72) | Q72: =IF(Investments_Import!H72="","",Investments_Import!H72) | R72: =IF($Q72="","",IF($Q72="USD",$P72,$P72*$J72)) | S72: =IF($R72="","",$R72*1) | U72: =IF(Mining_Import!A72="","",Mining_Import!A72) | V72: =IF(U72="","",U72*1) | W72: =V72 | X72: =IFERROR(INT($W72),"") | Y72: =$X72 | Z72: =IF(Mining_Import!B72="","",Mining_Import!B72) | AA72: =IF(Mining_Import!$C72="","",Mining_Import!$C72) | AB72: =IFERROR($AA72*1,"") | AC72: =IF($Y72>Dashboard!$Q$19,$AB72,"") | AD72: =IFERROR($AB72*$BU$19,"") | AE72: =IF(Mining_Import!D72="","",Mining_Import!D72) | AF72: =IF(Mining_Import!E72="","",Mining_Import!E72) | AG72: =IF(Mining_Import!F72="","",Mining_Import!F72) | AH72: =IF(Mining_Import!G72="","",Mining_Import!G72) | AI72: =IF(Mining_Import!H72="","",Mining_Import!H72) | AJ72: =IF(Mining_Import!I72="","",Mining_Import!I72) | BY72: =Y72 | BZ72: =AB72 | CA72: =IFERROR(VLOOKUP($BY72,Account_Value!$C$2:$F$2500,4,0),"") | CB72: =IF(BZ72="","",BZ72*CA72) | CC72: =IF($BZ72="","",SUM($BZ$2:$BZ72)) | CD72: =IF($BZ72="","",$BU$19*(SUM($BZ$2:$BZ72)))
A73: =IF($B73="","",$A72+1) | B73: =IF(Investments_Import!A73="","",Investments_Import!A73) | C73: =IF(B73="","",B73*1) | D73: =$C73 | E73: =IF(Investments_Import!B73="","",Investments_Import!B73) | F73: =CONCATENATE(TEXT($D73,"dd-mmm-yyyy")," ",$E73) | G73: =IF($B73="","",COUNTIF($F$2:$F73,$F73)) | H73: =CONCATENATE(TEXT($D73,"dd-mmm-yyyy")," ",$E73," ",$G73) | I73: =IF(Investments_Import!C73="","",Investments_Import!C73) | J73: =IF(Investments_Import!D73="","",Investments_Import!D73) | K73: =IF($B73="","",$J73*1) | L73: =IF(Investments_Import!E73="","",Investments_Import!E73) | M73: =IF($L73="","",$L73*1) | N73: =IF(Investments_Import!F73="","",Investments_Import!F73) | O73: =IF($N73="","",$N73*1) | P73: =IF(Investments_Import!G73="","",Investments_Import!G73) | Q73: =IF(Investments_Import!H73="","",Investments_Import!H73) | R73: =IF($Q73="","",IF($Q73="USD",$P73,$P73*$J73)) | S73: =IF($R73="","",$R73*1) | U73: =IF(Mining_Import!A73="","",Mining_Import!A73) | V73: =IF(U73="","",U73*1) | W73: =V73 | X73: =IFERROR(INT($W73),"") | Y73: =$X73 | Z73: =IF(Mining_Import!B73="","",Mining_Import!B73) | AA73: =IF(Mining_Import!$C73="","",Mining_Import!$C73) | AB73: =IFERROR($AA73*1,"") | AC73: =IF($Y73>Dashboard!$Q$19,$AB73,"") | AD73: =IFERROR($AB73*$BU$19,"") | AE73: =IF(Mining_Import!D73="","",Mining_Import!D73) | AF73: =IF(Mining_Import!E73="","",Mining_Import!E73) | AG73: =IF(Mining_Import!F73="","",Mining_Import!F73) | AH73: =IF(Mining_Import!G73="","",Mining_Import!G73) | AI73: =IF(Mining_Import!H73="","",Mining_Import!H73) | AJ73: =IF(Mining_Import!I73="","",Mining_Import!I73) | BY73: =Y73 | BZ73: =AB73 | CA73: =IFERROR(VLOOKUP($BY73,Account_Value!$C$2:$F$2500,4,0),"") | CB73: =IF(BZ73="","",BZ73*CA73) | CC73: =IF($BZ73="","",SUM($BZ$2:$BZ73)) | CD73: =IF($BZ73="","",$BU$19*(SUM($BZ$2:$BZ73)))
A74: =IF($B74="","",$A73+1) | B74: =IF(Investments_Import!A74="","",Investments_Import!A74) | C74: =IF(B74="","",B74*1) | D74: =$C74 | E74: =IF(Investments_Import!B74="","",Investments_Import!B74) | F74: =CONCATENATE(TEXT($D74,"dd-mmm-yyyy")," ",$E74) | G74: =IF($B74="","",COUNTIF($F$2:$F74,$F74)) | H74: =CONCATENATE(TEXT($D74,"dd-mmm-yyyy")," ",$E74," ",$G74) | I74: =IF(Investments_Import!C74="","",Investments_Import!C74) | J74: =IF(Investments_Import!D74="","",Investments_Import!D74) | K74: =IF($B74="","",$J74*1) | L74: =IF(Investments_Import!E74="","",Investments_Import!E74) | M74: =IF($L74="","",$L74*1) | N74: =IF(Investments_Import!F74="","",Investments_Import!F74) | O74: =IF($N74="","",$N74*1) | P74: =IF(Investments_Import!G74="","",Investments_Import!G74) | Q74: =IF(Investments_Import!H74="","",Investments_Import!H74) | R74: =IF($Q74="","",IF($Q74="USD",$P74,$P74*$J74)) | S74: =IF($R74="","",$R74*1) | U74: =IF(Mining_Import!A74="","",Mining_Import!A74) | V74: =IF(U74="","",U74*1) | W74: =V74 | X74: =IFERROR(INT($W74),"") | Y74: =$X74 | Z74: =IF(Mining_Import!B74="","",Mining_Import!B74) | AA74: =IF(Mining_Import!$C74="","",Mining_Import!$C74) | AB74: =IFERROR($AA74*1,"") | AC74: =IF($Y74>Dashboard!$Q$19,$AB74,"") | AD74: =IFERROR($AB74*$BU$19,"") | AE74: =IF(Mining_Import!D74="","",Mining_Import!D74) | AF74: =IF(Mining_Import!E74="","",Mining_Import!E74) | AG74: =IF(Mining_Import!F74="","",Mining_Import!F74) | AH74: =IF(Mining_Import!G74="","",Mining_Import!G74) | AI74: =IF(Mining_Import!H74="","",Mining_Import!H74) | AJ74: =IF(Mining_Import!I74="","",Mining_Import!I74) | BY74: =Y74 | BZ74: =AB74 | CA74: =IFERROR(VLOOKUP($BY74,Account_Value!$C$2:$F$2500,4,0),"") | CB74: =IF(BZ74="","",BZ74*CA74) | CC74: =IF($BZ74="","",SUM($BZ$2:$BZ74)) | CD74: =IF($BZ74="","",$BU$19*(SUM($BZ$2:$BZ74)))
